Workbook
Name wDiscountWeight: '09_KPI_StoreScore'!$B$9
Name wGrowthWeight: '09_KPI_StoreScore'!$B$10
Name wMarginWeight: '09_KPI_StoreScore'!$B$6
Name wReturnWeight: '09_KPI_StoreScore'!$B$8
Name wTrendWeight: '09_KPI_StoreScore'!$B$7

Sheet 00_Cover_ReadMe
B2: NOVA RETAIL — MIS REPORTING SYSTEM
B3: Profitability Monitoring, Margin Volatility & Performance Diagnostic
B6: Business Problem
B7: Nova Retail's leadership lacks a centralized, consistent MIS system to identify where profitability is unstable across regions, stores, categories, returns, and promotions.
B9: Scope & Data Source
B10: Source: Nova Retail ERP dataset (15 tables, Jan 2021 - Dec 2024, verified zero orphan keys). This workbook is built entirely from that dataset. No figures are estimated, assumed, or fabricated.
B12: How This Workbook Is Built
B13: Model_ sheets = cleaned and aggregated reporting layer produced from the ERP data.*
B14: KPI_* sheets = Business logic layer. Every cell is a live formula referencing Model_* tables (SUMIFS / INDEX-MATCH / LET). No hardcoded numbers.
B15: Report_* sheets = Aggregated views + native charts answering each locked business question.
B16: Dashboard = Executive reporting layer; KPI values and visuals are linked to calculated data, with no manually typed business numbers.
B17: Insights = Formula-generated sentences, built from live KPI cells.
... B31: No inventory/warehouse table, no freight/logistics cost, no supplier lead-time data, no employee cost data, no store-level sales target exists in source data.

Sheet 01_Model_Overall_Month
A3: year | B3: month | C3: ym | D3: revenue | E3: cost | F3: orders | G3: margin | H3: margin_pct
A4: 2021 | B4: 1 | C4: 2021-01 | D4: 196258182 | E4: 1.775816e+08 | F4: 3043 | G4: 18676578 | H4: 0.0952
A5: 2021 | B5: 2 | C5: 2021-02 | D5: 178833814 | E5: 1.5661328e+08 | F5: 2736 | G5: 22220536 | H5: 0.1243
A6: 2021 | B6: 3 | C6: 2021-03 | D6: 215985173 | E6: 1.8131914e+08 | F6: 3081 | G6: 34666032 | H6: 0.1605
A7: 2021 | B7: 4 | C7: 2021-04 | D7: 222112137 | E7: 1.9532314e+08 | F7: 3305 | G7: 26788996 | H7: 0.1206
A8: 2021 | B8: 5 | C8: 2021-05 | D8: 249111988 | E8: 2.1764874e+08 | F8: 3746 | G8: 31463253 | H8: 0.1263
A9: 2021 | B9: 6 | C9: 2021-06 | D9: 232257296 | E9: 2.0256513e+08 | F9: 3505 | G9: 29692161 | H9: 0.1278
A10: 2021 | B10: 7 | C10: 2021-07 | D10: 219645765 | E10: 1.9300395e+08 | F10: 3378 | G10: 26641819 | H10: 0.1213
A11: 2021 | B11: 8 | C11: 2021-08 | D11: 243118909 | E11: 2.0546319e+08 | F11: 3448 | G11: 37655723 | H11: 0.1549
A12: 2021 | B12: 9 | C12: 2021-09 | D12: 238960088 | E12: 2.0778255e+08 | F12: 3625 | G12: 31177540 | H12: 0.1305
A13: 2021 | B13: 10 | C13: 2021-10 | D13: 351828947 | E13: 2.9714688e+08 | F13: 5074 | G13: 54682070 | H13: 0.1554
A14: 2021 | B14: 11 | C14: 2021-11 | D14: 342872940 | E14: 2.8375449e+08 | F14: 4967 | G14: 59118451 | H14: 0.1724
A15: 2021 | B15: 12 | C15: 2021-12 | D15: 341260894 | E15: 2.8675124e+08 | F15: 4787 | G15: 54509659 | H15: 0.1597
... A51: 2024 | B51: 12 | C51: 2024-12 | D51: 700106315 | E51: 5.6078178e+08 | F51: 9569 | G51: 1.3932454e+08 | H51: 0.199

Sheet 01_Model_Region_Month
A1: 01_Model_Region_Month — ETL output (materialized). Source: Power Query joins documented in PowerQuery_DAX_Specification.md
A3: region_id | B3: region_name | C3: zone | D3: year | E3: month | F3: ym | G3: revenue | H3: cost | I3: orders | J3: margin | K3: margin_pct | L3: target_amount | M3: achievement_pct
A4: 1 | B4: Delhi NCR | C4: North | D4: 2021 | E4: 1 | F4: 2021-01 | G4: 12380981 | H4: 11087564 | I4: 213 | J4: 1293417.3 | K4: 0.1045 | L4: 10697000 | M4: 1.1574
A5: 1 | B5: Delhi NCR | C5: North | D5: 2021 | E5: 2 | F5: 2021-02 | G5: 10959141 | H5: 9670859.7 | I5: 174 | J5: 1288281.3 | K5: 0.1176 | L5: 9457000 | M5: 1.1588
A6: 1 | B6: Delhi NCR | C6: North | D6: 2021 | E6: 3 | F6: 2021-03 | G6: 15822191 | H6: 13111980 | I6: 208 | J6: 2710210.7 | K6: 0.1713 | L6: 13587000 | M6: 1.1645
A7: 1 | B7: Delhi NCR | C7: North | D7: 2021 | E7: 4 | F7: 2021-04 | G7: 16070756 | H7: 14418970 | I7: 245 | J7: 1651785.9 | K7: 0.1028 | L7: 13088000 | M7: 1.2279
A8: 1 | B8: Delhi NCR | C8: North | D8: 2021 | E8: 5 | F8: 2021-05 | G8: 18356840 | H8: 15878881 | I8: 270 | J8: 2477959.3 | K8: 0.135 | L8: 16709000 | M8: 1.0986
A9: 1 | B9: Delhi NCR | C9: North | D9: 2021 | E9: 6 | F9: 2021-06 | G9: 13950991 | H9: 12055818 | I9: 241 | J9: 1895172.6 | K9: 0.1358 | L9: 12129000 | M9: 1.1502
A10: 1 | B10: Delhi NCR | C10: North | D10: 2021 | E10: 7 | F10: 2021-07 | G10: 16941381 | H10: 14926802 | I10: 256 | J10: 2014578.9 | K10: 0.1189 | L10: 14875000 | M10: 1.1389
A11: 1 | B11: Delhi NCR | C11: North | D11: 2021 | E11: 8 | F11: 2021-08 | G11: 16036560 | H11: 13628002 | I11: 250 | J11: 2408558.2 | K11: 0.1502 | L11: 13400000 | M11: 1.1968
A12: 1 | B12: Delhi NCR | C12: North | D12: 2021 | E12: 9 | F12: 2021-09 | G12: 15839935 | H12: 13850584 | I12: 242 | J12: 1989351.1 | K12: 0.1256 | L12: 13365000 | M12: 1.1852
A13: 1 | B13: Delhi NCR | C13: North | D13: 2021 | E13: 10 | F13: 2021-10 | G13: 24202697 | H13: 20462867 | I13: 350 | J13: 3739830.1 | K13: 0.1545 | L13: 22084000 | M13: 1.0959
A14: 1 | B14: Delhi NCR | C14: North | D14: 2021 | E14: 11 | F14: 2021-11 | G14: 23510204 | H14: 19398145 | I14: 357 | J14: 4112059 | K14: 0.1749 | L14: 19722000 | M14: 1.1921
A15: 1 | B15: Delhi NCR | C15: North | D15: 2021 | E15: 12 | F15: 2021-12 | G15: 27045888 | H15: 22680534 | I15: 346 | J15: 4365353.6 | K15: 0.1614 | L15: 22318000 | M15: 1.2118
... A579: 9 | B579: West Bengal | C579: East | D579: 2024 | E579: 12 | F579: 2024-12 | G579: 102763407 | H579: 82395550 | I579: 1401 | J579: 20367857 | K579: 0.1982 | L579: 90056000 | M579: 1.1411

Sheet 01_Model_Store_Month
A1: 01_Model_Store_Month — ETL output (materialized). Source: Power Query joins documented in PowerQuery_DAX_Specification.md
A3: store_id | B3: store_name | C3: region_id | D3: region_name | E3: year | F3: month | G3: ym | H3: revenue | I3: cost | J3: orders | K3: discount_leak | L3: catalog_value | M3: margin | N3: margin_pct | O3: return_count | P3: refund_amount
A4: 82 | B4: Nova Retail - Ahmedabad Flagship | C4: 4 | D4: Gujarat | E4: 2021 | F4: 1 | G4: 2021-01 | H4: 4451189 | I4: 4074748.1 | J4: 79 | K4: 826353 | L4: 5268320 | M4: 376440.92 | N4: 0.0846 | O4: 4 | P4: 86498
A5: 82 | B5: Nova Retail - Ahmedabad Flagship | C5: 4 | D5: Gujarat | E5: 2021 | F5: 2 | G5: 2021-02 | H5: 4971793 | I5: 4327551.4 | J5: 88 | K5: 610040 | L5: 5560190 | M5: 644241.56 | N5: 0.1296 | O5: 5 | P5: 173374
A6: 82 | B6: Nova Retail - Ahmedabad Flagship | C6: 4 | D6: Gujarat | E6: 2021 | F6: 3 | G6: 2021-03 | H6: 5640965 | I6: 4593880.5 | J6: 68 | K6: 303127 | L6: 5919100 | M6: 1047084.5 | N6: 0.1856 | O6: 2 | P6: 7560
A7: 82 | B7: Nova Retail - Ahmedabad Flagship | C7: 4 | D7: Gujarat | E7: 2021 | F7: 4 | G7: 2021-04 | H7: 5911953 | I7: 5071904 | J7: 94 | K7: 608849 | L7: 6503760 | M7: 840049.03 | N7: 0.1421 | O7: 7 | P7: 174962
A8: 82 | B8: Nova Retail - Ahmedabad Flagship | C8: 4 | D8: Gujarat | E8: 2021 | F8: 5 | G8: 2021-05 | H8: 5659236 | I8: 5081764.6 | J8: 90 | K8: 846908 | L8: 6478060 | M8: 577471.41 | N8: 0.102 | O8: 11 | P8: 292299
A9: 82 | B9: Nova Retail - Ahmedabad Flagship | C9: 4 | D9: Gujarat | E9: 2021 | F9: 6 | G9: 2021-06 | H9: 6963757 | I9: 6069429.2 | J9: 111 | K9: 754315 | L9: 7699210 | M9: 894327.85 | N9: 0.1284 | O9: 2 | P9: 57497
A10: 82 | B10: Nova Retail - Ahmedabad Flagship | C10: 4 | D10: Gujarat | E10: 2021 | F10: 7 | G10: 2021-07 | H10: 6995955 | I10: 6004837.7 | J10: 96 | K10: 773574 | L10: 7748250 | M10: 991117.34 | N10: 0.1417 | O10: 8 | P10: 485994
A11: 82 | B11: Nova Retail - Ahmedabad Flagship | C11: 4 | D11: Gujarat | E11: 2021 | F11: 8 | G11: 2021-08 | H11: 6693632 | I11: 5829583.8 | J11: 97 | K11: 759863 | L11: 7431370 | M11: 864048.23 | N11: 0.1291 | O11: 8 | P11: 222499
A12: 82 | B12: Nova Retail - Ahmedabad Flagship | C12: 4 | D12: Gujarat | E12: 2021 | F12: 9 | G12: 2021-09 | H12: 6657458 | I12: 5866035.6 | J12: 99 | K12: 917483 | L12: 7561620 | M12: 791422.39 | N12: 0.1189 | O12: 15 | P12: 153855
A13: 82 | B13: Nova Retail - Ahmedabad Flagship | C13: 4 | D13: Gujarat | E13: 2021 | F13: 10 | G13: 2021-10 | H13: 9008786 | I13: 7619380 | J13: 121 | K13: 641819 | L13: 9618710 | M13: 1389406 | N13: 0.1542 | O13: 9 | P13: 314728
A14: 82 | B14: Nova Retail - Ahmedabad Flagship | C14: 4 | D14: Gujarat | E14: 2021 | F14: 11 | G14: 2021-11 | H14: 9076033 | I14: 7614981.2 | J14: 138 | K14: 731062 | L14: 9785670 | M14: 1461051.8 | N14: 0.161 | O14: 8 | P14: 321018
A15: 82 | B15: Nova Retail - Ahmedabad Flagship | C15: 4 | D15: Gujarat | E15: 2021 | F15: 12 | G15: 2021-12 | H15: 10251721 | I15: 8574234 | J15: 142 | K15: 803057 | L15: 11019830 | M15: 1677487 | N15: 0.1636 | O15: 10 | P15: 239266
... A5762: 40 | B5762: Nova Retail - Warangal Standard | C5762: 7 | D5762: Telangana-AP | E5762: 2024 | F5762: 12 | G5762: 2024-12 | H5762: 3816993 | I5762: 3129538.7 | J5762: 51 | K5762: 119382 | L5762: 3926190 | M5762: 687454.32 | N5762: 0.1801 | O5762: 3 | P5762: 13931

Sheet 01_Model_Store_Score
A1: 01_Model_Store_Score — ETL output (materialized). Source: Power Query joins documented in PowerQuery_DAX_Specification.md
A3: store_id | B3: store_name | C3: region_id | D3: region_name | E3: revenue_last6 | F3: cost_last6 | G3: discount_leak_last6 | H3: catalog_value_last6 | I3: order_count_last6 | J3: lines_last6 | K3: margin_last6 | L3: margin_pct_last6 | M3: discount_leak_pct_last6 | N3: revenue_prior6 | O3: cost_prior6 | P3: discount_leak_prior6 | Q3: catalog_value_prior6 | R3: order_count_prior6 | S3: lines_prior6 | T3: margin_prior6 | U3: margin_pct_prior6 | V3: discount_leak_pct_prior6 | W3: return_rate_last6 | X3: revenue_growth_pct | Y3: margin_trend_pp
A4: 82 | B4: Nova Retail - Ahmedabad Flagship | C4: 4 | D4: Gujarat | E4: 101854767 | F4: 83518150 | G4: 5903840 | H4: 107393300 | I4: 1433 | J4: 3180 | K4: 18336617 | L4: 0.18 | M4: 0.055 | N4: 68384180 | O4: 58998120 | P4: 7842824 | Q4: 75943640 | R4: 1105 | S4: 2392 | T4: 9386059.9 | U4: 0.1373 | V4: 0.1033 | W4: 0.0343 | X4: 0.4894 | Y4: 0.04
A5: 42 | B5: Nova Retail - Ahmedabad Standard | C5: 4 | D5: Gujarat | E5: 23674489 | F5: 19305903 | G5: 1430237 | H5: 25027930 | I5: 330 | J5: 761 | K5: 4368586.3 | L5: 0.1845 | M5: 0.0571 | N5: 17251617 | O5: 15170081 | P5: 2132533 | Q5: 19324710 | R5: 253 | S5: 553 | T5: 2081536.4 | U5: 0.1207 | V5: 0.1104 | W5: 0.0342 | X5: 0.3723 | Y5: 0.06
A6: 33 | B6: Nova Retail - Amritsar Compact | C6: 2 | D6: Punjab-Haryana | E6: 8773684 | F6: 7092388.6 | G6: 501149 | H6: 9240140 | I6: 143 | J6: 310 | K6: 1681295.4 | L6: 0.1916 | M6: 0.0542 | N6: 6958758 | O6: 6123577.2 | P6: 894536 | Q6: 7844010 | R6: 106 | S6: 247 | T6: 835180.79 | U6: 0.12 | V6: 0.114 | W6: 0.0484 | X6: 0.2608 | Y6: 0.07
A7: 105 | B7: Nova Retail - Amritsar Compact | C7: 2 | D7: Punjab-Haryana | E7: 18980924 | F7: 15405472 | G7: 906444 | H7: 19785650 | I7: 297 | J7: 644 | K7: 3575451.6 | L7: 0.1884 | M7: 0.0458 | N7: 14960019 | O7: 12854057 | P7: 1647468 | Q7: 16542910 | R7: 225 | S7: 494 | T7: 2105961.7 | U7: 0.1408 | V7: 0.0996 | W7: 0.0248 | X7: 0.2688 | Y7: 0.05
A8: 3 | B8: Nova Retail - Amritsar Flagship | C8: 2 | D8: Punjab-Haryana | E8: 34867529 | F8: 28562230 | G8: 2192997 | H8: 36961930 | I8: 482 | J8: 1072 | K8: 6305299.3 | L8: 0.1808 | M8: 0.0593 | N8: 26569033 | O8: 22786936 | P8: 2874276 | Q8: 29364600 | R8: 401 | S8: 858 | T8: 3782096.8 | U8: 0.1423 | V8: 0.0979 | W8: 0.0345 | X8: 0.3123 | Y8: 0.04
A9: 60 | B9: Nova Retail - Amritsar Standard | C9: 2 | D9: Punjab-Haryana | E9: 13824310 | F9: 11324838 | G9: 844619 | H9: 14625540 | I9: 213 | J9: 480 | K9: 2499471.9 | L9: 0.1808 | M9: 0.0577 | N9: 12195516 | O9: 10147357 | P9: 997981 | Q9: 13150730 | R9: 173 | S9: 387 | T9: 2048159.1 | U9: 0.1679 | V9: 0.0759 | W9: 0.0333 | X9: 0.1336 | Y9: 0.01
A10: 72 | B10: Nova Retail - Amritsar Standard | C10: 2 | D10: Punjab-Haryana | E10: 16754805 | F10: 13740100 | G10: 1061112 | H10: 17747390 | I10: 222 | J10: 500 | K10: 3014704.7 | L10: 0.1799 | M10: 0.0598 | N10: 11483018 | O10: 10050421 | P10: 1409173 | Q10: 12861630 | R10: 173 | S10: 358 | T10: 1432597.3 | U10: 0.1248 | V10: 0.1096 | W10: 0.036 | X10: 0.4591 | Y10: 0.06
A11: 7 | B11: Nova Retail - Bengaluru Compact | C11: 5 | D11: Karnataka | E11: 19550260 | F11: 15947157 | G11: 1066155 | H11: 20556530 | I11: 293 | J11: 638 | K11: 3603103.2 | L11: 0.1843 | M11: 0.0519 | N11: 15020882 | O11: 12834763 | P11: 1619194 | Q11: 16596250 | R11: 224 | S11: 515 | T11: 2186118.8 | U11: 0.1455 | V11: 0.0976 | W11: 0.0266 | X11: 0.3015 | Y11: 0.04
A12: 68 | B12: Nova Retail - Bengaluru Standard | C12: 5 | D12: Karnataka | E12: 36935554 | F12: 30517359 | G12: 2375158 | H12: 39195260 | I12: 502 | J12: 1083 | K12: 6418194.6 | L12: 0.1738 | M12: 0.0606 | N12: 27064300 | O12: 23247125 | P12: 3042016 | Q12: 30017640 | R12: 394 | S12: 888 | T12: 3817175.1 | U12: 0.141 | V12: 0.1013 | W12: 0.0305 | X12: 0.3647 | Y12: 0.03
A13: 98 | B13: Nova Retail - Bengaluru Standard | C13: 5 | D13: Karnataka | E13: 73810081 | F13: 60735367 | G13: 4594132 | H13: 78187120 | I13: 1029 | J13: 2283 | K13: 13074714 | L13: 0.1771 | M13: 0.0588 | N13: 56795916 | O13: 48979436 | P13: 6495680 | Q13: 63110730 | R13: 794 | S13: 1771 | T13: 7816480.2 | U13: 0.1376 | V13: 0.1029 | W13: 0.0385 | X13: 0.2996 | Y13: 0.04
A14: 90 | B14: Nova Retail - Bhopal Standard | C14: 11 | D14: Madhya Pradesh | E14: 15836198 | F14: 13039316 | G14: 895046 | H14: 16667180 | I14: 217 | J14: 486 | K14: 2796882.3 | L14: 0.1766 | M14: 0.0537 | N14: 8309214 | O14: 7084729.7 | P14: 861467 | Q14: 9136840 | R14: 147 | S14: 321 | T14: 1224484.3 | U14: 0.1474 | V14: 0.0943 | W14: 0.0226 | X14: 0.9059 | Y14: 0.03
A15: 20 | B15: Nova Retail - Bhubaneswar Standard | C15: 10 | D15: Odisha-Jharkhand | E15: 36652982 | F15: 30274627 | G15: 2341872 | H15: 38903040 | I15: 481 | J15: 1089 | K15: 6378355 | L15: 0.174 | M15: 0.0602 | N15: 24079752 | O15: 20850556 | P15: 2802787 | Q15: 26783760 | R15: 352 | S15: 770 | T15: 3229196.1 | U15: 0.1341 | V15: 0.1046 | W15: 0.0349 | X15: 0.5221 | Y15: 0.04
... A123: 40 | B123: Nova Retail - Warangal Standard | C123: 7 | D123: Telangana-AP | E123: 16126760 | F123: 13532496 | G123: 1187337 | H123: 17266820 | I123: 235 | J123: 499 | K123: 2594264.4 | L123: 0.1609 | M123: 0.0688 | N123: 9924161 | O123: 8440025.4 | P123: 1134022 | Q123: 11021690 | R123: 183 | S123: 385 | T123: 1484135.6 | U123: 0.1495 | V123: 0.1029 | W123: 0.022 | X123: 0.625 | Y123: 0.01

Sheet 01_Model_Category
A1: 01_Model_Category — ETL output (materialized). Source: Power Query joins documented in PowerQuery_DAX_Specification.md
A3: category_id | B3: category_name | C3: category_group | D3: revenue | E3: cost | F3: discount_leak | G3: catalog_value | H3: lines | I3: margin | J3: margin_pct | K3: discount_leak_pct | L3: return_count | M3: refund_amount | N3: return_rate | O3: revenue_share
A4: 6 | B4: Refrigerators | C4: Appliances | D4: 4382590644 | E4: 3.8491109e+09 | F4: 477412556 | G4: 4845220420 | H4: 60041 | I4: 5.3347975e+08 | J4: 0.1217 | K4: 0.0985 | L4: 2129 | M4: 139694518 | N4: 0.0355 | O4: 0.2321
A5: 2 | B5: Laptops & Computers | C5: Electronics | D5: 2977044772 | E5: 2.8067264e+09 | F5: 327405596 | G5: 3294481190 | H5: 23849 | I5: 1.7031837e+08 | J5: 0.0572 | K5: 0.0994 | L5: 1108 | M5: 120142131 | N5: 0.0465 | O5: 0.1577
A6: 3 | B6: Televisions | C6: Electronics | D6: 2296118310 | E6: 2.0218053e+09 | F6: 250368359 | G6: 2538567220 | H6: 38075 | I6: 2.7431298e+08 | J6: 0.1195 | K6: 0.0986 | L6: 1575 | M6: 88979549 | N6: 0.0414 | O6: 0.1216
A7: 14 | B7: Furniture | C7: Home & Living | D7: 1907350207 | E7: 1.6011459e+09 | F7: 209518887 | G7: 2110496580 | H7: 36122 | I7: 3.0620428e+08 | J7: 0.1605 | K7: 0.0993 | L7: 1131 | M7: 59141680 | N7: 0.0313 | O7: 0.101
A8: 1 | B8: Mobiles & Accessories | C8: Electronics | D8: 1718375549 | E8: 1.512548e+09 | F8: 186700048 | G8: 1899178170 | H8: 30469 | I8: 2.0582759e+08 | J8: 0.1198 | K8: 0.0983 | L8: 1326 | M8: 69832084 | N8: 0.0435 | O8: 0.091
A9: 5 | B9: Air Conditioners & Coolers | C9: Appliances | D9: 1462422495 | E9: 1.3095052e+09 | F9: 161801886 | G9: 1619237220 | H9: 20282 | I9: 1.5291731e+08 | J9: 0.1046 | K9: 0.0999 | L9: 730 | M9: 47019318 | N9: 0.036 | O9: 0.0775
A10: 7 | B10: Washing Machines | C10: Appliances | D10: 1242288851 | E10: 1.0986735e+09 | F10: 134651075 | G10: 1372667370 | H10: 20087 | I10: 1.4361536e+08 | J10: 0.1156 | K10: 0.0981 | L10: 682 | M10: 39892561 | N10: 0.034 | O10: 0.0658
A11: 8 | B11: Kitchen Appliances | C11: Appliances | D11: 602723939 | E11: 4.3512172e+08 | F11: 65733883 | G11: 666395200 | H11: 36206 | I11: 1.6760222e+08 | J11: 0.2781 | K11: 0.0986 | L11: 1037 | M11: 16974845 | N11: 0.0286 | O11: 0.0319
A12: 4 | B12: Home Audio | C12: Electronics | D12: 520527346 | E12: 4.2355083e+08 | F12: 56856404 | G12: 575620000 | H12: 28038 | I12: 96976521 | J12: 0.1863 | K12: 0.0988 | L12: 1084 | M12: 18808093 | N12: 0.0387 | O12: 0.0276
A13: 9 | B13: Heaters & Winter Appliances | C13: Appliances | D13: 258134495 | E13: 1.9102397e+08 | F13: 28051708 | G13: 285298830 | H13: 26198 | I13: 67110525 | J13: 0.26 | K13: 0.0983 | L13: 703 | M13: 6392296 | N13: 0.0268 | O13: 0.0137
A14: 13 | B14: Footwear | C14: Apparel | D14: 218483178 | E14: 1.4561926e+08 | F14: 24009501 | G14: 241743290 | H14: 25921 | I14: 72863913 | J14: 0.3335 | K14: 0.0993 | L14: 1751 | M14: 12659306 | N14: 0.0676 | O14: 0.0116
A15: 20 | B15: Festive & Gifting | C15: Seasonal | D15: 216122731 | E15: 1.4100408e+08 | F15: 23569987 | G15: 238954570 | H15: 41399 | I15: 75118653 | J15: 0.3476 | K15: 0.0986 | L15: 1238 | M15: 6073270 | N15: 0.0299 | O15: 0.0114
... A23: 17 | B23: Groceries & Staples | C23: Grocery | D23: 45075426 | E23: 41114892 | F23: 4946330 | G23: 49867370 | H23: 32688 | I23: 3960534.1 | J23: 0.0879 | K23: 0.0992 | L23: 244 | M23: 278695 | N23: 0.0075 | O23: 0.0024

Sheet 01_Model_Category_Month
A1: 01_Model_Category_Month — ETL output (materialized). Source: Power Query joins documented in PowerQuery_DAX_Specification.md
A3: category_id | B3: category_name | C3: ym | D3: year | E3: month | F3: revenue | G3: cost | H3: margin_pct
A4: 1 | B4: Mobiles & Accessories | C4: 2021-01 | D4: 2021 | E4: 1 | F4: 17107104 | G4: 15684713 | H4: 0.0831
A5: 1 | B5: Mobiles & Accessories | C5: 2021-02 | D5: 2021 | E5: 2 | F5: 16014997 | G5: 14223241 | H5: 0.1119
A6: 1 | B6: Mobiles & Accessories | C6: 2021-03 | D6: 2021 | E6: 3 | F6: 18291486 | G6: 15624253 | H6: 0.1458
A7: 1 | B7: Mobiles & Accessories | C7: 2021-04 | D7: 2021 | E7: 4 | F7: 18638974 | G7: 16829238 | H7: 0.0971
A8: 1 | B8: Mobiles & Accessories | C8: 2021-05 | D8: 2021 | E8: 5 | F8: 21969464 | G8: 19467092 | H8: 0.1139
A9: 1 | B9: Mobiles & Accessories | C9: 2021-06 | D9: 2021 | E9: 6 | F9: 21149075 | G9: 19093382 | H9: 0.0972
A10: 1 | B10: Mobiles & Accessories | C10: 2021-07 | D10: 2021 | E10: 7 | F10: 20971192 | G10: 18804495 | H10: 0.1033
A11: 1 | B11: Mobiles & Accessories | C11: 2021-08 | D11: 2021 | E11: 8 | F11: 21807094 | G11: 18694725 | H11: 0.1427
A12: 1 | B12: Mobiles & Accessories | C12: 2021-09 | D12: 2021 | E12: 9 | F12: 22562520 | G12: 20072668 | H12: 0.1104
A13: 1 | B13: Mobiles & Accessories | C13: 2021-10 | D13: 2021 | E13: 10 | F13: 33204464 | G13: 28787595 | H13: 0.133
A14: 1 | B14: Mobiles & Accessories | C14: 2021-11 | D14: 2021 | E14: 11 | F14: 33878499 | G14: 28688733 | H14: 0.1532
A15: 1 | B15: Mobiles & Accessories | C15: 2021-12 | D15: 2021 | E15: 12 | F15: 30883593 | G15: 26252193 | H15: 0.15
... A963: 20 | B963: Festive & Gifting | C963: 2024-12 | D963: 2024 | E963: 12 | F963: 7952461 | G963: 4844544.5 | H963: 0.3908

Sheet 01_Model_Promotion
A1: 01_Model_Promotion — ETL output (materialized). Source: Power Query joins documented in PowerQuery_DAX_Specification.md
A3: promotion_id | B3: revenue | C3: cost | D3: orders | E3: lines | F3: margin | G3: margin_pct | H3: avg_order_value | I3: promotion_name | J3: promotion_type | K3: discount_pct | L3: start_date | M3: end_date | N3: baseline_margin_pct | O3: baseline_avg_order_value | P3: margin_pct_delta_pp | Q3: aov_lift_pct
A4: 158 | B4: 478598231 | C4: 3.9289352e+08 | D4: 6171 | E4: 13564 | F4: 85704709 | G4: 0.1791 | H4: 77556.03 | I4: Loyalty Sep2024 - 5% Off | J4: Loyalty | K4: 5 | L4: 2024-09-19 | M4: 2024-10-03 | N4: 0.2226 | O4: 68093.63 | P4: -0.0435 | Q4: 0.139
A5: 182 | B5: 265770437 | C5: 2.1793244e+08 | D5: 3447 | E5: 7559 | F5: 47837999 | G5: 0.18 | H5: 77101.95 | I5: Festive Nov2024 - 5% Off | J5: Festive | K5: 5 | L5: 2024-11-26 | M5: 2024-12-06 | N5: 0.2226 | O5: 68093.63 | P5: -0.0426 | Q5: 0.1323
A6: 104 | B6: 261412791 | C6: 2.1400298e+08 | D6: 3408 | E6: 7433 | F6: 47409807 | G6: 0.1814 | H6: 76705.63 | I6: Seasonal Nov2024 - 5% Off | J6: Seasonal | K6: 5 | L6: 2024-11-24 | M6: 2024-12-01 | N6: 0.2226 | O6: 68093.63 | P6: -0.0413 | Q6: 0.1265
A7: 191 | B7: 171291786 | C7: 1.5652976e+08 | D7: 2409 | E7: 5330 | F7: 14762024 | G7: 0.0862 | H7: 71104.93 | I7: Seasonal Dec2023 - 15% Off | J7: Seasonal | K7: 15 | L7: 2023-12-25 | M7: 2024-01-12 | N7: 0.2226 | O7: 68093.63 | P7: -0.1364 | Q7: 0.0442
A8: 86 | B8: 150307327 | C8: 1.2305607e+08 | D8: 1902 | E8: 4193 | F8: 27251254 | G8: 0.1813 | H8: 79025.93 | I8: Festive Nov2022 - 5% Off | J8: Festive | K8: 5 | L8: 2022-11-27 | M8: 2022-12-17 | N8: 0.2226 | O8: 68093.63 | P8: -0.0413 | Q8: 0.1605
A9: 37 | B9: 136643946 | C9: 1.1178656e+08 | D9: 1852 | E9: 4016 | F9: 24857382 | G9: 0.1819 | H9: 73781.83 | I9: Festive Oct2021 - 5% Off | J9: Festive | K9: 5 | L9: 2021-10-30 | M9: 2021-11-06 | N9: 0.2226 | O9: 68093.63 | P9: -0.0407 | Q9: 0.0835
A10: 72 | B10: 132548651 | C10: 1.1432939e+08 | D10: 1875 | E10: 4059 | F10: 18219261 | G10: 0.1375 | H10: 70692.61 | I10: Festive Jun2022 - 10% Off | J10: Festive | K10: 10 | L10: 2022-06-27 | M10: 2022-07-09 | N10: 0.2226 | O10: 68093.63 | P10: -0.0852 | Q10: 0.0382
A11: 187 | B11: 130796895 | C11: 1.3550542e+08 | D11: 2219 | E11: 4843 | F11: -4708521.8 | G11: -0.036 | H11: 58944.07 | I11: Festive Nov2023 - 25% Off | J11: Festive | K11: 25 | L11: 2023-11-27 | M11: 2023-12-13 | N11: 0.2226 | O11: 68093.63 | P11: -0.2586 | Q11: -0.1344
A12: 155 | B12: 130476222 | C12: 1.1545389e+08 | D12: 1895 | E12: 4194 | F12: 15022331 | G12: 0.1151 | H12: 68852.89 | I12: Seasonal Nov2022 - 12% Off | J12: Seasonal | K12: 12 | L12: 2022-11-22 | M12: 2022-12-04 | N12: 0.2226 | O12: 68093.63 | P12: -0.1075 | Q12: 0.0112
A13: 140 | B13: 127756385 | C13: 1.1743837e+08 | D13: 1818 | E13: 3952 | F13: 10318013 | G13: 0.0808 | H13: 70273.04 | I13: Festive Oct2021 - 15% Off | J13: Festive | K13: 15 | L13: 2021-10-26 | M13: 2021-11-07 | N13: 0.2226 | O13: 68093.63 | P13: -0.1419 | Q13: 0.032
A14: 60 | B14: 124049338 | C14: 1.3775341e+08 | D14: 2238 | E14: 4985 | F14: -13704073 | G14: -0.1105 | H14: 55428.66 | I14: Loyalty Nov2023 - 30% Off | J14: Loyalty | K14: 30 | L14: 2023-11-13 | M14: 2023-12-01 | N14: 0.2226 | O14: 68093.63 | P14: -0.3331 | Q14: -0.186
A15: 83 | B15: 111883993 | C15: 1.2445211e+08 | D15: 1945 | E15: 4312 | F15: -12568118 | G15: -0.1123 | H15: 57523.9 | I15: Flash Sale Jun2022 - 30% Off | J15: Flash Sale | K15: 30 | L15: 2022-06-30 | M15: 2022-07-02 | N15: 0.2226 | O15: 68093.63 | P15: -0.335 | Q15: -0.1552
... A203: 193 | B203: 10199470 | C203: 10693015 | D203: 190 | E203: 391 | F203: -493544.72 | G203: -0.0484 | H203: 53681.42 | I203: Loyalty Jun2021 - 25% Off | J203: Loyalty | K203: 25 | L203: 2021-06-19 | M203: 2021-06-28 | N203: 0.2226 | O203: 68093.63 | P203: -0.271 | Q203: -0.2117

Sheet 01_Model_SLA
A1: 01_Model_SLA — ETL output (materialized). Source: Power Query joins documented in PowerQuery_DAX_Specification.md
A3: region_id | B3: region_name | C3: courier_partner | D3: shipment_count | E3: late_count | F3: late_rate
A4: 1 | B4: Delhi NCR | C4: BlueDart Express | D4: 3842 | E4: 337 | F4: 0.0877
A5: 1 | B5: Delhi NCR | C5: DTDC | D5: 3886 | E5: 342 | F5: 0.088
A6: 1 | B6: Delhi NCR | C6: Delhivery | D6: 3889 | E6: 307 | F6: 0.0789
A7: 1 | B7: Delhi NCR | C7: Ekart Logistics | D7: 3868 | E7: 320 | F7: 0.0827
A8: 1 | B8: Delhi NCR | C8: XpressBees | D8: 4017 | E8: 311 | F8: 0.0774
A9: 4 | B9: Gujarat | C9: BlueDart Express | D9: 4142 | E9: 388 | F9: 0.0937
A10: 4 | B10: Gujarat | C10: DTDC | D10: 4009 | E10: 385 | F10: 0.096
A11: 4 | B11: Gujarat | C11: Delhivery | D11: 4153 | E11: 404 | F11: 0.0973
A12: 4 | B12: Gujarat | C12: Ekart Logistics | D12: 4172 | E12: 408 | F12: 0.0978
A13: 4 | B13: Gujarat | C13: XpressBees | D13: 3986 | E13: 382 | F13: 0.0958
A14: 5 | B14: Karnataka | C14: BlueDart Express | D14: 5349 | E14: 541 | F14: 0.1011
A15: 5 | B15: Karnataka | C15: DTDC | D15: 5425 | E15: 525 | F15: 0.0968
... A63: 9 | B63: West Bengal | C63: XpressBees | D63: 8038 | E63: 743 | F63: 0.0924

Sheet 02_KPI_Margin
A1: Q1 — Revenue & Margin Trend
A2: All figures computed live from 01_Model_Overall_Month. No typed totals.
A4: Overall Metrics (Full Period: Jan 2021 - Dec 2024)
A5: Total Revenue | B5: =SUM(tblModelOverallMonth[revenue]) -> 18879364487
A6: Total Cost | B6: =SUM(tblModelOverallMonth[cost]) -> 1.6237586e+10
A7: Total Margin (Rs) | B7: =B5-B6 -> 2.6417786e+09
A8: Overall Margin % | B8: =B7/B5 -> 0.13992943
A9: Margin % Volatility (StDev of monthly margin %) | B9: =STDEV(tblModelOverallMonth[margin_pct]) -> 0.026464573
A10: Highest Monthly Margin % | B10: =MAX(tblModelOverallMonth[margin_pct]) -> 0.199
A11: Lowest Monthly Margin % | B11: =MIN(tblModelOverallMonth[margin_pct]) -> 0.059
A12: Margin % Range (Volatility Spread) | B12: =B10-B11 -> 0.14
A14: Margin % by Year
A15: Year | B15: Revenue | C15: Cost | D15: Margin | E15: Margin %
A16: 2021 | B16: =SUMIFS(tblModelOverallMonth[revenue],tblModelOverallMonth[year],A16) -> 3032246133 | C16: =SUMIFS(tblModelOverallMonth[cost],tblModelOverallMonth[year],A16) -> 2.6049533e+09 | D16: =B16-C16 -> 4.2729282e+08 | E16: =D16/B16 -> 0.14091627
A17: 2022 | B17: =SUMIFS(tblModelOverallMonth[revenue],tblModelOverallMonth[year],A17) -> 4288277586 | C17: =SUMIFS(tblModelOverallMonth[cost],tblModelOverallMonth[year],A17) -> 3.7151179e+09 | D17: =B17-C17 -> 5.7315965e+08 | E17: =D17/B17 -> 0.13365731
A18: 2023 | B18: =SUMIFS(tblModelOverallMonth[revenue],tblModelOverallMonth[year],A18) -> 5394885335 | C18: =SUMIFS(tblModelOverallMonth[cost],tblModelOverallMonth[year],A18) -> 4.7347705e+09 | D18: =B18-C18 -> 6.6011484e+08 | E18: =D18/B18 -> 0.12235938
A19: 2024 | B19: =SUMIFS(tblModelOverallMonth[revenue],tblModelOverallMonth[year],A19) -> 6163955433 | C19: =SUMIFS(tblModelOverallMonth[cost],tblModelOverallMonth[year],A19) -> 5.1827441e+09 | D19: =B19-C19 -> 9.8121134e+08 | E19: =D19/B19 -> 0.15918534
A22: Last 6 Months (Jul-Dec 2024) vs Prior 6 Months (Jan-Jun 2024)
A23: Period | B23: Revenue | C23: Margin %
A24: Prior 6M (Jan-Jun 2024) | B24: =SUMIFS(tblModelOverallMonth[revenue],tblModelOverallMonth[year],2024,tblModelOverallMonth[month],">=1",tblModelOverallMonth[month],"<=6") -> 2629402466 | C24: =SUMIFS(tblModelOverallMonth[margin],tblModelOverallMonth[year],2024,tblModelOverallMonth[month],">=1",tblModelOverallMonth[month],"<=6")/B24 -> 0.13710958
A25: Last 6M (Jul-Dec 2024) | B25: =SUMIFS(tblModelOverallMonth[revenue],tblModelOverallMonth[year],2024,tblModelOverallMonth[month],">=7",tblModelOverallMonth[month],"<=12") -> 3534552967 | C25: =SUMIFS(tblModelOverallMonth[margin],tblModelOverallMonth[year],2024,tblModelOverallMonth[month],">=7",tblModelOverallMonth[month],"<=12")/B25 -> 0.1756078
A26: Change (percentage points) | C26: =C25-C24 -> 0.03849822

Sheet 03_KPI_Target
A1: Q2 — Target vs Achievement (Region-Level; no store-level target exists in source data)
A3: FY2024 Region-Level Target vs Achievement (Jan-Dec 2024)
A4: Region | B4: Zone | C4: Revenue 2024 | D4: Target 2024 | E4: Achievement % | F4: Status
A5: Delhi NCR | B5: North | C5: =SUMIFS(tblModelRegionMonth[revenue],tblModelRegionMonth[region_name],A5,tblModelRegionMonth[year],2024) -> 427064177 | D5: =SUMIFS(tblModelRegionMonth[target_amount],tblModelRegionMonth[region_name],A5,tblModelRegionMonth[year],2024) -> 372579000 | E5: =C5/D5 -> 1.1462379 | F5: =IF(E5>=1,"On/Above Target","Below Target") -> On/Above Target
A6: Gujarat | B6: West | C6: =SUMIFS(tblModelRegionMonth[revenue],tblModelRegionMonth[region_name],A6,tblModelRegionMonth[year],2024) -> 450052766 | D6: =SUMIFS(tblModelRegionMonth[target_amount],tblModelRegionMonth[region_name],A6,tblModelRegionMonth[year],2024) -> 415613000 | E6: =C6/D6 -> 1.082865 | F6: =IF(E6>=1,"On/Above Target","Below Target") -> On/Above Target
A7: Karnataka | B7: South | C7: =SUMIFS(tblModelRegionMonth[revenue],tblModelRegionMonth[region_name],A7,tblModelRegionMonth[year],2024) -> 591917328 | D7: =SUMIFS(tblModelRegionMonth[target_amount],tblModelRegionMonth[region_name],A7,tblModelRegionMonth[year],2024) -> 544739000 | E7: =C7/D7 -> 1.0866072 | F7: =IF(E7>=1,"On/Above Target","Below Target") -> On/Above Target
A8: Kerala | B8: South | C8: =SUMIFS(tblModelRegionMonth[revenue],tblModelRegionMonth[region_name],A8,tblModelRegionMonth[year],2024) -> 427842945 | D8: =SUMIFS(tblModelRegionMonth[target_amount],tblModelRegionMonth[region_name],A8,tblModelRegionMonth[year],2024) -> 338539000 | E8: =C8/D8 -> 1.2637922 | F8: =IF(E8>=1,"On/Above Target","Below Target") -> On/Above Target
A9: Madhya Pradesh | B9: Central | C9: =SUMIFS(tblModelRegionMonth[revenue],tblModelRegionMonth[region_name],A9,tblModelRegionMonth[year],2024) -> 334767166 | D9: =SUMIFS(tblModelRegionMonth[target_amount],tblModelRegionMonth[region_name],A9,tblModelRegionMonth[year],2024) -> 270092000 | E9: =C9/D9 -> 1.2394561 | F9: =IF(E9>=1,"On/Above Target","Below Target") -> On/Above Target
A10: Maharashtra | B10: West | C10: =SUMIFS(tblModelRegionMonth[revenue],tblModelRegionMonth[region_name],A10,tblModelRegionMonth[year],2024) -> 606425965 | D10: =SUMIFS(tblModelRegionMonth[target_amount],tblModelRegionMonth[region_name],A10,tblModelRegionMonth[year],2024) -> 554212000 | E10: =C10/D10 -> 1.094213 | F10: =IF(E10>=1,"On/Above Target","Below Target") -> On/Above Target
A11: Odisha-Jharkhand | B11: East | C11: =SUMIFS(tblModelRegionMonth[revenue],tblModelRegionMonth[region_name],A11,tblModelRegionMonth[year],2024) -> 333544565 | D11: =SUMIFS(tblModelRegionMonth[target_amount],tblModelRegionMonth[region_name],A11,tblModelRegionMonth[year],2024) -> 341602000 | E11: =C11/D11 -> 0.9764128 | F11: =IF(E11>=1,"On/Above Target","Below Target") -> Below Target
A12: Punjab-Haryana | B12: North | C12: =SUMIFS(tblModelRegionMonth[revenue],tblModelRegionMonth[region_name],A12,tblModelRegionMonth[year],2024) -> 743332896 | D12: =SUMIFS(tblModelRegionMonth[target_amount],tblModelRegionMonth[region_name],A12,tblModelRegionMonth[year],2024) -> 693045000 | E12: =C12/D12 -> 1.0725608 | F12: =IF(E12>=1,"On/Above Target","Below Target") -> On/Above Target
A13: Rajasthan | B13: North | C13: =SUMIFS(tblModelRegionMonth[revenue],tblModelRegionMonth[region_name],A13,tblModelRegionMonth[year],2024) -> 459325321 | D13: =SUMIFS(tblModelRegionMonth[target_amount],tblModelRegionMonth[region_name],A13,tblModelRegionMonth[year],2024) -> 391442000 | E13: =C13/D13 -> 1.1734186 | F13: =IF(E13>=1,"On/Above Target","Below Target") -> On/Above Target
A14: Tamil Nadu | B14: South | C14: =SUMIFS(tblModelRegionMonth[revenue],tblModelRegionMonth[region_name],A14,tblModelRegionMonth[year],2024) -> 614337984 | D14: =SUMIFS(tblModelRegionMonth[target_amount],tblModelRegionMonth[region_name],A14,tblModelRegionMonth[year],2024) -> 617125000 | E14: =C14/D14 -> 0.99548387 | F14: =IF(E14>=1,"On/Above Target","Below Target") -> Below Target
A15: Telangana-AP | B15: South | C15: =SUMIFS(tblModelRegionMonth[revenue],tblModelRegionMonth[region_name],A15,tblModelRegionMonth[year],2024) -> 275671560 | D15: =SUMIFS(tblModelRegionMonth[target_amount],tblModelRegionMonth[region_name],A15,tblModelRegionMonth[year],2024) -> 284519000 | E15: =C15/D15 -> 0.96890387 | F15: =IF(E15>=1,"On/Above Target","Below Target") -> Below Target
A16: West Bengal | B16: East | C16: =SUMIFS(tblModelRegionMonth[revenue],tblModelRegionMonth[region_name],A16,tblModelRegionMonth[year],2024) -> 899672760 | D16: =SUMIFS(tblModelRegionMonth[target_amount],tblModelRegionMonth[region_name],A16,tblModelRegionMonth[year],2024) -> 763106000 | E16: =C16/D16 -> 1.1789617 | F16: =IF(E16>=1,"On/Above Target","Below Target") -> On/Above Target

Sheet 04_KPI_Category
A1: Q3 — Which categories drive revenue but not profit, and why | H1: Overall Avg Margin % | I1: =AVERAGE(tblModelCategory[margin_pct]) -> 0.23779
A2: Ranked by revenue. Diagnostic columns show discount leakage % and return rate as candidate causes. | H2: Median Revenue Share % | I2: =MEDIAN(C5:C24) -> 0.012622715
A4: Category | B4: Revenue | C4: Revenue Share % | D4: Margin % | E4: Discount Leak % | F4: Return Rate % | G4: Diagnosis
A5: =INDEX(tblModelCategory[category_name],1) -> Refrigerators | B5: =INDEX(tblModelCategory[revenue],1) -> 4382590644 | C5: =B5/SUM(tblModelCategory[revenue]) -> 0.23213656 | D5: =INDEX(tblModelCategory[margin_pct],1) -> 0.1217 | E5: =INDEX(tblModelCategory[discount_leak_pct],1) -> 0.0985 | F5: =INDEX(tblModelCategory[return_rate],1) -> 0.0355 | G5: =IF(AND(C5>$I$2,D5<$I$1),"High Revenue / Low Margin - review discount & returns",IF(AND(C5>$I$2,D5>=$I$1),"High Revenue / Healthy Margin",IF(AND(C5<=$I$2,D5<$I$1),"Low Revenue / Low Margin - low priority","Low Revenue / Healthy Margin"))) -> High Revenue / Low Margin - review discount & returns
A6: =INDEX(tblModelCategory[category_name],2) -> Laptops & Computers | B6: =INDEX(tblModelCategory[revenue],2) -> 2977044772 | C6: =B6/SUM(tblModelCategory[revenue]) -> 0.15768776 | D6: =INDEX(tblModelCategory[margin_pct],2) -> 0.0572 | E6: =INDEX(tblModelCategory[discount_leak_pct],2) -> 0.0994 | F6: =INDEX(tblModelCategory[return_rate],2) -> 0.0465 | G6: =IF(AND(C6>$I$2,D6<$I$1),"High Revenue / Low Margin - review discount & returns",IF(AND(C6>$I$2,D6>=$I$1),"High Revenue / Healthy Margin",IF(AND(C6<=$I$2,D6<$I$1),"Low Revenue / Low Margin - low priority","Low Revenue / Healthy Margin"))) -> High Revenue / Low Margin - review discount & returns
A7: =INDEX(tblModelCategory[category_name],3) -> Televisions | B7: =INDEX(tblModelCategory[revenue],3) -> 2296118310 | C7: =B7/SUM(tblModelCategory[revenue]) -> 0.12162053 | D7: =INDEX(tblModelCategory[margin_pct],3) -> 0.1195 | E7: =INDEX(tblModelCategory[discount_leak_pct],3) -> 0.0986 | F7: =INDEX(tblModelCategory[return_rate],3) -> 0.0414 | G7: =IF(AND(C7>$I$2,D7<$I$1),"High Revenue / Low Margin - review discount & returns",IF(AND(C7>$I$2,D7>=$I$1),"High Revenue / Healthy Margin",IF(AND(C7<=$I$2,D7<$I$1),"Low Revenue / Low Margin - low priority","Low Revenue / Healthy Margin"))) -> High Revenue / Low Margin - review discount & returns
A8: =INDEX(tblModelCategory[category_name],4) -> Furniture | B8: =INDEX(tblModelCategory[revenue],4) -> 1907350207 | C8: =B8/SUM(tblModelCategory[revenue]) -> 0.10102831 | D8: =INDEX(tblModelCategory[margin_pct],4) -> 0.1605 | E8: =INDEX(tblModelCategory[discount_leak_pct],4) -> 0.0993 | F8: =INDEX(tblModelCategory[return_rate],4) -> 0.0313 | G8: =IF(AND(C8>$I$2,D8<$I$1),"High Revenue / Low Margin - review discount & returns",IF(AND(C8>$I$2,D8>=$I$1),"High Revenue / Healthy Margin",IF(AND(C8<=$I$2,D8<$I$1),"Low Revenue / Low Margin - low priority","Low Revenue / Healthy Margin"))) -> High Revenue / Low Margin - review discount & returns
A9: =INDEX(tblModelCategory[category_name],5) -> Mobiles & Accessories | B9: =INDEX(tblModelCategory[revenue],5) -> 1718375549 | C9: =B9/SUM(tblModelCategory[revenue]) -> 0.091018718 | D9: =INDEX(tblModelCategory[margin_pct],5) -> 0.1198 | E9: =INDEX(tblModelCategory[discount_leak_pct],5) -> 0.0983 | F9: =INDEX(tblModelCategory[return_rate],5) -> 0.0435 | G9: =IF(AND(C9>$I$2,D9<$I$1),"High Revenue / Low Margin - review discount & returns",IF(AND(C9>$I$2,D9>=$I$1),"High Revenue / Healthy Margin",IF(AND(C9<=$I$2,D9<$I$1),"Low Revenue / Low Margin - low priority","Low Revenue / Healthy Margin"))) -> High Revenue / Low Margin - review discount & returns
A10: =INDEX(tblModelCategory[category_name],6) -> Air Conditioners & Coolers | B10: =INDEX(tblModelCategory[revenue],6) -> 1462422495 | C10: =B10/SUM(tblModelCategory[revenue]) -> 0.077461426 | D10: =INDEX(tblModelCategory[margin_pct],6) -> 0.1046 | E10: =INDEX(tblModelCategory[discount_leak_pct],6) -> 0.0999 | F10: =INDEX(tblModelCategory[return_rate],6) -> 0.036 | G10: =IF(AND(C10>$I$2,D10<$I$1),"High Revenue / Low Margin - review discount & returns",IF(AND(C10>$I$2,D10>=$I$1),"High Revenue / Healthy Margin",IF(AND(C10<=$I$2,D10<$I$1),"Low Revenue / Low Margin - low priority","Low Revenue / Healthy Margin"))) -> High Revenue / Low Margin - review discount & returns
A11: =INDEX(tblModelCategory[category_name],7) -> Washing Machines | B11: =INDEX(tblModelCategory[revenue],7) -> 1242288851 | C11: =B11/SUM(tblModelCategory[revenue]) -> 0.065801413 | D11: =INDEX(tblModelCategory[margin_pct],7) -> 0.1156 | E11: =INDEX(tblModelCategory[discount_leak_pct],7) -> 0.0981 | F11: =INDEX(tblModelCategory[return_rate],7) -> 0.034 | G11: =IF(AND(C11>$I$2,D11<$I$1),"High Revenue / Low Margin - review discount & returns",IF(AND(C11>$I$2,D11>=$I$1),"High Revenue / Healthy Margin",IF(AND(C11<=$I$2,D11<$I$1),"Low Revenue / Low Margin - low priority","Low Revenue / Healthy Margin"))) -> High Revenue / Low Margin - review discount & returns
A12: =INDEX(tblModelCategory[category_name],8) -> Kitchen Appliances | B12: =INDEX(tblModelCategory[revenue],8) -> 602723939 | C12: =B12/SUM(tblModelCategory[revenue]) -> 0.031925012 | D12: =INDEX(tblModelCategory[margin_pct],8) -> 0.2781 | E12: =INDEX(tblModelCategory[discount_leak_pct],8) -> 0.0986 | F12: =INDEX(tblModelCategory[return_rate],8) -> 0.0286 | G12: =IF(AND(C12>$I$2,D12<$I$1),"High Revenue / Low Margin - review discount & returns",IF(AND(C12>$I$2,D12>=$I$1),"High Revenue / Healthy Margin",IF(AND(C12<=$I$2,D12<$I$1),"Low Revenue / Low Margin - low priority","Low Revenue / Healthy Margin"))) -> High Revenue / Healthy Margin
A13: =INDEX(tblModelCategory[category_name],9) -> Home Audio | B13: =INDEX(tblModelCategory[revenue],9) -> 520527346 | C13: =B13/SUM(tblModelCategory[revenue]) -> 0.027571232 | D13: =INDEX(tblModelCategory[margin_pct],9) -> 0.1863 | E13: =INDEX(tblModelCategory[discount_leak_pct],9) -> 0.0988 | F13: =INDEX(tblModelCategory[return_rate],9) -> 0.0387 | G13: =IF(AND(C13>$I$2,D13<$I$1),"High Revenue / Low Margin - review discount & returns",IF(AND(C13>$I$2,D13>=$I$1),"High Revenue / Healthy Margin",IF(AND(C13<=$I$2,D13<$I$1),"Low Revenue / Low Margin - low priority","Low Revenue / Healthy Margin"))) -> High Revenue / Low Margin - review discount & returns
A14: =INDEX(tblModelCategory[category_name],10) -> Heaters & Winter Appliances | B14: =INDEX(tblModelCategory[revenue],10) -> 258134495 | C14: =B14/SUM(tblModelCategory[revenue]) -> 0.013672838 | D14: =INDEX(tblModelCategory[margin_pct],10) -> 0.26 | E14: =INDEX(tblModelCategory[discount_leak_pct],10) -> 0.0983 | F14: =INDEX(tblModelCategory[return_rate],10) -> 0.0268 | G14: =IF(AND(C14>$I$2,D14<$I$1),"High Revenue / Low Margin - review discount & returns",IF(AND(C14>$I$2,D14>=$I$1),"High Revenue / Healthy Margin",IF(AND(C14<=$I$2,D14<$I$1),"Low Revenue / Low Margin - low priority","Low Revenue / Healthy Margin"))) -> High Revenue / Healthy Margin
A15: =INDEX(tblModelCategory[category_name],11) -> Footwear | B15: =INDEX(tblModelCategory[revenue],11) -> 218483178 | C15: =B15/SUM(tblModelCategory[revenue]) -> 0.011572592 | D15: =INDEX(tblModelCategory[margin_pct],11) -> 0.3335 | E15: =INDEX(tblModelCategory[discount_leak_pct],11) -> 0.0993 | F15: =INDEX(tblModelCategory[return_rate],11) -> 0.0676 | G15: =IF(AND(C15>$I$2,D15<$I$1),"High Revenue / Low Margin - review discount & returns",IF(AND(C15>$I$2,D15>=$I$1),"High Revenue / Healthy Margin",IF(AND(C15<=$I$2,D15<$I$1),"Low Revenue / Low Margin - low priority","Low Revenue / Healthy Margin"))) -> Low Revenue / Healthy Margin
A16: =INDEX(tblModelCategory[category_name],12) -> Festive & Gifting | B16: =INDEX(tblModelCategory[revenue],12) -> 216122731 | C16: =B16/SUM(tblModelCategory[revenue]) -> 0.011447564 | D16: =INDEX(tblModelCategory[margin_pct],12) -> 0.3476 | E16: =INDEX(tblModelCategory[discount_leak_pct],12) -> 0.0986 | F16: =INDEX(tblModelCategory[return_rate],12) -> 0.0299 | G16: =IF(AND(C16>$I$2,D16<$I$1),"High Revenue / Low Margin - review discount & returns",IF(AND(C16>$I$2,D16>=$I$1),"High Revenue / Healthy Margin",IF(AND(C16<=$I$2,D16<$I$1),"Low Revenue / Low Margin - low priority","Low Revenue / Healthy Margin"))) -> Low Revenue / Healthy Margin
A17: =INDEX(tblModelCategory[category_name],13) -> Home Decor | B17: =INDEX(tblModelCategory[revenue],13) -> 190662742 | C17: =B17/SUM(tblModelCategory[revenue]) -> 0.010099002 | D17: =INDEX(tblModelCategory[margin_pct],13) -> 0.3881 | E17: =INDEX(tblModelCategory[discount_leak_pct],13) -> 0.0978 | F17: =INDEX(tblModelCategory[return_rate],13) -> 0.0288 | G17: =IF(AND(C17>$I$2,D17<$I$1),"High Revenue / Low Margin - review discount & returns",IF(AND(C17>$I$2,D17>=$I$1),"High Revenue / Healthy Margin",IF(AND(C17<=$I$2,D17<$I$1),"Low Revenue / Low Margin - low priority","Low Revenue / Healthy Margin"))) -> Low Revenue / Healthy Margin
A18: =INDEX(tblModelCategory[category_name],14) -> Women's Apparel | B18: =INDEX(tblModelCategory[revenue],14) -> 180387906 | C18: =B18/SUM(tblModelCategory[revenue]) -> 0.0095547658 | D18: =INDEX(tblModelCategory[margin_pct],14) -> 0.4008 | E18: =INDEX(tblModelCategory[discount_leak_pct],14) -> 0.0989 | F18: =INDEX(tblModelCategory[return_rate],14) -> 0.0672 | G18: =IF(AND(C18>$I$2,D18<$I$1),"High Revenue / Low Margin - review discount & returns",IF(AND(C18>$I$2,D18>=$I$1),"High Revenue / Healthy Margin",IF(AND(C18<=$I$2,D18<$I$1),"Low Revenue / Low Margin - low priority","Low Revenue / Healthy Margin"))) -> Low Revenue / Healthy Margin
A19: =INDEX(tblModelCategory[category_name],15) -> Men's Apparel | B19: =INDEX(tblModelCategory[revenue],15) -> 174253220 | C19: =B19/SUM(tblModelCategory[revenue]) -> 0.0092298245 | D19: =INDEX(tblModelCategory[margin_pct],15) -> 0.3818 | E19: =INDEX(tblModelCategory[discount_leak_pct],15) -> 0.0973 | F19: =INDEX(tblModelCategory[return_rate],15) -> 0.0693 | G19: =IF(AND(C19>$I$2,D19<$I$1),"High Revenue / Low Margin - review discount & returns",IF(AND(C19>$I$2,D19>=$I$1),"High Revenue / Healthy Margin",IF(AND(C19<=$I$2,D19<$I$1),"Low Revenue / Low Margin - low priority","Low Revenue / Healthy Margin"))) -> Low Revenue / Healthy Margin
A20: =INDEX(tblModelCategory[category_name],16) -> Toys & Games | B20: =INDEX(tblModelCategory[revenue],16) -> 152264378 | C20: =B20/SUM(tblModelCategory[revenue]) -> 0.008065122 | D20: =INDEX(tblModelCategory[margin_pct],16) -> 0.2979 | E20: =INDEX(tblModelCategory[discount_leak_pct],16) -> 0.0989 | F20: =INDEX(tblModelCategory[return_rate],16) -> 0.0314 | G20: =IF(AND(C20>$I$2,D20<$I$1),"High Revenue / Low Margin - review discount & returns",IF(AND(C20>$I$2,D20>=$I$1),"High Revenue / Healthy Margin",IF(AND(C20<=$I$2,D20<$I$1),"Low Revenue / Low Margin - low priority","Low Revenue / Healthy Margin"))) -> Low Revenue / Healthy Margin
A21: =INDEX(tblModelCategory[category_name],17) -> Kitchenware | B21: =INDEX(tblModelCategory[revenue],17) -> 150573007 | C21: =B21/SUM(tblModelCategory[revenue]) -> 0.0079755337 | D21: =INDEX(tblModelCategory[margin_pct],17) -> 0.3423 | E21: =INDEX(tblModelCategory[discount_leak_pct],17) -> 0.1008 | F21: =INDEX(tblModelCategory[return_rate],17) -> 0.0262 | G21: =IF(AND(C21>$I$2,D21<$I$1),"High Revenue / Low Margin - review discount & returns",IF(AND(C21>$I$2,D21>=$I$1),"High Revenue / Healthy Margin",IF(AND(C21<=$I$2,D21<$I$1),"Low Revenue / Low Margin - low priority","Low Revenue / Healthy Margin"))) -> Low Revenue / Healthy Margin
A22: =INDEX(tblModelCategory[category_name],18) -> Kids Apparel | B22: =INDEX(tblModelCategory[revenue],18) -> 109354906 | C22: =B22/SUM(tblModelCategory[revenue]) -> 0.005792298 | D22: =INDEX(tblModelCategory[margin_pct],18) -> 0.3757 | E22: =INDEX(tblModelCategory[discount_leak_pct],18) -> 0.101 | F22: =INDEX(tblModelCategory[return_rate],18) -> 0.0692 | G22: =IF(AND(C22>$I$2,D22<$I$1),"High Revenue / Low Margin - review discount & returns",IF(AND(C22>$I$2,D22>=$I$1),"High Revenue / Healthy Margin",IF(AND(C22<=$I$2,D22<$I$1),"Low Revenue / Low Margin - low priority","Low Revenue / Healthy Margin"))) -> Low Revenue / Healthy Margin
A23: =INDEX(tblModelCategory[category_name],19) -> Personal Care | B23: =INDEX(tblModelCategory[revenue],19) -> 74610385 | C23: =B23/SUM(tblModelCategory[revenue]) -> 0.0039519543 | D23: =INDEX(tblModelCategory[margin_pct],19) -> 0.2769 | E23: =INDEX(tblModelCategory[discount_leak_pct],19) -> 0.0999 | F23: =INDEX(tblModelCategory[return_rate],19) -> 0.0076 | G23: =IF(AND(C23>$I$2,D23<$I$1),"High Revenue / Low Margin - review discount & returns",IF(AND(C23>$I$2,D23>=$I$1),"High Revenue / Healthy Margin",IF(AND(C23<=$I$2,D23<$I$1),"Low Revenue / Low Margin - low priority","Low Revenue / Healthy Margin"))) -> Low Revenue / Healthy Margin
A24: =INDEX(tblModelCategory[category_name],20) -> Groceries & Staples | B24: =INDEX(tblModelCategory[revenue],20) -> 45075426 | C24: =B24/SUM(tblModelCategory[revenue]) -> 0.00238755 | D24: =INDEX(tblModelCategory[margin_pct],20) -> 0.0879 | E24: =INDEX(tblModelCategory[discount_leak_pct],20) -> 0.0992 | F24: =INDEX(tblModelCategory[return_rate],20) -> 0.0075 | G24: =IF(AND(C24>$I$2,D24<$I$1),"High Revenue / Low Margin - review discount & returns",IF(AND(C24>$I$2,D24>=$I$1),"High Revenue / Healthy Margin",IF(AND(C24<=$I$2,D24<$I$1),"Low Revenue / Low Margin - low priority","Low Revenue / Healthy Margin"))) -> Low Revenue / Low Margin - low priority

Sheet 05_KPI_Discount
A1: Q5 — Where discounting erodes margin the most | H1: Overall Avg Discount Leak % | I1: =AVERAGE(tblModelCategory[discount_leak_pct]) -> 0.098975
A2: Category-level discount leakage (catalog price vs actual charged price). Flagged vs overall average.
A4: Category | B4: Revenue | C4: Catalog Value | D4: Discount Leakage (Rs) | E4: Discount Leakage % | F4: Flag
A5: =INDEX(tblModelCategory[category_name],MATCH("Kids Apparel",tblModelCategory[category_name],0)) -> Kids Apparel | B5: =SUMIFS(tblModelCategory[revenue],tblModelCategory[category_name],A5) -> 109354906 | C5: =SUMIFS(tblModelCategory[catalog_value],tblModelCategory[category_name],A5) -> 121236720 | D5: =SUMIFS(tblModelCategory[discount_leak],tblModelCategory[category_name],A5) -> 12241067 | E5: =D5/C5 -> 0.10096831 | F5: =IF(E5>$I$1,"Above Average - Review Discount Policy","Within Normal Range") -> Above Average - Review Discount Policy
A6: =INDEX(tblModelCategory[category_name],MATCH("Kitchenware",tblModelCategory[category_name],0)) -> Kitchenware | B6: =SUMIFS(tblModelCategory[revenue],tblModelCategory[category_name],A6) -> 150573007 | C6: =SUMIFS(tblModelCategory[catalog_value],tblModelCategory[category_name],A6) -> 166904040 | D6: =SUMIFS(tblModelCategory[discount_leak],tblModelCategory[category_name],A6) -> 16830249 | E6: =D6/C6 -> 0.10083788 | F6: =IF(E6>$I$1,"Above Average - Review Discount Policy","Within Normal Range") -> Above Average - Review Discount Policy
A7: =INDEX(tblModelCategory[category_name],MATCH("Personal Care",tblModelCategory[category_name],0)) -> Personal Care | B7: =SUMIFS(tblModelCategory[revenue],tblModelCategory[category_name],A7) -> 74610385 | C7: =SUMIFS(tblModelCategory[catalog_value],tblModelCategory[category_name],A7) -> 82606690 | D7: =SUMIFS(tblModelCategory[discount_leak],tblModelCategory[category_name],A7) -> 8249305 | E7: =D7/C7 -> 0.099862432 | F7: =IF(E7>$I$1,"Above Average - Review Discount Policy","Within Normal Range") -> Above Average - Review Discount Policy
A8: =INDEX(tblModelCategory[category_name],MATCH("Air Conditioners & Coolers",tblModelCategory[category_name],0)) -> Air Conditioners & Coolers | B8: =SUMIFS(tblModelCategory[revenue],tblModelCategory[category_name],A8) -> 1462422495 | C8: =SUMIFS(tblModelCategory[catalog_value],tblModelCategory[category_name],A8) -> 1619237220 | D8: =SUMIFS(tblModelCategory[discount_leak],tblModelCategory[category_name],A8) -> 161801886 | E8: =D8/C8 -> 0.099924757 | F8: =IF(E8>$I$1,"Above Average - Review Discount Policy","Within Normal Range") -> Above Average - Review Discount Policy
A9: =INDEX(tblModelCategory[category_name],MATCH("Laptops & Computers",tblModelCategory[category_name],0)) -> Laptops & Computers | B9: =SUMIFS(tblModelCategory[revenue],tblModelCategory[category_name],A9) -> 2977044772 | C9: =SUMIFS(tblModelCategory[catalog_value],tblModelCategory[category_name],A9) -> 3294481190 | D9: =SUMIFS(tblModelCategory[discount_leak],tblModelCategory[category_name],A9) -> 327405596 | E9: =D9/C9 -> 0.099380017 | F9: =IF(E9>$I$1,"Above Average - Review Discount Policy","Within Normal Range") -> Above Average - Review Discount Policy
A10: =INDEX(tblModelCategory[category_name],MATCH("Footwear",tblModelCategory[category_name],0)) -> Footwear | B10: =SUMIFS(tblModelCategory[revenue],tblModelCategory[category_name],A10) -> 218483178 | C10: =SUMIFS(tblModelCategory[catalog_value],tblModelCategory[category_name],A10) -> 241743290 | D10: =SUMIFS(tblModelCategory[discount_leak],tblModelCategory[category_name],A10) -> 24009501 | E10: =D10/C10 -> 0.099318169 | F10: =IF(E10>$I$1,"Above Average - Review Discount Policy","Within Normal Range") -> Above Average - Review Discount Policy
A11: =INDEX(tblModelCategory[category_name],MATCH("Furniture",tblModelCategory[category_name],0)) -> Furniture | B11: =SUMIFS(tblModelCategory[revenue],tblModelCategory[category_name],A11) -> 1907350207 | C11: =SUMIFS(tblModelCategory[catalog_value],tblModelCategory[category_name],A11) -> 2110496580 | D11: =SUMIFS(tblModelCategory[discount_leak],tblModelCategory[category_name],A11) -> 209518887 | E11: =D11/C11 -> 0.099274687 | F11: =IF(E11>$I$1,"Above Average - Review Discount Policy","Within Normal Range") -> Above Average - Review Discount Policy
A12: =INDEX(tblModelCategory[category_name],MATCH("Groceries & Staples",tblModelCategory[category_name],0)) -> Groceries & Staples | B12: =SUMIFS(tblModelCategory[revenue],tblModelCategory[category_name],A12) -> 45075426 | C12: =SUMIFS(tblModelCategory[catalog_value],tblModelCategory[category_name],A12) -> 49867370 | D12: =SUMIFS(tblModelCategory[discount_leak],tblModelCategory[category_name],A12) -> 4946330 | E12: =D12/C12 -> 0.099189711 | F12: =IF(E12>$I$1,"Above Average - Review Discount Policy","Within Normal Range") -> Above Average - Review Discount Policy
A13: =INDEX(tblModelCategory[category_name],MATCH("Women's Apparel",tblModelCategory[category_name],0)) -> Women's Apparel | B13: =SUMIFS(tblModelCategory[revenue],tblModelCategory[category_name],A13) -> 180387906 | C13: =SUMIFS(tblModelCategory[catalog_value],tblModelCategory[category_name],A13) -> 199503650 | D13: =SUMIFS(tblModelCategory[discount_leak],tblModelCategory[category_name],A13) -> 19724058 | E13: =D13/C13 -> 0.09886565 | F13: =IF(E13>$I$1,"Above Average - Review Discount Policy","Within Normal Range") -> Within Normal Range
A14: =INDEX(tblModelCategory[category_name],MATCH("Toys & Games",tblModelCategory[category_name],0)) -> Toys & Games | B14: =SUMIFS(tblModelCategory[revenue],tblModelCategory[category_name],A14) -> 152264378 | C14: =SUMIFS(tblModelCategory[catalog_value],tblModelCategory[category_name],A14) -> 168422050 | D14: =SUMIFS(tblModelCategory[discount_leak],tblModelCategory[category_name],A14) -> 16662928 | E14: =D14/C14 -> 0.098935549 | F14: =IF(E14>$I$1,"Above Average - Review Discount Policy","Within Normal Range") -> Within Normal Range
A15: =INDEX(tblModelCategory[category_name],MATCH("Home Audio",tblModelCategory[category_name],0)) -> Home Audio | B15: =SUMIFS(tblModelCategory[revenue],tblModelCategory[category_name],A15) -> 520527346 | C15: =SUMIFS(tblModelCategory[catalog_value],tblModelCategory[category_name],A15) -> 575620000 | D15: =SUMIFS(tblModelCategory[discount_leak],tblModelCategory[category_name],A15) -> 56856404 | E15: =D15/C15 -> 0.098774198 | F15: =IF(E15>$I$1,"Above Average - Review Discount Policy","Within Normal Range") -> Within Normal Range
A16: =INDEX(tblModelCategory[category_name],MATCH("Televisions",tblModelCategory[category_name],0)) -> Televisions | B16: =SUMIFS(tblModelCategory[revenue],tblModelCategory[category_name],A16) -> 2296118310 | C16: =SUMIFS(tblModelCategory[catalog_value],tblModelCategory[category_name],A16) -> 2538567220 | D16: =SUMIFS(tblModelCategory[discount_leak],tblModelCategory[category_name],A16) -> 250368359 | E16: =D16/C16 -> 0.098625854 | F16: =IF(E16>$I$1,"Above Average - Review Discount Policy","Within Normal Range") -> Within Normal Range
A17: =INDEX(tblModelCategory[category_name],MATCH("Festive & Gifting",tblModelCategory[category_name],0)) -> Festive & Gifting | B17: =SUMIFS(tblModelCategory[revenue],tblModelCategory[category_name],A17) -> 216122731 | C17: =SUMIFS(tblModelCategory[catalog_value],tblModelCategory[category_name],A17) -> 238954570 | D17: =SUMIFS(tblModelCategory[discount_leak],tblModelCategory[category_name],A17) -> 23569987 | E17: =D17/C17 -> 0.098637942 | F17: =IF(E17>$I$1,"Above Average - Review Discount Policy","Within Normal Range") -> Within Normal Range
A18: =INDEX(tblModelCategory[category_name],MATCH("Kitchen Appliances",tblModelCategory[category_name],0)) -> Kitchen Appliances | B18: =SUMIFS(tblModelCategory[revenue],tblModelCategory[category_name],A18) -> 602723939 | C18: =SUMIFS(tblModelCategory[catalog_value],tblModelCategory[category_name],A18) -> 666395200 | D18: =SUMIFS(tblModelCategory[discount_leak],tblModelCategory[category_name],A18) -> 65733883 | E18: =D18/C18 -> 0.098640991 | F18: =IF(E18>$I$1,"Above Average - Review Discount Policy","Within Normal Range") -> Within Normal Range
A19: =INDEX(tblModelCategory[category_name],MATCH("Refrigerators",tblModelCategory[category_name],0)) -> Refrigerators | B19: =SUMIFS(tblModelCategory[revenue],tblModelCategory[category_name],A19) -> 4382590644 | C19: =SUMIFS(tblModelCategory[catalog_value],tblModelCategory[category_name],A19) -> 4845220420 | D19: =SUMIFS(tblModelCategory[discount_leak],tblModelCategory[category_name],A19) -> 477412556 | E19: =D19/C19 -> 0.098532681 | F19: =IF(E19>$I$1,"Above Average - Review Discount Policy","Within Normal Range") -> Within Normal Range
A20: =INDEX(tblModelCategory[category_name],MATCH("Mobiles & Accessories",tblModelCategory[category_name],0)) -> Mobiles & Accessories | B20: =SUMIFS(tblModelCategory[revenue],tblModelCategory[category_name],A20) -> 1718375549 | C20: =SUMIFS(tblModelCategory[catalog_value],tblModelCategory[category_name],A20) -> 1899178170 | D20: =SUMIFS(tblModelCategory[discount_leak],tblModelCategory[category_name],A20) -> 186700048 | E20: =D20/C20 -> 0.098305705 | F20: =IF(E20>$I$1,"Above Average - Review Discount Policy","Within Normal Range") -> Within Normal Range
A21: =INDEX(tblModelCategory[category_name],MATCH("Heaters & Winter Appliances",tblModelCategory[category_name],0)) -> Heaters & Winter Appliances | B21: =SUMIFS(tblModelCategory[revenue],tblModelCategory[category_name],A21) -> 258134495 | C21: =SUMIFS(tblModelCategory[catalog_value],tblModelCategory[category_name],A21) -> 285298830 | D21: =SUMIFS(tblModelCategory[discount_leak],tblModelCategory[category_name],A21) -> 28051708 | E21: =D21/C21 -> 0.09832395 | F21: =IF(E21>$I$1,"Above Average - Review Discount Policy","Within Normal Range") -> Within Normal Range
A22: =INDEX(tblModelCategory[category_name],MATCH("Washing Machines",tblModelCategory[category_name],0)) -> Washing Machines | B22: =SUMIFS(tblModelCategory[revenue],tblModelCategory[category_name],A22) -> 1242288851 | C22: =SUMIFS(tblModelCategory[catalog_value],tblModelCategory[category_name],A22) -> 1372667370 | D22: =SUMIFS(tblModelCategory[discount_leak],tblModelCategory[category_name],A22) -> 134651075 | E22: =D22/C22 -> 0.098094468 | F22: =IF(E22>$I$1,"Above Average - Review Discount Policy","Within Normal Range") -> Within Normal Range
A23: =INDEX(tblModelCategory[category_name],MATCH("Home Decor",tblModelCategory[category_name],0)) -> Home Decor | B23: =SUMIFS(tblModelCategory[revenue],tblModelCategory[category_name],A23) -> 190662742 | C23: =SUMIFS(tblModelCategory[catalog_value],tblModelCategory[category_name],A23) -> 210602220 | D23: =SUMIFS(tblModelCategory[discount_leak],tblModelCategory[category_name],A23) -> 20606146 | E23: =D23/C23 -> 0.097843916 | F23: =IF(E23>$I$1,"Above Average - Review Discount Policy","Within Normal Range") -> Within Normal Range
A24: =INDEX(tblModelCategory[category_name],MATCH("Men's Apparel",tblModelCategory[category_name],0)) -> Men's Apparel | B24: =SUMIFS(tblModelCategory[revenue],tblModelCategory[category_name],A24) -> 174253220 | C24: =SUMIFS(tblModelCategory[catalog_value],tblModelCategory[category_name],A24) -> 192360750 | D24: =SUMIFS(tblModelCategory[discount_leak],tblModelCategory[category_name],A24) -> 18713357 | E24: =D24/C24 -> 0.097282616 | F24: =IF(E24>$I$1,"Above Average - Review Discount Policy","Within Normal Range") -> Within Normal Range

Sheet 06_KPI_Returns
A1: Q4 — Highest-return categories and Rs margin leakage from refunds | H1: Overall Avg Return Rate % | I1: =AVERAGE(tblModelCategory[return_rate]) -> 0.03835
A4: Category | B4: Order Lines | C4: Return Count | D4: Return Rate % | E4: Refund Leakage (Rs) | F4: Flag
A5: =INDEX(tblModelCategory[category_name],MATCH("Men's Apparel",tblModelCategory[category_name],0)) -> Men's Apparel | B5: =SUMIFS(tblModelCategory[lines],tblModelCategory[category_name],A5) -> 23457 | C5: =SUMIFS(tblModelCategory[return_count],tblModelCategory[category_name],A5) -> 1626 | D5: =C5/B5 -> 0.069318327 | E5: =SUMIFS(tblModelCategory[refund_amount],tblModelCategory[category_name],A5) -> 10202661 | F5: =IF(D5>$I$1,"Above Average - Investigate Return Reasons","Within Normal Range") -> Above Average - Investigate Return Reasons
A6: =INDEX(tblModelCategory[category_name],MATCH("Kids Apparel",tblModelCategory[category_name],0)) -> Kids Apparel | B6: =SUMIFS(tblModelCategory[lines],tblModelCategory[category_name],A6) -> 27448 | C6: =SUMIFS(tblModelCategory[return_count],tblModelCategory[category_name],A6) -> 1900 | D6: =C6/B6 -> 0.069221801 | E6: =SUMIFS(tblModelCategory[refund_amount],tblModelCategory[category_name],A6) -> 6606248 | F6: =IF(D6>$I$1,"Above Average - Investigate Return Reasons","Within Normal Range") -> Above Average - Investigate Return Reasons
A7: =INDEX(tblModelCategory[category_name],MATCH("Footwear",tblModelCategory[category_name],0)) -> Footwear | B7: =SUMIFS(tblModelCategory[lines],tblModelCategory[category_name],A7) -> 25921 | C7: =SUMIFS(tblModelCategory[return_count],tblModelCategory[category_name],A7) -> 1751 | D7: =C7/B7 -> 0.067551406 | E7: =SUMIFS(tblModelCategory[refund_amount],tblModelCategory[category_name],A7) -> 12659306 | F7: =IF(D7>$I$1,"Above Average - Investigate Return Reasons","Within Normal Range") -> Above Average - Investigate Return Reasons
A8: =INDEX(tblModelCategory[category_name],MATCH("Women's Apparel",tblModelCategory[category_name],0)) -> Women's Apparel | B8: =SUMIFS(tblModelCategory[lines],tblModelCategory[category_name],A8) -> 23635 | C8: =SUMIFS(tblModelCategory[return_count],tblModelCategory[category_name],A8) -> 1588 | D8: =C8/B8 -> 0.067188492 | E8: =SUMIFS(tblModelCategory[refund_amount],tblModelCategory[category_name],A8) -> 10512341 | F8: =IF(D8>$I$1,"Above Average - Investigate Return Reasons","Within Normal Range") -> Above Average - Investigate Return Reasons
A9: =INDEX(tblModelCategory[category_name],MATCH("Laptops & Computers",tblModelCategory[category_name],0)) -> Laptops & Computers | B9: =SUMIFS(tblModelCategory[lines],tblModelCategory[category_name],A9) -> 23849 | C9: =SUMIFS(tblModelCategory[return_count],tblModelCategory[category_name],A9) -> 1108 | D9: =C9/B9 -> 0.046458971 | E9: =SUMIFS(tblModelCategory[refund_amount],tblModelCategory[category_name],A9) -> 120142131 | F9: =IF(D9>$I$1,"Above Average - Investigate Return Reasons","Within Normal Range") -> Above Average - Investigate Return Reasons
A10: =INDEX(tblModelCategory[category_name],MATCH("Mobiles & Accessories",tblModelCategory[category_name],0)) -> Mobiles & Accessories | B10: =SUMIFS(tblModelCategory[lines],tblModelCategory[category_name],A10) -> 30469 | C10: =SUMIFS(tblModelCategory[return_count],tblModelCategory[category_name],A10) -> 1326 | D10: =C10/B10 -> 0.043519643 | E10: =SUMIFS(tblModelCategory[refund_amount],tblModelCategory[category_name],A10) -> 69832084 | F10: =IF(D10>$I$1,"Above Average - Investigate Return Reasons","Within Normal Range") -> Above Average - Investigate Return Reasons
A11: =INDEX(tblModelCategory[category_name],MATCH("Televisions",tblModelCategory[category_name],0)) -> Televisions | B11: =SUMIFS(tblModelCategory[lines],tblModelCategory[category_name],A11) -> 38075 | C11: =SUMIFS(tblModelCategory[return_count],tblModelCategory[category_name],A11) -> 1575 | D11: =C11/B11 -> 0.041365726 | E11: =SUMIFS(tblModelCategory[refund_amount],tblModelCategory[category_name],A11) -> 88979549 | F11: =IF(D11>$I$1,"Above Average - Investigate Return Reasons","Within Normal Range") -> Above Average - Investigate Return Reasons
A12: =INDEX(tblModelCategory[category_name],MATCH("Home Audio",tblModelCategory[category_name],0)) -> Home Audio | B12: =SUMIFS(tblModelCategory[lines],tblModelCategory[category_name],A12) -> 28038 | C12: =SUMIFS(tblModelCategory[return_count],tblModelCategory[category_name],A12) -> 1084 | D12: =C12/B12 -> 0.038661816 | E12: =SUMIFS(tblModelCategory[refund_amount],tblModelCategory[category_name],A12) -> 18808093 | F12: =IF(D12>$I$1,"Above Average - Investigate Return Reasons","Within Normal Range") -> Above Average - Investigate Return Reasons
A13: =INDEX(tblModelCategory[category_name],MATCH("Air Conditioners & Coolers",tblModelCategory[category_name],0)) -> Air Conditioners & Coolers | B13: =SUMIFS(tblModelCategory[lines],tblModelCategory[category_name],A13) -> 20282 | C13: =SUMIFS(tblModelCategory[return_count],tblModelCategory[category_name],A13) -> 730 | D13: =C13/B13 -> 0.035992506 | E13: =SUMIFS(tblModelCategory[refund_amount],tblModelCategory[category_name],A13) -> 47019318 | F13: =IF(D13>$I$1,"Above Average - Investigate Return Reasons","Within Normal Range") -> Within Normal Range
A14: =INDEX(tblModelCategory[category_name],MATCH("Refrigerators",tblModelCategory[category_name],0)) -> Refrigerators | B14: =SUMIFS(tblModelCategory[lines],tblModelCategory[category_name],A14) -> 60041 | C14: =SUMIFS(tblModelCategory[return_count],tblModelCategory[category_name],A14) -> 2129 | D14: =C14/B14 -> 0.035459103 | E14: =SUMIFS(tblModelCategory[refund_amount],tblModelCategory[category_name],A14) -> 139694518 | F14: =IF(D14>$I$1,"Above Average - Investigate Return Reasons","Within Normal Range") -> Within Normal Range
A15: =INDEX(tblModelCategory[category_name],MATCH("Washing Machines",tblModelCategory[category_name],0)) -> Washing Machines | B15: =SUMIFS(tblModelCategory[lines],tblModelCategory[category_name],A15) -> 20087 | C15: =SUMIFS(tblModelCategory[return_count],tblModelCategory[category_name],A15) -> 682 | D15: =C15/B15 -> 0.033952307 | E15: =SUMIFS(tblModelCategory[refund_amount],tblModelCategory[category_name],A15) -> 39892561 | F15: =IF(D15>$I$1,"Above Average - Investigate Return Reasons","Within Normal Range") -> Within Normal Range
A16: =INDEX(tblModelCategory[category_name],MATCH("Toys & Games",tblModelCategory[category_name],0)) -> Toys & Games | B16: =SUMIFS(tblModelCategory[lines],tblModelCategory[category_name],A16) -> 30724 | C16: =SUMIFS(tblModelCategory[return_count],tblModelCategory[category_name],A16) -> 964 | D16: =C16/B16 -> 0.031376123 | E16: =SUMIFS(tblModelCategory[refund_amount],tblModelCategory[category_name],A16) -> 3945164 | F16: =IF(D16>$I$1,"Above Average - Investigate Return Reasons","Within Normal Range") -> Within Normal Range
A17: =INDEX(tblModelCategory[category_name],MATCH("Furniture",tblModelCategory[category_name],0)) -> Furniture | B17: =SUMIFS(tblModelCategory[lines],tblModelCategory[category_name],A17) -> 36122 | C17: =SUMIFS(tblModelCategory[return_count],tblModelCategory[category_name],A17) -> 1131 | D17: =C17/B17 -> 0.031310559 | E17: =SUMIFS(tblModelCategory[refund_amount],tblModelCategory[category_name],A17) -> 59141680 | F17: =IF(D17>$I$1,"Above Average - Investigate Return Reasons","Within Normal Range") -> Within Normal Range
A18: =INDEX(tblModelCategory[category_name],MATCH("Festive & Gifting",tblModelCategory[category_name],0)) -> Festive & Gifting | B18: =SUMIFS(tblModelCategory[lines],tblModelCategory[category_name],A18) -> 41399 | C18: =SUMIFS(tblModelCategory[return_count],tblModelCategory[category_name],A18) -> 1238 | D18: =C18/B18 -> 0.029904104 | E18: =SUMIFS(tblModelCategory[refund_amount],tblModelCategory[category_name],A18) -> 6073270 | F18: =IF(D18>$I$1,"Above Average - Investigate Return Reasons","Within Normal Range") -> Within Normal Range
A19: =INDEX(tblModelCategory[category_name],MATCH("Home Decor",tblModelCategory[category_name],0)) -> Home Decor | B19: =SUMIFS(tblModelCategory[lines],tblModelCategory[category_name],A19) -> 21871 | C19: =SUMIFS(tblModelCategory[return_count],tblModelCategory[category_name],A19) -> 629 | D19: =C19/B19 -> 0.028759545 | E19: =SUMIFS(tblModelCategory[refund_amount],tblModelCategory[category_name],A19) -> 4586453 | F19: =IF(D19>$I$1,"Above Average - Investigate Return Reasons","Within Normal Range") -> Within Normal Range
A20: =INDEX(tblModelCategory[category_name],MATCH("Kitchen Appliances",tblModelCategory[category_name],0)) -> Kitchen Appliances | B20: =SUMIFS(tblModelCategory[lines],tblModelCategory[category_name],A20) -> 36206 | C20: =SUMIFS(tblModelCategory[return_count],tblModelCategory[category_name],A20) -> 1037 | D20: =C20/B20 -> 0.028641662 | E20: =SUMIFS(tblModelCategory[refund_amount],tblModelCategory[category_name],A20) -> 16974845 | F20: =IF(D20>$I$1,"Above Average - Investigate Return Reasons","Within Normal Range") -> Within Normal Range
A21: =INDEX(tblModelCategory[category_name],MATCH("Heaters & Winter Appliances",tblModelCategory[category_name],0)) -> Heaters & Winter Appliances | B21: =SUMIFS(tblModelCategory[lines],tblModelCategory[category_name],A21) -> 26198 | C21: =SUMIFS(tblModelCategory[return_count],tblModelCategory[category_name],A21) -> 703 | D21: =C21/B21 -> 0.026834109 | E21: =SUMIFS(tblModelCategory[refund_amount],tblModelCategory[category_name],A21) -> 6392296 | F21: =IF(D21>$I$1,"Above Average - Investigate Return Reasons","Within Normal Range") -> Within Normal Range
A22: =INDEX(tblModelCategory[category_name],MATCH("Kitchenware",tblModelCategory[category_name],0)) -> Kitchenware | B22: =SUMIFS(tblModelCategory[lines],tblModelCategory[category_name],A22) -> 29968 | C22: =SUMIFS(tblModelCategory[return_count],tblModelCategory[category_name],A22) -> 784 | D22: =C22/B22 -> 0.026161239 | E22: =SUMIFS(tblModelCategory[refund_amount],tblModelCategory[category_name],A22) -> 3284893 | F22: =IF(D22>$I$1,"Above Average - Investigate Return Reasons","Within Normal Range") -> Within Normal Range
A23: =INDEX(tblModelCategory[category_name],MATCH("Personal Care",tblModelCategory[category_name],0)) -> Personal Care | B23: =SUMIFS(tblModelCategory[lines],tblModelCategory[category_name],A23) -> 35175 | C23: =SUMIFS(tblModelCategory[return_count],tblModelCategory[category_name],A23) -> 266 | D23: =C23/B23 -> 0.0075621891 | E23: =SUMIFS(tblModelCategory[refund_amount],tblModelCategory[category_name],A23) -> 458580 | F23: =IF(D23>$I$1,"Above Average - Investigate Return Reasons","Within Normal Range") -> Within Normal Range
A24: =INDEX(tblModelCategory[category_name],MATCH("Groceries & Staples",tblModelCategory[category_name],0)) -> Groceries & Staples | B24: =SUMIFS(tblModelCategory[lines],tblModelCategory[category_name],A24) -> 32688 | C24: =SUMIFS(tblModelCategory[return_count],tblModelCategory[category_name],A24) -> 244 | D24: =C24/B24 -> 0.007464513 | E24: =SUMIFS(tblModelCategory[refund_amount],tblModelCategory[category_name],A24) -> 278695 | F24: =IF(D24>$I$1,"Above Average - Investigate Return Reasons","Within Normal Range") -> Within Normal Range

Sheet 07_KPI_SLA
A1: Q6 — Delivery SLA by Region & Courier (OPERATIONAL RISK INDICATOR ONLY) | H1: Overall Avg Late Rate % | I1: =AVERAGE(tblModelSLA[late_rate]) -> 0.090805
A4: Region | B4: Courier | C4: Shipments | D4: Late Count | E4: Late Rate % | F4: Flag
A5: Maharashtra | B5: XpressBees | C5: =SUMIFS(tblModelSLA[shipment_count],tblModelSLA[region_name],A5,tblModelSLA[courier_partner],B5) -> 5310 | D5: =SUMIFS(tblModelSLA[late_count],tblModelSLA[region_name],A5,tblModelSLA[courier_partner],B5) -> 732 | E5: =D5/C5 -> 0.13785311 | F5: =IF(E5>$I$1,"Above Average Late Rate","Within Normal Range") -> Above Average Late Rate
A6: Maharashtra | B6: Delhivery | C6: =SUMIFS(tblModelSLA[shipment_count],tblModelSLA[region_name],A6,tblModelSLA[courier_partner],B6) -> 5345 | D6: =SUMIFS(tblModelSLA[late_count],tblModelSLA[region_name],A6,tblModelSLA[courier_partner],B6) -> 717 | E6: =D6/C6 -> 0.13414406 | F6: =IF(E6>$I$1,"Above Average Late Rate","Within Normal Range") -> Above Average Late Rate
A7: Maharashtra | B7: BlueDart Express | C7: =SUMIFS(tblModelSLA[shipment_count],tblModelSLA[region_name],A7,tblModelSLA[courier_partner],B7) -> 5576 | D7: =SUMIFS(tblModelSLA[late_count],tblModelSLA[region_name],A7,tblModelSLA[courier_partner],B7) -> 743 | E7: =D7/C7 -> 0.13324964 | F7: =IF(E7>$I$1,"Above Average Late Rate","Within Normal Range") -> Above Average Late Rate
A8: Maharashtra | B8: DTDC | C8: =SUMIFS(tblModelSLA[shipment_count],tblModelSLA[region_name],A8,tblModelSLA[courier_partner],B8) -> 5446 | D8: =SUMIFS(tblModelSLA[late_count],tblModelSLA[region_name],A8,tblModelSLA[courier_partner],B8) -> 722 | E8: =D8/C8 -> 0.13257437 | F8: =IF(E8>$I$1,"Above Average Late Rate","Within Normal Range") -> Above Average Late Rate
A9: Maharashtra | B9: Ekart Logistics | C9: =SUMIFS(tblModelSLA[shipment_count],tblModelSLA[region_name],A9,tblModelSLA[courier_partner],B9) -> 5418 | D9: =SUMIFS(tblModelSLA[late_count],tblModelSLA[region_name],A9,tblModelSLA[courier_partner],B9) -> 687 | E9: =D9/C9 -> 0.12679956 | F9: =IF(E9>$I$1,"Above Average Late Rate","Within Normal Range") -> Above Average Late Rate
A10: Rajasthan | B10: Delhivery | C10: =SUMIFS(tblModelSLA[shipment_count],tblModelSLA[region_name],A10,tblModelSLA[courier_partner],B10) -> 4064 | D10: =SUMIFS(tblModelSLA[late_count],tblModelSLA[region_name],A10,tblModelSLA[courier_partner],B10) -> 449 | E10: =D10/C10 -> 0.11048228 | F10: =IF(E10>$I$1,"Above Average Late Rate","Within Normal Range") -> Above Average Late Rate
A11: Rajasthan | B11: BlueDart Express | C11: =SUMIFS(tblModelSLA[shipment_count],tblModelSLA[region_name],A11,tblModelSLA[courier_partner],B11) -> 4207 | D11: =SUMIFS(tblModelSLA[late_count],tblModelSLA[region_name],A11,tblModelSLA[courier_partner],B11) -> 447 | E11: =D11/C11 -> 0.10625149 | F11: =IF(E11>$I$1,"Above Average Late Rate","Within Normal Range") -> Above Average Late Rate
A12: Rajasthan | B12: DTDC | C12: =SUMIFS(tblModelSLA[shipment_count],tblModelSLA[region_name],A12,tblModelSLA[courier_partner],B12) -> 4076 | D12: =SUMIFS(tblModelSLA[late_count],tblModelSLA[region_name],A12,tblModelSLA[courier_partner],B12) -> 428 | E12: =D12/C12 -> 0.10500491 | F12: =IF(E12>$I$1,"Above Average Late Rate","Within Normal Range") -> Above Average Late Rate
A13: Rajasthan | B13: Ekart Logistics | C13: =SUMIFS(tblModelSLA[shipment_count],tblModelSLA[region_name],A13,tblModelSLA[courier_partner],B13) -> 4091 | D13: =SUMIFS(tblModelSLA[late_count],tblModelSLA[region_name],A13,tblModelSLA[courier_partner],B13) -> 427 | E13: =D13/C13 -> 0.10437546 | F13: =IF(E13>$I$1,"Above Average Late Rate","Within Normal Range") -> Above Average Late Rate
A14: Karnataka | B14: XpressBees | C14: =SUMIFS(tblModelSLA[shipment_count],tblModelSLA[region_name],A14,tblModelSLA[courier_partner],B14) -> 5247 | D14: =SUMIFS(tblModelSLA[late_count],tblModelSLA[region_name],A14,tblModelSLA[courier_partner],B14) -> 541 | E14: =D14/C14 -> 0.10310654 | F14: =IF(E14>$I$1,"Above Average Late Rate","Within Normal Range") -> Above Average Late Rate
A15: Rajasthan | B15: XpressBees | C15: =SUMIFS(tblModelSLA[shipment_count],tblModelSLA[region_name],A15,tblModelSLA[courier_partner],B15) -> 4334 | D15: =SUMIFS(tblModelSLA[late_count],tblModelSLA[region_name],A15,tblModelSLA[courier_partner],B15) -> 446 | E15: =D15/C15 -> 0.10290725 | F15: =IF(E15>$I$1,"Above Average Late Rate","Within Normal Range") -> Above Average Late Rate
A16: Karnataka | B16: BlueDart Express | C16: =SUMIFS(tblModelSLA[shipment_count],tblModelSLA[region_name],A16,tblModelSLA[courier_partner],B16) -> 5349 | D16: =SUMIFS(tblModelSLA[late_count],tblModelSLA[region_name],A16,tblModelSLA[courier_partner],B16) -> 541 | E16: =D16/C16 -> 0.1011404 | F16: =IF(E16>$I$1,"Above Average Late Rate","Within Normal Range") -> Above Average Late Rate
... A64: Odisha-Jharkhand | B64: Delhivery | C64: =SUMIFS(tblModelSLA[shipment_count],tblModelSLA[region_name],A64,tblModelSLA[courier_partner],B64) -> 2996 | D64: =SUMIFS(tblModelSLA[late_count],tblModelSLA[region_name],A64,tblModelSLA[courier_partner],B64) -> 196 | E64: =D64/C64 -> 0.065420561 | F64: =IF(E64>$I$1,"Above Average Late Rate","Within Normal Range") -> Within Normal Range

Sheet 08_KPI_Promotion
A1: Q8 — Promotion Effectiveness: Continue vs Discontinue | K1: Median Margin Impact (pp) | L1: =MEDIAN(G5:G204) -> -0.1395
K2: Median AOV Lift % | L2: =MEDIAN(H5:H204) -> 0.00085
K3: 25th Pctile Margin Impact (pp) - worst quartile | L3: =QUARTILE(G5:G204,1) -> -0.200675
A4: Promotion | B4: Type | C4: Discount % | D4: Revenue | E4: Margin % (Promo) | F4: Margin % (Baseline, same category) | G4: Margin Impact (pp) | H4: AOV Lift % | I4: Decision
A5: =INDEX(tblModelPromotion[promotion_name],MATCH("Clearance May2021 - 5% Off",tblModelPromotion[promotion_name],0)) -> Clearance May2021 - 5% Off | B5: =INDEX(tblModelPromotion[promotion_type],MATCH(A5,tblModelPromotion[promotion_name],0)) -> Clearance | C5: =INDEX(tblModelPromotion[discount_pct],MATCH(A5,tblModelPromotion[promotion_name],0))/100 -> 0.05 | D5: =INDEX(tblModelPromotion[revenue],MATCH(A5,tblModelPromotion[promotion_name],0)) -> 24348964 | E5: =INDEX(tblModelPromotion[margin_pct],MATCH(A5,tblModelPromotion[promotion_name],0)) -> 0.1902 | F5: =INDEX(tblModelPromotion[baseline_margin_pct],MATCH(A5,tblModelPromotion[promotion_name],0)) -> 0.2226 | G5: =E5-F5 -> -0.0324 | H5: =INDEX(tblModelPromotion[aov_lift_pct],MATCH(A5,tblModelPromotion[promotion_name],0)) -> 0.0771 | I5: =IF(AND(G5>=$L$1,H5>=$L$2),"Continue - efficient lift for margin cost",IF(AND(G5<=$L$3,H5<$L$2),"Discontinue - high margin cost, weak lift","Review - mixed signal")) -> Continue - efficient lift for margin cost
A6: =INDEX(tblModelPromotion[promotion_name],MATCH("Flash Sale Mar2022 - 5% Off",tblModelPromotion[promotion_name],0)) -> Flash Sale Mar2022 - 5% Off | B6: =INDEX(tblModelPromotion[promotion_type],MATCH(A6,tblModelPromotion[promotion_name],0)) -> Flash Sale | C6: =INDEX(tblModelPromotion[discount_pct],MATCH(A6,tblModelPromotion[promotion_name],0))/100 -> 0.05 | D6: =INDEX(tblModelPromotion[revenue],MATCH(A6,tblModelPromotion[promotion_name],0)) -> 33945695 | E6: =INDEX(tblModelPromotion[margin_pct],MATCH(A6,tblModelPromotion[promotion_name],0)) -> 0.1874 | F6: =INDEX(tblModelPromotion[baseline_margin_pct],MATCH(A6,tblModelPromotion[promotion_name],0)) -> 0.2226 | G6: =E6-F6 -> -0.0352 | H6: =INDEX(tblModelPromotion[aov_lift_pct],MATCH(A6,tblModelPromotion[promotion_name],0)) -> 0.162 | I6: =IF(AND(G6>=$L$1,H6>=$L$2),"Continue - efficient lift for margin cost",IF(AND(G6<=$L$3,H6<$L$2),"Discontinue - high margin cost, weak lift","Review - mixed signal")) -> Continue - efficient lift for margin cost
A7: =INDEX(tblModelPromotion[promotion_name],MATCH("Flash Sale Oct2021 - 5% Off",tblModelPromotion[promotion_name],0)) -> Flash Sale Oct2021 - 5% Off | B7: =INDEX(tblModelPromotion[promotion_type],MATCH(A7,tblModelPromotion[promotion_name],0)) -> Flash Sale | C7: =INDEX(tblModelPromotion[discount_pct],MATCH(A7,tblModelPromotion[promotion_name],0))/100 -> 0.05 | D7: =INDEX(tblModelPromotion[revenue],MATCH(A7,tblModelPromotion[promotion_name],0)) -> 31864105 | E7: =INDEX(tblModelPromotion[margin_pct],MATCH(A7,tblModelPromotion[promotion_name],0)) -> 0.1866 | F7: =INDEX(tblModelPromotion[baseline_margin_pct],MATCH(A7,tblModelPromotion[promotion_name],0)) -> 0.2226 | G7: =E7-F7 -> -0.036 | H7: =INDEX(tblModelPromotion[aov_lift_pct],MATCH(A7,tblModelPromotion[promotion_name],0)) -> 0.0399 | I7: =IF(AND(G7>=$L$1,H7>=$L$2),"Continue - efficient lift for margin cost",IF(AND(G7<=$L$3,H7<$L$2),"Discontinue - high margin cost, weak lift","Review - mixed signal")) -> Continue - efficient lift for margin cost
A8: =INDEX(tblModelPromotion[promotion_name],MATCH("Festive Feb2023 - 5% Off",tblModelPromotion[promotion_name],0)) -> Festive Feb2023 - 5% Off | B8: =INDEX(tblModelPromotion[promotion_type],MATCH(A8,tblModelPromotion[promotion_name],0)) -> Festive | C8: =INDEX(tblModelPromotion[discount_pct],MATCH(A8,tblModelPromotion[promotion_name],0))/100 -> 0.05 | D8: =INDEX(tblModelPromotion[revenue],MATCH(A8,tblModelPromotion[promotion_name],0)) -> 14777330 | E8: =INDEX(tblModelPromotion[margin_pct],MATCH(A8,tblModelPromotion[promotion_name],0)) -> 0.1859 | F8: =INDEX(tblModelPromotion[baseline_margin_pct],MATCH(A8,tblModelPromotion[promotion_name],0)) -> 0.2226 | G8: =E8-F8 -> -0.0367 | H8: =INDEX(tblModelPromotion[aov_lift_pct],MATCH(A8,tblModelPromotion[promotion_name],0)) -> -0.0882 | I8: =IF(AND(G8>=$L$1,H8>=$L$2),"Continue - efficient lift for margin cost",IF(AND(G8<=$L$3,H8<$L$2),"Discontinue - high margin cost, weak lift","Review - mixed signal")) -> Review - mixed signal
A9: =INDEX(tblModelPromotion[promotion_name],MATCH("Seasonal Feb2021 - 5% Off",tblModelPromotion[promotion_name],0)) -> Seasonal Feb2021 - 5% Off | B9: =INDEX(tblModelPromotion[promotion_type],MATCH(A9,tblModelPromotion[promotion_name],0)) -> Seasonal | C9: =INDEX(tblModelPromotion[discount_pct],MATCH(A9,tblModelPromotion[promotion_name],0))/100 -> 0.05 | D9: =INDEX(tblModelPromotion[revenue],MATCH(A9,tblModelPromotion[promotion_name],0)) -> 24189378 | E9: =INDEX(tblModelPromotion[margin_pct],MATCH(A9,tblModelPromotion[promotion_name],0)) -> 0.1855 | F9: =INDEX(tblModelPromotion[baseline_margin_pct],MATCH(A9,tblModelPromotion[promotion_name],0)) -> 0.2226 | G9: =E9-F9 -> -0.0371 | H9: =INDEX(tblModelPromotion[aov_lift_pct],MATCH(A9,tblModelPromotion[promotion_name],0)) -> 0.0732 | I9: =IF(AND(G9>=$L$1,H9>=$L$2),"Continue - efficient lift for margin cost",IF(AND(G9<=$L$3,H9<$L$2),"Discontinue - high margin cost, weak lift","Review - mixed signal")) -> Continue - efficient lift for margin cost
A10: =INDEX(tblModelPromotion[promotion_name],MATCH("Flash Sale Nov2024 - 5% Off",tblModelPromotion[promotion_name],0)) -> Flash Sale Nov2024 - 5% Off | B10: =INDEX(tblModelPromotion[promotion_type],MATCH(A10,tblModelPromotion[promotion_name],0)) -> Flash Sale | C10: =INDEX(tblModelPromotion[discount_pct],MATCH(A10,tblModelPromotion[promotion_name],0))/100 -> 0.05 | D10: =INDEX(tblModelPromotion[revenue],MATCH(A10,tblModelPromotion[promotion_name],0)) -> 58224407 | E10: =INDEX(tblModelPromotion[margin_pct],MATCH(A10,tblModelPromotion[promotion_name],0)) -> 0.1851 | F10: =INDEX(tblModelPromotion[baseline_margin_pct],MATCH(A10,tblModelPromotion[promotion_name],0)) -> 0.2226 | G10: =E10-F10 -> -0.0375 | H10: =INDEX(tblModelPromotion[aov_lift_pct],MATCH(A10,tblModelPromotion[promotion_name],0)) -> 0.0083 | I10: =IF(AND(G10>=$L$1,H10>=$L$2),"Continue - efficient lift for margin cost",IF(AND(G10<=$L$3,H10<$L$2),"Discontinue - high margin cost, weak lift","Review - mixed signal")) -> Continue - efficient lift for margin cost
A11: =INDEX(tblModelPromotion[promotion_name],MATCH("Festive Mar2021 - 5% Off",tblModelPromotion[promotion_name],0)) -> Festive Mar2021 - 5% Off | B11: =INDEX(tblModelPromotion[promotion_type],MATCH(A11,tblModelPromotion[promotion_name],0)) -> Festive | C11: =INDEX(tblModelPromotion[discount_pct],MATCH(A11,tblModelPromotion[promotion_name],0))/100 -> 0.05 | D11: =INDEX(tblModelPromotion[revenue],MATCH(A11,tblModelPromotion[promotion_name],0)) -> 63050549 | E11: =INDEX(tblModelPromotion[margin_pct],MATCH(A11,tblModelPromotion[promotion_name],0)) -> 0.1846 | F11: =INDEX(tblModelPromotion[baseline_margin_pct],MATCH(A11,tblModelPromotion[promotion_name],0)) -> 0.2226 | G11: =E11-F11 -> -0.038 | H11: =INDEX(tblModelPromotion[aov_lift_pct],MATCH(A11,tblModelPromotion[promotion_name],0)) -> 0.1142 | I11: =IF(AND(G11>=$L$1,H11>=$L$2),"Continue - efficient lift for margin cost",IF(AND(G11<=$L$3,H11<$L$2),"Discontinue - high margin cost, weak lift","Review - mixed signal")) -> Continue - efficient lift for margin cost
A12: =INDEX(tblModelPromotion[promotion_name],MATCH("Seasonal Apr2022 - 5% Off",tblModelPromotion[promotion_name],0)) -> Seasonal Apr2022 - 5% Off | B12: =INDEX(tblModelPromotion[promotion_type],MATCH(A12,tblModelPromotion[promotion_name],0)) -> Seasonal | C12: =INDEX(tblModelPromotion[discount_pct],MATCH(A12,tblModelPromotion[promotion_name],0))/100 -> 0.05 | D12: =INDEX(tblModelPromotion[revenue],MATCH(A12,tblModelPromotion[promotion_name],0)) -> 32420135 | E12: =INDEX(tblModelPromotion[margin_pct],MATCH(A12,tblModelPromotion[promotion_name],0)) -> 0.184 | F12: =INDEX(tblModelPromotion[baseline_margin_pct],MATCH(A12,tblModelPromotion[promotion_name],0)) -> 0.2226 | G12: =E12-F12 -> -0.0386 | H12: =INDEX(tblModelPromotion[aov_lift_pct],MATCH(A12,tblModelPromotion[promotion_name],0)) -> 0.1756 | I12: =IF(AND(G12>=$L$1,H12>=$L$2),"Continue - efficient lift for margin cost",IF(AND(G12<=$L$3,H12<$L$2),"Discontinue - high margin cost, weak lift","Review - mixed signal")) -> Continue - efficient lift for margin cost
A13: =INDEX(tblModelPromotion[promotion_name],MATCH("Flash Sale Feb2022 - 5% Off",tblModelPromotion[promotion_name],0)) -> Flash Sale Feb2022 - 5% Off | B13: =INDEX(tblModelPromotion[promotion_type],MATCH(A13,tblModelPromotion[promotion_name],0)) -> Flash Sale | C13: =INDEX(tblModelPromotion[discount_pct],MATCH(A13,tblModelPromotion[promotion_name],0))/100 -> 0.05 | D13: =INDEX(tblModelPromotion[revenue],MATCH(A13,tblModelPromotion[promotion_name],0)) -> 31109407 | E13: =INDEX(tblModelPromotion[margin_pct],MATCH(A13,tblModelPromotion[promotion_name],0)) -> 0.1837 | F13: =INDEX(tblModelPromotion[baseline_margin_pct],MATCH(A13,tblModelPromotion[promotion_name],0)) -> 0.2226 | G13: =E13-F13 -> -0.0389 | H13: =INDEX(tblModelPromotion[aov_lift_pct],MATCH(A13,tblModelPromotion[promotion_name],0)) -> 0.1365 | I13: =IF(AND(G13>=$L$1,H13>=$L$2),"Continue - efficient lift for margin cost",IF(AND(G13<=$L$3,H13<$L$2),"Discontinue - high margin cost, weak lift","Review - mixed signal")) -> Continue - efficient lift for margin cost
A14: =INDEX(tblModelPromotion[promotion_name],MATCH("Clearance Mar2022 - 5% Off",tblModelPromotion[promotion_name],0)) -> Clearance Mar2022 - 5% Off | B14: =INDEX(tblModelPromotion[promotion_type],MATCH(A14,tblModelPromotion[promotion_name],0)) -> Clearance | C14: =INDEX(tblModelPromotion[discount_pct],MATCH(A14,tblModelPromotion[promotion_name],0))/100 -> 0.05 | D14: =INDEX(tblModelPromotion[revenue],MATCH(A14,tblModelPromotion[promotion_name],0)) -> 31226578 | E14: =INDEX(tblModelPromotion[margin_pct],MATCH(A14,tblModelPromotion[promotion_name],0)) -> 0.1836 | F14: =INDEX(tblModelPromotion[baseline_margin_pct],MATCH(A14,tblModelPromotion[promotion_name],0)) -> 0.2226 | G14: =E14-F14 -> -0.039 | H14: =INDEX(tblModelPromotion[aov_lift_pct],MATCH(A14,tblModelPromotion[promotion_name],0)) -> 0.1077 | I14: =IF(AND(G14>=$L$1,H14>=$L$2),"Continue - efficient lift for margin cost",IF(AND(G14<=$L$3,H14<$L$2),"Discontinue - high margin cost, weak lift","Review - mixed signal")) -> Continue - efficient lift for margin cost
A15: =INDEX(tblModelPromotion[promotion_name],MATCH("Seasonal Dec2021 - 5% Off",tblModelPromotion[promotion_name],0)) -> Seasonal Dec2021 - 5% Off | B15: =INDEX(tblModelPromotion[promotion_type],MATCH(A15,tblModelPromotion[promotion_name],0)) -> Seasonal | C15: =INDEX(tblModelPromotion[discount_pct],MATCH(A15,tblModelPromotion[promotion_name],0))/100 -> 0.05 | D15: =INDEX(tblModelPromotion[revenue],MATCH(A15,tblModelPromotion[promotion_name],0)) -> 30999756 | E15: =INDEX(tblModelPromotion[margin_pct],MATCH(A15,tblModelPromotion[promotion_name],0)) -> 0.1832 | F15: =INDEX(tblModelPromotion[baseline_margin_pct],MATCH(A15,tblModelPromotion[promotion_name],0)) -> 0.2226 | G15: =E15-F15 -> -0.0394 | H15: =INDEX(tblModelPromotion[aov_lift_pct],MATCH(A15,tblModelPromotion[promotion_name],0)) -> 0.1269 | I15: =IF(AND(G15>=$L$1,H15>=$L$2),"Continue - efficient lift for margin cost",IF(AND(G15<=$L$3,H15<$L$2),"Discontinue - high margin cost, weak lift","Review - mixed signal")) -> Continue - efficient lift for margin cost
A16: =INDEX(tblModelPromotion[promotion_name],MATCH("Flash Sale Dec2021 - 5% Off",tblModelPromotion[promotion_name],0)) -> Flash Sale Dec2021 - 5% Off | B16: =INDEX(tblModelPromotion[promotion_type],MATCH(A16,tblModelPromotion[promotion_name],0)) -> Flash Sale | C16: =INDEX(tblModelPromotion[discount_pct],MATCH(A16,tblModelPromotion[promotion_name],0))/100 -> 0.05 | D16: =INDEX(tblModelPromotion[revenue],MATCH(A16,tblModelPromotion[promotion_name],0)) -> 29084891 | E16: =INDEX(tblModelPromotion[margin_pct],MATCH(A16,tblModelPromotion[promotion_name],0)) -> 0.1826 | F16: =INDEX(tblModelPromotion[baseline_margin_pct],MATCH(A16,tblModelPromotion[promotion_name],0)) -> 0.2226 | G16: =E16-F16 -> -0.04 | H16: =INDEX(tblModelPromotion[aov_lift_pct],MATCH(A16,tblModelPromotion[promotion_name],0)) -> 0.0652 | I16: =IF(AND(G16>=$L$1,H16>=$L$2),"Continue - efficient lift for margin cost",IF(AND(G16<=$L$3,H16<$L$2),"Discontinue - high margin cost, weak lift","Review - mixed signal")) -> Continue - efficient lift for margin cost
A17: =INDEX(tblModelPromotion[promotion_name],MATCH("Festive Oct2021 - 5% Off",tblModelPromotion[promotion_name],0)) -> Festive Oct2021 - 5% Off | B17: =INDEX(tblModelPromotion[promotion_type],MATCH(A17,tblModelPromotion[promotion_name],0)) -> Festive | C17: =INDEX(tblModelPromotion[discount_pct],MATCH(A17,tblModelPromotion[promotion_name],0))/100 -> 0.05 | D17: =INDEX(tblModelPromotion[revenue],MATCH(A17,tblModelPromotion[promotion_name],0)) -> 136643946 | E17: =INDEX(tblModelPromotion[margin_pct],MATCH(A17,tblModelPromotion[promotion_name],0)) -> 0.1819 | F17: =INDEX(tblModelPromotion[baseline_margin_pct],MATCH(A17,tblModelPromotion[promotion_name],0)) -> 0.2226 | G17: =E17-F17 -> -0.0407 | H17: =INDEX(tblModelPromotion[aov_lift_pct],MATCH(A17,tblModelPromotion[promotion_name],0)) -> 0.0835 | I17: =IF(AND(G17>=$L$1,H17>=$L$2),"Continue - efficient lift for margin cost",IF(AND(G17<=$L$3,H17<$L$2),"Discontinue - high margin cost, weak lift","Review - mixed signal")) -> Continue - efficient lift for margin cost
A18: =INDEX(tblModelPromotion[promotion_name],MATCH("Seasonal Nov2024 - 5% Off",tblModelPromotion[promotion_name],0)) -> Seasonal Nov2024 - 5% Off | B18: =INDEX(tblModelPromotion[promotion_type],MATCH(A18,tblModelPromotion[promotion_name],0)) -> Seasonal | C18: =INDEX(tblModelPromotion[discount_pct],MATCH(A18,tblModelPromotion[promotion_name],0))/100 -> 0.05 | D18: =INDEX(tblModelPromotion[revenue],MATCH(A18,tblModelPromotion[promotion_name],0)) -> 261412791 | E18: =INDEX(tblModelPromotion[margin_pct],MATCH(A18,tblModelPromotion[promotion_name],0)) -> 0.1814 | F18: =INDEX(tblModelPromotion[baseline_margin_pct],MATCH(A18,tblModelPromotion[promotion_name],0)) -> 0.2226 | G18: =E18-F18 -> -0.0412 | H18: =INDEX(tblModelPromotion[aov_lift_pct],MATCH(A18,tblModelPromotion[promotion_name],0)) -> 0.1265 | I18: =IF(AND(G18>=$L$1,H18>=$L$2),"Continue - efficient lift for margin cost",IF(AND(G18<=$L$3,H18<$L$2),"Discontinue - high margin cost, weak lift","Review - mixed signal")) -> Continue - efficient lift for margin cost
A19: =INDEX(tblModelPromotion[promotion_name],MATCH("Festive Nov2022 - 5% Off",tblModelPromotion[promotion_name],0)) -> Festive Nov2022 - 5% Off | B19: =INDEX(tblModelPromotion[promotion_type],MATCH(A19,tblModelPromotion[promotion_name],0)) -> Festive | C19: =INDEX(tblModelPromotion[discount_pct],MATCH(A19,tblModelPromotion[promotion_name],0))/100 -> 0.05 | D19: =INDEX(tblModelPromotion[revenue],MATCH(A19,tblModelPromotion[promotion_name],0)) -> 150307327 | E19: =INDEX(tblModelPromotion[margin_pct],MATCH(A19,tblModelPromotion[promotion_name],0)) -> 0.1813 | F19: =INDEX(tblModelPromotion[baseline_margin_pct],MATCH(A19,tblModelPromotion[promotion_name],0)) -> 0.2226 | G19: =E19-F19 -> -0.0413 | H19: =INDEX(tblModelPromotion[aov_lift_pct],MATCH(A19,tblModelPromotion[promotion_name],0)) -> 0.1605 | I19: =IF(AND(G19>=$L$1,H19>=$L$2),"Continue - efficient lift for margin cost",IF(AND(G19<=$L$3,H19<$L$2),"Discontinue - high margin cost, weak lift","Review - mixed signal")) -> Continue - efficient lift for margin cost
A20: =INDEX(tblModelPromotion[promotion_name],MATCH("Festive Jun2024 - 5% Off",tblModelPromotion[promotion_name],0)) -> Festive Jun2024 - 5% Off | B20: =INDEX(tblModelPromotion[promotion_type],MATCH(A20,tblModelPromotion[promotion_name],0)) -> Festive | C20: =INDEX(tblModelPromotion[discount_pct],MATCH(A20,tblModelPromotion[promotion_name],0))/100 -> 0.05 | D20: =INDEX(tblModelPromotion[revenue],MATCH(A20,tblModelPromotion[promotion_name],0)) -> 59507362 | E20: =INDEX(tblModelPromotion[margin_pct],MATCH(A20,tblModelPromotion[promotion_name],0)) -> 0.1808 | F20: =INDEX(tblModelPromotion[baseline_margin_pct],MATCH(A20,tblModelPromotion[promotion_name],0)) -> 0.2226 | G20: =E20-F20 -> -0.0418 | H20: =INDEX(tblModelPromotion[aov_lift_pct],MATCH(A20,tblModelPromotion[promotion_name],0)) -> 0.1175 | I20: =IF(AND(G20>=$L$1,H20>=$L$2),"Continue - efficient lift for margin cost",IF(AND(G20<=$L$3,H20<$L$2),"Discontinue - high margin cost, weak lift","Review - mixed signal")) -> Continue - efficient lift for margin cost
A21: =INDEX(tblModelPromotion[promotion_name],MATCH("Seasonal Sep2024 - 5% Off",tblModelPromotion[promotion_name],0)) -> Seasonal Sep2024 - 5% Off | B21: =INDEX(tblModelPromotion[promotion_type],MATCH(A21,tblModelPromotion[promotion_name],0)) -> Seasonal | C21: =INDEX(tblModelPromotion[discount_pct],MATCH(A21,tblModelPromotion[promotion_name],0))/100 -> 0.05 | D21: =INDEX(tblModelPromotion[revenue],MATCH(A21,tblModelPromotion[promotion_name],0)) -> 60585042 | E21: =INDEX(tblModelPromotion[margin_pct],MATCH(A21,tblModelPromotion[promotion_name],0)) -> 0.1803 | F21: =INDEX(tblModelPromotion[baseline_margin_pct],MATCH(A21,tblModelPromotion[promotion_name],0)) -> 0.2226 | G21: =E21-F21 -> -0.0423 | H21: =INDEX(tblModelPromotion[aov_lift_pct],MATCH(A21,tblModelPromotion[promotion_name],0)) -> 0.0798 | I21: =IF(AND(G21>=$L$1,H21>=$L$2),"Continue - efficient lift for margin cost",IF(AND(G21<=$L$3,H21<$L$2),"Discontinue - high margin cost, weak lift","Review - mixed signal")) -> Continue - efficient lift for margin cost
A22: =INDEX(tblModelPromotion[promotion_name],MATCH("Festive Nov2024 - 5% Off",tblModelPromotion[promotion_name],0)) -> Festive Nov2024 - 5% Off | B22: =INDEX(tblModelPromotion[promotion_type],MATCH(A22,tblModelPromotion[promotion_name],0)) -> Festive | C22: =INDEX(tblModelPromotion[discount_pct],MATCH(A22,tblModelPromotion[promotion_name],0))/100 -> 0.05 | D22: =INDEX(tblModelPromotion[revenue],MATCH(A22,tblModelPromotion[promotion_name],0)) -> 265770437 | E22: =INDEX(tblModelPromotion[margin_pct],MATCH(A22,tblModelPromotion[promotion_name],0)) -> 0.18 | F22: =INDEX(tblModelPromotion[baseline_margin_pct],MATCH(A22,tblModelPromotion[promotion_name],0)) -> 0.2226 | G22: =E22-F22 -> -0.0426 | H22: =INDEX(tblModelPromotion[aov_lift_pct],MATCH(A22,tblModelPromotion[promotion_name],0)) -> 0.1323 | I22: =IF(AND(G22>=$L$1,H22>=$L$2),"Continue - efficient lift for margin cost",IF(AND(G22<=$L$3,H22<$L$2),"Discontinue - high margin cost, weak lift","Review - mixed signal")) -> Continue - efficient lift for margin cost
A23: =INDEX(tblModelPromotion[promotion_name],MATCH("Loyalty Feb2022 - 5% Off",tblModelPromotion[promotion_name],0)) -> Loyalty Feb2022 - 5% Off | B23: =INDEX(tblModelPromotion[promotion_type],MATCH(A23,tblModelPromotion[promotion_name],0)) -> Loyalty | C23: =INDEX(tblModelPromotion[discount_pct],MATCH(A23,tblModelPromotion[promotion_name],0))/100 -> 0.05 | D23: =INDEX(tblModelPromotion[revenue],MATCH(A23,tblModelPromotion[promotion_name],0)) -> 68835124 | E23: =INDEX(tblModelPromotion[margin_pct],MATCH(A23,tblModelPromotion[promotion_name],0)) -> 0.1799 | F23: =INDEX(tblModelPromotion[baseline_margin_pct],MATCH(A23,tblModelPromotion[promotion_name],0)) -> 0.2226 | G23: =E23-F23 -> -0.0427 | H23: =INDEX(tblModelPromotion[aov_lift_pct],MATCH(A23,tblModelPromotion[promotion_name],0)) -> 0.1755 | I23: =IF(AND(G23>=$L$1,H23>=$L$2),"Continue - efficient lift for margin cost",IF(AND(G23<=$L$3,H23<$L$2),"Discontinue - high margin cost, weak lift","Review - mixed signal")) -> Continue - efficient lift for margin cost
A24: =INDEX(tblModelPromotion[promotion_name],MATCH("Festive Apr2022 - 5% Off",tblModelPromotion[promotion_name],0)) -> Festive Apr2022 - 5% Off | B24: =INDEX(tblModelPromotion[promotion_type],MATCH(A24,tblModelPromotion[promotion_name],0)) -> Festive | C24: =INDEX(tblModelPromotion[discount_pct],MATCH(A24,tblModelPromotion[promotion_name],0))/100 -> 0.05 | D24: =INDEX(tblModelPromotion[revenue],MATCH(A24,tblModelPromotion[promotion_name],0)) -> 64926882 | E24: =INDEX(tblModelPromotion[margin_pct],MATCH(A24,tblModelPromotion[promotion_name],0)) -> 0.1799 | F24: =INDEX(tblModelPromotion[baseline_margin_pct],MATCH(A24,tblModelPromotion[promotion_name],0)) -> 0.2226 | G24: =E24-F24 -> -0.0427 | H24: =INDEX(tblModelPromotion[aov_lift_pct],MATCH(A24,tblModelPromotion[promotion_name],0)) -> 0.1516 | I24: =IF(AND(G24>=$L$1,H24>=$L$2),"Continue - efficient lift for margin cost",IF(AND(G24<=$L$3,H24<$L$2),"Discontinue - high margin cost, weak lift","Review - mixed signal")) -> Continue - efficient lift for margin cost
A25: =INDEX(tblModelPromotion[promotion_name],MATCH("Seasonal Jan2023 - 5% Off",tblModelPromotion[promotion_name],0)) -> Seasonal Jan2023 - 5% Off | B25: =INDEX(tblModelPromotion[promotion_type],MATCH(A25,tblModelPromotion[promotion_name],0)) -> Seasonal | C25: =INDEX(tblModelPromotion[discount_pct],MATCH(A25,tblModelPromotion[promotion_name],0))/100 -> 0.05 | D25: =INDEX(tblModelPromotion[revenue],MATCH(A25,tblModelPromotion[promotion_name],0)) -> 66605073 | E25: =INDEX(tblModelPromotion[margin_pct],MATCH(A25,tblModelPromotion[promotion_name],0)) -> 0.1795 | F25: =INDEX(tblModelPromotion[baseline_margin_pct],MATCH(A25,tblModelPromotion[promotion_name],0)) -> 0.2226 | G25: =E25-F25 -> -0.0431 | H25: =INDEX(tblModelPromotion[aov_lift_pct],MATCH(A25,tblModelPromotion[promotion_name],0)) -> 0.1672 | I25: =IF(AND(G25>=$L$1,H25>=$L$2),"Continue - efficient lift for margin cost",IF(AND(G25<=$L$3,H25<$L$2),"Discontinue - high margin cost, weak lift","Review - mixed signal")) -> Continue - efficient lift for margin cost
A26: =INDEX(tblModelPromotion[promotion_name],MATCH("Flash Sale Feb2022 - 5% Off",tblModelPromotion[promotion_name],0)) -> Flash Sale Feb2022 - 5% Off | B26: =INDEX(tblModelPromotion[promotion_type],MATCH(A26,tblModelPromotion[promotion_name],0)) -> Flash Sale | C26: =INDEX(tblModelPromotion[discount_pct],MATCH(A26,tblModelPromotion[promotion_name],0))/100 -> 0.05 | D26: =INDEX(tblModelPromotion[revenue],MATCH(A26,tblModelPromotion[promotion_name],0)) -> 31109407 | E26: =INDEX(tblModelPromotion[margin_pct],MATCH(A26,tblModelPromotion[promotion_name],0)) -> 0.1837 | F26: =INDEX(tblModelPromotion[baseline_margin_pct],MATCH(A26,tblModelPromotion[promotion_name],0)) -> 0.2226 | G26: =E26-F26 -> -0.0389 | H26: =INDEX(tblModelPromotion[aov_lift_pct],MATCH(A26,tblModelPromotion[promotion_name],0)) -> 0.1365 | I26: =IF(AND(G26>=$L$1,H26>=$L$2),"Continue - efficient lift for margin cost",IF(AND(G26<=$L$3,H26<$L$2),"Discontinue - high margin cost, weak lift","Review - mixed signal")) -> Continue - efficient lift for margin cost
A27: =INDEX(tblModelPromotion[promotion_name],MATCH("Loyalty Dec2021 - 5% Off",tblModelPromotion[promotion_name],0)) -> Loyalty Dec2021 - 5% Off | B27: =INDEX(tblModelPromotion[promotion_type],MATCH(A27,tblModelPromotion[promotion_name],0)) -> Loyalty | C27: =INDEX(tblModelPromotion[discount_pct],MATCH(A27,tblModelPromotion[promotion_name],0))/100 -> 0.05 | D27: =INDEX(tblModelPromotion[revenue],MATCH(A27,tblModelPromotion[promotion_name],0)) -> 88869563 | E27: =INDEX(tblModelPromotion[margin_pct],MATCH(A27,tblModelPromotion[promotion_name],0)) -> 0.1791 | F27: =INDEX(tblModelPromotion[baseline_margin_pct],MATCH(A27,tblModelPromotion[promotion_name],0)) -> 0.2226 | G27: =E27-F27 -> -0.0435 | H27: =INDEX(tblModelPromotion[aov_lift_pct],MATCH(A27,tblModelPromotion[promotion_name],0)) -> 0.1032 | I27: =IF(AND(G27>=$L$1,H27>=$L$2),"Continue - efficient lift for margin cost",IF(AND(G27<=$L$3,H27<$L$2),"Discontinue - high margin cost, weak lift","Review - mixed signal")) -> Continue - efficient lift for margin cost
A28: =INDEX(tblModelPromotion[promotion_name],MATCH("Loyalty Sep2024 - 5% Off",tblModelPromotion[promotion_name],0)) -> Loyalty Sep2024 - 5% Off | B28: =INDEX(tblModelPromotion[promotion_type],MATCH(A28,tblModelPromotion[promotion_name],0)) -> Loyalty | C28: =INDEX(tblModelPromotion[discount_pct],MATCH(A28,tblModelPromotion[promotion_name],0))/100 -> 0.05 | D28: =INDEX(tblModelPromotion[revenue],MATCH(A28,tblModelPromotion[promotion_name],0)) -> 478598231 | E28: =INDEX(tblModelPromotion[margin_pct],MATCH(A28,tblModelPromotion[promotion_name],0)) -> 0.1791 | F28: =INDEX(tblModelPromotion[baseline_margin_pct],MATCH(A28,tblModelPromotion[promotion_name],0)) -> 0.2226 | G28: =E28-F28 -> -0.0435 | H28: =INDEX(tblModelPromotion[aov_lift_pct],MATCH(A28,tblModelPromotion[promotion_name],0)) -> 0.139 | I28: =IF(AND(G28>=$L$1,H28>=$L$2),"Continue - efficient lift for margin cost",IF(AND(G28<=$L$3,H28<$L$2),"Discontinue - high margin cost, weak lift","Review - mixed signal")) -> Continue - efficient lift for margin cost
A29: =INDEX(tblModelPromotion[promotion_name],MATCH("Seasonal Jun2024 - 5% Off",tblModelPromotion[promotion_name],0)) -> Seasonal Jun2024 - 5% Off | B29: =INDEX(tblModelPromotion[promotion_type],MATCH(A29,tblModelPromotion[promotion_name],0)) -> Seasonal | C29: =INDEX(tblModelPromotion[discount_pct],MATCH(A29,tblModelPromotion[promotion_name],0))/100 -> 0.05 | D29: =INDEX(tblModelPromotion[revenue],MATCH(A29,tblModelPromotion[promotion_name],0)) -> 96683502 | E29: =INDEX(tblModelPromotion[margin_pct],MATCH(A29,tblModelPromotion[promotion_name],0)) -> 0.1791 | F29: =INDEX(tblModelPromotion[baseline_margin_pct],MATCH(A29,tblModelPromotion[promotion_name],0)) -> 0.2226 | G29: =E29-F29 -> -0.0435 | H29: =INDEX(tblModelPromotion[aov_lift_pct],MATCH(A29,tblModelPromotion[promotion_name],0)) -> 0.1581 | I29: =IF(AND(G29>=$L$1,H29>=$L$2),"Continue - efficient lift for margin cost",IF(AND(G29<=$L$3,H29<$L$2),"Discontinue - high margin cost, weak lift","Review - mixed signal")) -> Continue - efficient lift for margin cost
A30: =INDEX(tblModelPromotion[promotion_name],MATCH("Festive Mar2024 - 5% Off",tblModelPromotion[promotion_name],0)) -> Festive Mar2024 - 5% Off | B30: =INDEX(tblModelPromotion[promotion_type],MATCH(A30,tblModelPromotion[promotion_name],0)) -> Festive | C30: =INDEX(tblModelPromotion[discount_pct],MATCH(A30,tblModelPromotion[promotion_name],0))/100 -> 0.05 | D30: =INDEX(tblModelPromotion[revenue],MATCH(A30,tblModelPromotion[promotion_name],0)) -> 42369113 | E30: =INDEX(tblModelPromotion[margin_pct],MATCH(A30,tblModelPromotion[promotion_name],0)) -> 0.1788 | F30: =INDEX(tblModelPromotion[baseline_margin_pct],MATCH(A30,tblModelPromotion[promotion_name],0)) -> 0.2226 | G30: =E30-F30 -> -0.0438 | H30: =INDEX(tblModelPromotion[aov_lift_pct],MATCH(A30,tblModelPromotion[promotion_name],0)) -> 0.1252 | I30: =IF(AND(G30>=$L$1,H30>=$L$2),"Continue - efficient lift for margin cost",IF(AND(G30<=$L$3,H30<$L$2),"Discontinue - high margin cost, weak lift","Review - mixed signal")) -> Continue - efficient lift for margin cost
A31: =INDEX(tblModelPromotion[promotion_name],MATCH("Seasonal Jan2022 - 5% Off",tblModelPromotion[promotion_name],0)) -> Seasonal Jan2022 - 5% Off | B31: =INDEX(tblModelPromotion[promotion_type],MATCH(A31,tblModelPromotion[promotion_name],0)) -> Seasonal | C31: =INDEX(tblModelPromotion[discount_pct],MATCH(A31,tblModelPromotion[promotion_name],0))/100 -> 0.05 | D31: =INDEX(tblModelPromotion[revenue],MATCH(A31,tblModelPromotion[promotion_name],0)) -> 57271842 | E31: =INDEX(tblModelPromotion[margin_pct],MATCH(A31,tblModelPromotion[promotion_name],0)) -> 0.1781 | F31: =INDEX(tblModelPromotion[baseline_margin_pct],MATCH(A31,tblModelPromotion[promotion_name],0)) -> 0.2226 | G31: =E31-F31 -> -0.0445 | H31: =INDEX(tblModelPromotion[aov_lift_pct],MATCH(A31,tblModelPromotion[promotion_name],0)) -> 0.1428 | I31: =IF(AND(G31>=$L$1,H31>=$L$2),"Continue - efficient lift for margin cost",IF(AND(G31<=$L$3,H31<$L$2),"Discontinue - high margin cost, weak lift","Review - mixed signal")) -> Continue - efficient lift for margin cost
A32: =INDEX(tblModelPromotion[promotion_name],MATCH("Festive Dec2021 - 5% Off",tblModelPromotion[promotion_name],0)) -> Festive Dec2021 - 5% Off | B32: =INDEX(tblModelPromotion[promotion_type],MATCH(A32,tblModelPromotion[promotion_name],0)) -> Festive | C32: =INDEX(tblModelPromotion[discount_pct],MATCH(A32,tblModelPromotion[promotion_name],0))/100 -> 0.05 | D32: =INDEX(tblModelPromotion[revenue],MATCH(A32,tblModelPromotion[promotion_name],0)) -> 30335972 | E32: =INDEX(tblModelPromotion[margin_pct],MATCH(A32,tblModelPromotion[promotion_name],0)) -> 0.1748 | F32: =INDEX(tblModelPromotion[baseline_margin_pct],MATCH(A32,tblModelPromotion[promotion_name],0)) -> 0.2226 | G32: =E32-F32 -> -0.0478 | H32: =INDEX(tblModelPromotion[aov_lift_pct],MATCH(A32,tblModelPromotion[promotion_name],0)) -> 0.1512 | I32: =IF(AND(G32>=$L$1,H32>=$L$2),"Continue - efficient lift for margin cost",IF(AND(G32<=$L$3,H32<$L$2),"Discontinue - high margin cost, weak lift","Review - mixed signal")) -> Continue - efficient lift for margin cost
A33: =INDEX(tblModelPromotion[promotion_name],MATCH("Seasonal Dec2021 - 5% Off",tblModelPromotion[promotion_name],0)) -> Seasonal Dec2021 - 5% Off | B33: =INDEX(tblModelPromotion[promotion_type],MATCH(A33,tblModelPromotion[promotion_name],0)) -> Seasonal | C33: =INDEX(tblModelPromotion[discount_pct],MATCH(A33,tblModelPromotion[promotion_name],0))/100 -> 0.05 | D33: =INDEX(tblModelPromotion[revenue],MATCH(A33,tblModelPromotion[promotion_name],0)) -> 30999756 | E33: =INDEX(tblModelPromotion[margin_pct],MATCH(A33,tblModelPromotion[promotion_name],0)) -> 0.1832 | F33: =INDEX(tblModelPromotion[baseline_margin_pct],MATCH(A33,tblModelPromotion[promotion_name],0)) -> 0.2226 | G33: =E33-F33 -> -0.0394 | H33: =INDEX(tblModelPromotion[aov_lift_pct],MATCH(A33,tblModelPromotion[promotion_name],0)) -> 0.1269 | I33: =IF(AND(G33>=$L$1,H33>=$L$2),"Continue - efficient lift for margin cost",IF(AND(G33<=$L$3,H33<$L$2),"Discontinue - high margin cost, weak lift","Review - mixed signal")) -> Continue - efficient lift for margin cost
A34: =INDEX(tblModelPromotion[promotion_name],MATCH("Clearance Feb2024 - 10% Off",tblModelPromotion[promotion_name],0)) -> Clearance Feb2024 - 10% Off | B34: =INDEX(tblModelPromotion[promotion_type],MATCH(A34,tblModelPromotion[promotion_name],0)) -> Clearance | C34: =INDEX(tblModelPromotion[discount_pct],MATCH(A34,tblModelPromotion[promotion_name],0))/100 -> 0.1 | D34: =INDEX(tblModelPromotion[revenue],MATCH(A34,tblModelPromotion[promotion_name],0)) -> 54702959 | E34: =INDEX(tblModelPromotion[margin_pct],MATCH(A34,tblModelPromotion[promotion_name],0)) -> 0.132 | F34: =INDEX(tblModelPromotion[baseline_margin_pct],MATCH(A34,tblModelPromotion[promotion_name],0)) -> 0.2226 | G34: =E34-F34 -> -0.0906 | H34: =INDEX(tblModelPromotion[aov_lift_pct],MATCH(A34,tblModelPromotion[promotion_name],0)) -> 0.1559 | I34: =IF(AND(G34>=$L$1,H34>=$L$2),"Continue - efficient lift for margin cost",IF(AND(G34<=$L$3,H34<$L$2),"Discontinue - high margin cost, weak lift","Review - mixed signal")) -> Continue - efficient lift for margin cost
A35: =INDEX(tblModelPromotion[promotion_name],MATCH("Loyalty Jul2024 - 10% Off",tblModelPromotion[promotion_name],0)) -> Loyalty Jul2024 - 10% Off | B35: =INDEX(tblModelPromotion[promotion_type],MATCH(A35,tblModelPromotion[promotion_name],0)) -> Loyalty | C35: =INDEX(tblModelPromotion[discount_pct],MATCH(A35,tblModelPromotion[promotion_name],0))/100 -> 0.1 | D35: =INDEX(tblModelPromotion[revenue],MATCH(A35,tblModelPromotion[promotion_name],0)) -> 29983311 | E35: =INDEX(tblModelPromotion[margin_pct],MATCH(A35,tblModelPromotion[promotion_name],0)) -> 0.1411 | F35: =INDEX(tblModelPromotion[baseline_margin_pct],MATCH(A35,tblModelPromotion[promotion_name],0)) -> 0.2226 | G35: =E35-F35 -> -0.0815 | H35: =INDEX(tblModelPromotion[aov_lift_pct],MATCH(A35,tblModelPromotion[promotion_name],0)) -> 0.0053 | I35: =IF(AND(G35>=$L$1,H35>=$L$2),"Continue - efficient lift for margin cost",IF(AND(G35<=$L$3,H35<$L$2),"Discontinue - high margin cost, weak lift","Review - mixed signal")) -> Continue - efficient lift for margin cost
A36: =INDEX(tblModelPromotion[promotion_name],MATCH("Clearance Mar2024 - 10% Off",tblModelPromotion[promotion_name],0)) -> Clearance Mar2024 - 10% Off | B36: =INDEX(tblModelPromotion[promotion_type],MATCH(A36,tblModelPromotion[promotion_name],0)) -> Clearance | C36: =INDEX(tblModelPromotion[discount_pct],MATCH(A36,tblModelPromotion[promotion_name],0))/100 -> 0.1 | D36: =INDEX(tblModelPromotion[revenue],MATCH(A36,tblModelPromotion[promotion_name],0)) -> 39618388 | E36: =INDEX(tblModelPromotion[margin_pct],MATCH(A36,tblModelPromotion[promotion_name],0)) -> 0.1404 | F36: =INDEX(tblModelPromotion[baseline_margin_pct],MATCH(A36,tblModelPromotion[promotion_name],0)) -> 0.2226 | G36: =E36-F36 -> -0.0822 | H36: =INDEX(tblModelPromotion[aov_lift_pct],MATCH(A36,tblModelPromotion[promotion_name],0)) -> 0.0119 | I36: =IF(AND(G36>=$L$1,H36>=$L$2),"Continue - efficient lift for margin cost",IF(AND(G36<=$L$3,H36<$L$2),"Discontinue - high margin cost, weak lift","Review - mixed signal")) -> Continue - efficient lift for margin cost
A37: =INDEX(tblModelPromotion[promotion_name],MATCH("Seasonal Jun2024 - 10% Off",tblModelPromotion[promotion_name],0)) -> Seasonal Jun2024 - 10% Off | B37: =INDEX(tblModelPromotion[promotion_type],MATCH(A37,tblModelPromotion[promotion_name],0)) -> Seasonal | C37: =INDEX(tblModelPromotion[discount_pct],MATCH(A37,tblModelPromotion[promotion_name],0))/100 -> 0.1 | D37: =INDEX(tblModelPromotion[revenue],MATCH(A37,tblModelPromotion[promotion_name],0)) -> 85707135 | E37: =INDEX(tblModelPromotion[margin_pct],MATCH(A37,tblModelPromotion[promotion_name],0)) -> 0.139 | F37: =INDEX(tblModelPromotion[baseline_margin_pct],MATCH(A37,tblModelPromotion[promotion_name],0)) -> 0.2226 | G37: =E37-F37 -> -0.0836 | H37: =INDEX(tblModelPromotion[aov_lift_pct],MATCH(A37,tblModelPromotion[promotion_name],0)) -> 0.0317 | I37: =IF(AND(G37>=$L$1,H37>=$L$2),"Continue - efficient lift for margin cost",IF(AND(G37<=$L$3,H37<$L$2),"Discontinue - high margin cost, weak lift","Review - mixed signal")) -> Continue - efficient lift for margin cost
A38: =INDEX(tblModelPromotion[promotion_name],MATCH("Flash Sale Sep2024 - 10% Off",tblModelPromotion[promotion_name],0)) -> Flash Sale Sep2024 - 10% Off | B38: =INDEX(tblModelPromotion[promotion_type],MATCH(A38,tblModelPromotion[promotion_name],0)) -> Flash Sale | C38: =INDEX(tblModelPromotion[discount_pct],MATCH(A38,tblModelPromotion[promotion_name],0))/100 -> 0.1 | D38: =INDEX(tblModelPromotion[revenue],MATCH(A38,tblModelPromotion[promotion_name],0)) -> 65154956 | E38: =INDEX(tblModelPromotion[margin_pct],MATCH(A38,tblModelPromotion[promotion_name],0)) -> 0.1389 | F38: =INDEX(tblModelPromotion[baseline_margin_pct],MATCH(A38,tblModelPromotion[promotion_name],0)) -> 0.2226 | G38: =E38-F38 -> -0.0837 | H38: =INDEX(tblModelPromotion[aov_lift_pct],MATCH(A38,tblModelPromotion[promotion_name],0)) -> 0.1297 | I38: =IF(AND(G38>=$L$1,H38>=$L$2),"Continue - efficient lift for margin cost",IF(AND(G38<=$L$3,H38<$L$2),"Discontinue - high margin cost, weak lift","Review - mixed signal")) -> Continue - efficient lift for margin cost
A39: =INDEX(tblModelPromotion[promotion_name],MATCH("Seasonal Feb2023 - 10% Off",tblModelPromotion[promotion_name],0)) -> Seasonal Feb2023 - 10% Off | B39: =INDEX(tblModelPromotion[promotion_type],MATCH(A39,tblModelPromotion[promotion_name],0)) -> Seasonal | C39: =INDEX(tblModelPromotion[discount_pct],MATCH(A39,tblModelPromotion[promotion_name],0))/100 -> 0.1 | D39: =INDEX(tblModelPromotion[revenue],MATCH(A39,tblModelPromotion[promotion_name],0)) -> 40401984 | E39: =INDEX(tblModelPromotion[margin_pct],MATCH(A39,tblModelPromotion[promotion_name],0)) -> 0.1386 | F39: =INDEX(tblModelPromotion[baseline_margin_pct],MATCH(A39,tblModelPromotion[promotion_name],0)) -> 0.2226 | G39: =E39-F39 -> -0.084 | H39: =INDEX(tblModelPromotion[aov_lift_pct],MATCH(A39,tblModelPromotion[promotion_name],0)) -> 0.0301 | I39: =IF(AND(G39>=$L$1,H39>=$L$2),"Continue - efficient lift for margin cost",IF(AND(G39<=$L$3,H39<$L$2),"Discontinue - high margin cost, weak lift","Review - mixed signal")) -> Continue - efficient lift for margin cost
A40: =INDEX(tblModelPromotion[promotion_name],MATCH("Festive Feb2023 - 10% Off",tblModelPromotion[promotion_name],0)) -> Festive Feb2023 - 10% Off | B40: =INDEX(tblModelPromotion[promotion_type],MATCH(A40,tblModelPromotion[promotion_name],0)) -> Festive | C40: =INDEX(tblModelPromotion[discount_pct],MATCH(A40,tblModelPromotion[promotion_name],0))/100 -> 0.1 | D40: =INDEX(tblModelPromotion[revenue],MATCH(A40,tblModelPromotion[promotion_name],0)) -> 17191645 | E40: =INDEX(tblModelPromotion[margin_pct],MATCH(A40,tblModelPromotion[promotion_name],0)) -> 0.1386 | F40: =INDEX(tblModelPromotion[baseline_margin_pct],MATCH(A40,tblModelPromotion[promotion_name],0)) -> 0.2226 | G40: =E40-F40 -> -0.084 | H40: =INDEX(tblModelPromotion[aov_lift_pct],MATCH(A40,tblModelPromotion[promotion_name],0)) -> 0.1171 | I40: =IF(AND(G40>=$L$1,H40>=$L$2),"Continue - efficient lift for margin cost",IF(AND(G40<=$L$3,H40<$L$2),"Discontinue - high margin cost, weak lift","Review - mixed signal")) -> Continue - efficient lift for margin cost
A41: =INDEX(tblModelPromotion[promotion_name],MATCH("Seasonal May2023 - 10% Off",tblModelPromotion[promotion_name],0)) -> Seasonal May2023 - 10% Off | B41: =INDEX(tblModelPromotion[promotion_type],MATCH(A41,tblModelPromotion[promotion_name],0)) -> Seasonal | C41: =INDEX(tblModelPromotion[discount_pct],MATCH(A41,tblModelPromotion[promotion_name],0))/100 -> 0.1 | D41: =INDEX(tblModelPromotion[revenue],MATCH(A41,tblModelPromotion[promotion_name],0)) -> 43411088 | E41: =INDEX(tblModelPromotion[margin_pct],MATCH(A41,tblModelPromotion[promotion_name],0)) -> 0.1385 | F41: =INDEX(tblModelPromotion[baseline_margin_pct],MATCH(A41,tblModelPromotion[promotion_name],0)) -> 0.2226 | G41: =E41-F41 -> -0.0841 | H41: =INDEX(tblModelPromotion[aov_lift_pct],MATCH(A41,tblModelPromotion[promotion_name],0)) -> 0.04 | I41: =IF(AND(G41>=$L$1,H41>=$L$2),"Continue - efficient lift for margin cost",IF(AND(G41<=$L$3,H41<$L$2),"Discontinue - high margin cost, weak lift","Review - mixed signal")) -> Continue - efficient lift for margin cost
A42: =INDEX(tblModelPromotion[promotion_name],MATCH("Loyalty Sep2024 - 10% Off",tblModelPromotion[promotion_name],0)) -> Loyalty Sep2024 - 10% Off | B42: =INDEX(tblModelPromotion[promotion_type],MATCH(A42,tblModelPromotion[promotion_name],0)) -> Loyalty | C42: =INDEX(tblModelPromotion[discount_pct],MATCH(A42,tblModelPromotion[promotion_name],0))/100 -> 0.1 | D42: =INDEX(tblModelPromotion[revenue],MATCH(A42,tblModelPromotion[promotion_name],0)) -> 61052571 | E42: =INDEX(tblModelPromotion[margin_pct],MATCH(A42,tblModelPromotion[promotion_name],0)) -> 0.1378 | F42: =INDEX(tblModelPromotion[baseline_margin_pct],MATCH(A42,tblModelPromotion[promotion_name],0)) -> 0.2226 | G42: =E42-F42 -> -0.0848 | H42: =INDEX(tblModelPromotion[aov_lift_pct],MATCH(A42,tblModelPromotion[promotion_name],0)) -> 0.1221 | I42: =IF(AND(G42>=$L$1,H42>=$L$2),"Continue - efficient lift for margin cost",IF(AND(G42<=$L$3,H42<$L$2),"Discontinue - high margin cost, weak lift","Review - mixed signal")) -> Continue - efficient lift for margin cost
A43: =INDEX(tblModelPromotion[promotion_name],MATCH("Festive Jun2022 - 10% Off",tblModelPromotion[promotion_name],0)) -> Festive Jun2022 - 10% Off | B43: =INDEX(tblModelPromotion[promotion_type],MATCH(A43,tblModelPromotion[promotion_name],0)) -> Festive | C43: =INDEX(tblModelPromotion[discount_pct],MATCH(A43,tblModelPromotion[promotion_name],0))/100 -> 0.1 | D43: =INDEX(tblModelPromotion[revenue],MATCH(A43,tblModelPromotion[promotion_name],0)) -> 132548651 | E43: =INDEX(tblModelPromotion[margin_pct],MATCH(A43,tblModelPromotion[promotion_name],0)) -> 0.1375 | F43: =INDEX(tblModelPromotion[baseline_margin_pct],MATCH(A43,tblModelPromotion[promotion_name],0)) -> 0.2226 | G43: =E43-F43 -> -0.0851 | H43: =INDEX(tblModelPromotion[aov_lift_pct],MATCH(A43,tblModelPromotion[promotion_name],0)) -> 0.0382 | I43: =IF(AND(G43>=$L$1,H43>=$L$2),"Continue - efficient lift for margin cost",IF(AND(G43<=$L$3,H43<$L$2),"Discontinue - high margin cost, weak lift","Review - mixed signal")) -> Continue - efficient lift for margin cost
A44: =INDEX(tblModelPromotion[promotion_name],MATCH("Loyalty Jun2023 - 10% Off",tblModelPromotion[promotion_name],0)) -> Loyalty Jun2023 - 10% Off | B44: =INDEX(tblModelPromotion[promotion_type],MATCH(A44,tblModelPromotion[promotion_name],0)) -> Loyalty | C44: =INDEX(tblModelPromotion[discount_pct],MATCH(A44,tblModelPromotion[promotion_name],0))/100 -> 0.1 | D44: =INDEX(tblModelPromotion[revenue],MATCH(A44,tblModelPromotion[promotion_name],0)) -> 65406079 | E44: =INDEX(tblModelPromotion[margin_pct],MATCH(A44,tblModelPromotion[promotion_name],0)) -> 0.1373 | F44: =INDEX(tblModelPromotion[baseline_margin_pct],MATCH(A44,tblModelPromotion[promotion_name],0)) -> 0.2226 | G44: =E44-F44 -> -0.0853 | H44: =INDEX(tblModelPromotion[aov_lift_pct],MATCH(A44,tblModelPromotion[promotion_name],0)) -> 0.1028 | I44: =IF(AND(G44>=$L$1,H44>=$L$2),"Continue - efficient lift for margin cost",IF(AND(G44<=$L$3,H44<$L$2),"Discontinue - high margin cost, weak lift","Review - mixed signal")) -> Continue - efficient lift for margin cost
A45: =INDEX(tblModelPromotion[promotion_name],MATCH("Seasonal Aug2024 - 10% Off",tblModelPromotion[promotion_name],0)) -> Seasonal Aug2024 - 10% Off | B45: =INDEX(tblModelPromotion[promotion_type],MATCH(A45,tblModelPromotion[promotion_name],0)) -> Seasonal | C45: =INDEX(tblModelPromotion[discount_pct],MATCH(A45,tblModelPromotion[promotion_name],0))/100 -> 0.1 | D45: =INDEX(tblModelPromotion[revenue],MATCH(A45,tblModelPromotion[promotion_name],0)) -> 38583299 | E45: =INDEX(tblModelPromotion[margin_pct],MATCH(A45,tblModelPromotion[promotion_name],0)) -> 0.137 | F45: =INDEX(tblModelPromotion[baseline_margin_pct],MATCH(A45,tblModelPromotion[promotion_name],0)) -> 0.2226 | G45: =E45-F45 -> -0.0856 | H45: =INDEX(tblModelPromotion[aov_lift_pct],MATCH(A45,tblModelPromotion[promotion_name],0)) -> 0.0532 | I45: =IF(AND(G45>=$L$1,H45>=$L$2),"Continue - efficient lift for margin cost",IF(AND(G45<=$L$3,H45<$L$2),"Discontinue - high margin cost, weak lift","Review - mixed signal")) -> Continue - efficient lift for margin cost
A46: =INDEX(tblModelPromotion[promotion_name],MATCH("Flash Sale Jun2023 - 10% Off",tblModelPromotion[promotion_name],0)) -> Flash Sale Jun2023 - 10% Off | B46: =INDEX(tblModelPromotion[promotion_type],MATCH(A46,tblModelPromotion[promotion_name],0)) -> Flash Sale | C46: =INDEX(tblModelPromotion[discount_pct],MATCH(A46,tblModelPromotion[promotion_name],0))/100 -> 0.1 | D46: =INDEX(tblModelPromotion[revenue],MATCH(A46,tblModelPromotion[promotion_name],0)) -> 103437743 | E46: =INDEX(tblModelPromotion[margin_pct],MATCH(A46,tblModelPromotion[promotion_name],0)) -> 0.1369 | F46: =INDEX(tblModelPromotion[baseline_margin_pct],MATCH(A46,tblModelPromotion[promotion_name],0)) -> 0.2226 | G46: =E46-F46 -> -0.0857 | H46: =INDEX(tblModelPromotion[aov_lift_pct],MATCH(A46,tblModelPromotion[promotion_name],0)) -> 0.0897 | I46: =IF(AND(G46>=$L$1,H46>=$L$2),"Continue - efficient lift for margin cost",IF(AND(G46<=$L$3,H46<$L$2),"Discontinue - high margin cost, weak lift","Review - mixed signal")) -> Continue - efficient lift for margin cost
A47: =INDEX(tblModelPromotion[promotion_name],MATCH("Flash Sale Nov2023 - 10% Off",tblModelPromotion[promotion_name],0)) -> Flash Sale Nov2023 - 10% Off | B47: =INDEX(tblModelPromotion[promotion_type],MATCH(A47,tblModelPromotion[promotion_name],0)) -> Flash Sale | C47: =INDEX(tblModelPromotion[discount_pct],MATCH(A47,tblModelPromotion[promotion_name],0))/100 -> 0.1 | D47: =INDEX(tblModelPromotion[revenue],MATCH(A47,tblModelPromotion[promotion_name],0)) -> 70726320 | E47: =INDEX(tblModelPromotion[margin_pct],MATCH(A47,tblModelPromotion[promotion_name],0)) -> 0.1369 | F47: =INDEX(tblModelPromotion[baseline_margin_pct],MATCH(A47,tblModelPromotion[promotion_name],0)) -> 0.2226 | G47: =E47-F47 -> -0.0857 | H47: =INDEX(tblModelPromotion[aov_lift_pct],MATCH(A47,tblModelPromotion[promotion_name],0)) -> 0.0513 | I47: =IF(AND(G47>=$L$1,H47>=$L$2),"Continue - efficient lift for margin cost",IF(AND(G47<=$L$3,H47<$L$2),"Discontinue - high margin cost, weak lift","Review - mixed signal")) -> Continue - efficient lift for margin cost
A48: =INDEX(tblModelPromotion[promotion_name],MATCH("Seasonal Aug2023 - 10% Off",tblModelPromotion[promotion_name],0)) -> Seasonal Aug2023 - 10% Off | B48: =INDEX(tblModelPromotion[promotion_type],MATCH(A48,tblModelPromotion[promotion_name],0)) -> Seasonal | C48: =INDEX(tblModelPromotion[discount_pct],MATCH(A48,tblModelPromotion[promotion_name],0))/100 -> 0.1 | D48: =INDEX(tblModelPromotion[revenue],MATCH(A48,tblModelPromotion[promotion_name],0)) -> 42662861 | E48: =INDEX(tblModelPromotion[margin_pct],MATCH(A48,tblModelPromotion[promotion_name],0)) -> 0.1362 | F48: =INDEX(tblModelPromotion[baseline_margin_pct],MATCH(A48,tblModelPromotion[promotion_name],0)) -> 0.2226 | G48: =E48-F48 -> -0.0864 | H48: =INDEX(tblModelPromotion[aov_lift_pct],MATCH(A48,tblModelPromotion[promotion_name],0)) -> 0.1011 | I48: =IF(AND(G48>=$L$1,H48>=$L$2),"Continue - efficient lift for margin cost",IF(AND(G48<=$L$3,H48<$L$2),"Discontinue - high margin cost, weak lift","Review - mixed signal")) -> Continue - efficient lift for margin cost
A49: =INDEX(tblModelPromotion[promotion_name],MATCH("Loyalty Oct2023 - 10% Off",tblModelPromotion[promotion_name],0)) -> Loyalty Oct2023 - 10% Off | B49: =INDEX(tblModelPromotion[promotion_type],MATCH(A49,tblModelPromotion[promotion_name],0)) -> Loyalty | C49: =INDEX(tblModelPromotion[discount_pct],MATCH(A49,tblModelPromotion[promotion_name],0))/100 -> 0.1 | D49: =INDEX(tblModelPromotion[revenue],MATCH(A49,tblModelPromotion[promotion_name],0)) -> 62132738 | E49: =INDEX(tblModelPromotion[margin_pct],MATCH(A49,tblModelPromotion[promotion_name],0)) -> 0.136 | F49: =INDEX(tblModelPromotion[baseline_margin_pct],MATCH(A49,tblModelPromotion[promotion_name],0)) -> 0.2226 | G49: =E49-F49 -> -0.0866 | H49: =INDEX(tblModelPromotion[aov_lift_pct],MATCH(A49,tblModelPromotion[promotion_name],0)) -> 0.1521 | I49: =IF(AND(G49>=$L$1,H49>=$L$2),"Continue - efficient lift for margin cost",IF(AND(G49<=$L$3,H49<$L$2),"Discontinue - high margin cost, weak lift","Review - mixed signal")) -> Continue - efficient lift for margin cost
A50: =INDEX(tblModelPromotion[promotion_name],MATCH("Festive May2022 - 10% Off",tblModelPromotion[promotion_name],0)) -> Festive May2022 - 10% Off | B50: =INDEX(tblModelPromotion[promotion_type],MATCH(A50,tblModelPromotion[promotion_name],0)) -> Festive | C50: =INDEX(tblModelPromotion[discount_pct],MATCH(A50,tblModelPromotion[promotion_name],0))/100 -> 0.1 | D50: =INDEX(tblModelPromotion[revenue],MATCH(A50,tblModelPromotion[promotion_name],0)) -> 74118462 | E50: =INDEX(tblModelPromotion[margin_pct],MATCH(A50,tblModelPromotion[promotion_name],0)) -> 0.1353 | F50: =INDEX(tblModelPromotion[baseline_margin_pct],MATCH(A50,tblModelPromotion[promotion_name],0)) -> 0.2226 | G50: =E50-F50 -> -0.0873 | H50: =INDEX(tblModelPromotion[aov_lift_pct],MATCH(A50,tblModelPromotion[promotion_name],0)) -> 0.0517 | I50: =IF(AND(G50>=$L$1,H50>=$L$2),"Continue - efficient lift for margin cost",IF(AND(G50<=$L$3,H50<$L$2),"Discontinue - high margin cost, weak lift","Review - mixed signal")) -> Continue - efficient lift for margin cost
A51: =INDEX(tblModelPromotion[promotion_name],MATCH("Seasonal Jun2021 - 10% Off",tblModelPromotion[promotion_name],0)) -> Seasonal Jun2021 - 10% Off | B51: =INDEX(tblModelPromotion[promotion_type],MATCH(A51,tblModelPromotion[promotion_name],0)) -> Seasonal | C51: =INDEX(tblModelPromotion[discount_pct],MATCH(A51,tblModelPromotion[promotion_name],0))/100 -> 0.1 | D51: =INDEX(tblModelPromotion[revenue],MATCH(A51,tblModelPromotion[promotion_name],0)) -> 14303457 | E51: =INDEX(tblModelPromotion[margin_pct],MATCH(A51,tblModelPromotion[promotion_name],0)) -> 0.1352 | F51: =INDEX(tblModelPromotion[baseline_margin_pct],MATCH(A51,tblModelPromotion[promotion_name],0)) -> 0.2226 | G51: =E51-F51 -> -0.0874 | H51: =INDEX(tblModelPromotion[aov_lift_pct],MATCH(A51,tblModelPromotion[promotion_name],0)) -> 0.1354 | I51: =IF(AND(G51>=$L$1,H51>=$L$2),"Continue - efficient lift for margin cost",IF(AND(G51<=$L$3,H51<$L$2),"Discontinue - high margin cost, weak lift","Review - mixed signal")) -> Continue - efficient lift for margin cost
A52: =INDEX(tblModelPromotion[promotion_name],MATCH("Seasonal Apr2023 - 10% Off",tblModelPromotion[promotion_name],0)) -> Seasonal Apr2023 - 10% Off | B52: =INDEX(tblModelPromotion[promotion_type],MATCH(A52,tblModelPromotion[promotion_name],0)) -> Seasonal | C52: =INDEX(tblModelPromotion[discount_pct],MATCH(A52,tblModelPromotion[promotion_name],0))/100 -> 0.1 | D52: =INDEX(tblModelPromotion[revenue],MATCH(A52,tblModelPromotion[promotion_name],0)) -> 35210698 | E52: =INDEX(tblModelPromotion[margin_pct],MATCH(A52,tblModelPromotion[promotion_name],0)) -> 0.1349 | F52: =INDEX(tblModelPromotion[baseline_margin_pct],MATCH(A52,tblModelPromotion[promotion_name],0)) -> 0.2226 | G52: =E52-F52 -> -0.0877 | H52: =INDEX(tblModelPromotion[aov_lift_pct],MATCH(A52,tblModelPromotion[promotion_name],0)) -> 0.0773 | I52: =IF(AND(G52>=$L$1,H52>=$L$2),"Continue - efficient lift for margin cost",IF(AND(G52<=$L$3,H52<$L$2),"Discontinue - high margin cost, weak lift","Review - mixed signal")) -> Continue - efficient lift for margin cost
A53: =INDEX(tblModelPromotion[promotion_name],MATCH("Festive Jan2023 - 10% Off",tblModelPromotion[promotion_name],0)) -> Festive Jan2023 - 10% Off | B53: =INDEX(tblModelPromotion[promotion_type],MATCH(A53,tblModelPromotion[promotion_name],0)) -> Festive | C53: =INDEX(tblModelPromotion[discount_pct],MATCH(A53,tblModelPromotion[promotion_name],0))/100 -> 0.1 | D53: =INDEX(tblModelPromotion[revenue],MATCH(A53,tblModelPromotion[promotion_name],0)) -> 64163824 | E53: =INDEX(tblModelPromotion[margin_pct],MATCH(A53,tblModelPromotion[promotion_name],0)) -> 0.1344 | F53: =INDEX(tblModelPromotion[baseline_margin_pct],MATCH(A53,tblModelPromotion[promotion_name],0)) -> 0.2226 | G53: =E53-F53 -> -0.0882 | H53: =INDEX(tblModelPromotion[aov_lift_pct],MATCH(A53,tblModelPromotion[promotion_name],0)) -> 0.1271 | I53: =IF(AND(G53>=$L$1,H53>=$L$2),"Continue - efficient lift for margin cost",IF(AND(G53<=$L$3,H53<$L$2),"Discontinue - high margin cost, weak lift","Review - mixed signal")) -> Continue - efficient lift for margin cost
A54: =INDEX(tblModelPromotion[promotion_name],MATCH("Seasonal Aug2021 - 10% Off",tblModelPromotion[promotion_name],0)) -> Seasonal Aug2021 - 10% Off | B54: =INDEX(tblModelPromotion[promotion_type],MATCH(A54,tblModelPromotion[promotion_name],0)) -> Seasonal | C54: =INDEX(tblModelPromotion[discount_pct],MATCH(A54,tblModelPromotion[promotion_name],0))/100 -> 0.1 | D54: =INDEX(tblModelPromotion[revenue],MATCH(A54,tblModelPromotion[promotion_name],0)) -> 35557539 | E54: =INDEX(tblModelPromotion[margin_pct],MATCH(A54,tblModelPromotion[promotion_name],0)) -> 0.1344 | F54: =INDEX(tblModelPromotion[baseline_margin_pct],MATCH(A54,tblModelPromotion[promotion_name],0)) -> 0.2226 | G54: =E54-F54 -> -0.0882 | H54: =INDEX(tblModelPromotion[aov_lift_pct],MATCH(A54,tblModelPromotion[promotion_name],0)) -> 0.1017 | I54: =IF(AND(G54>=$L$1,H54>=$L$2),"Continue - efficient lift for margin cost",IF(AND(G54<=$L$3,H54<$L$2),"Discontinue - high margin cost, weak lift","Review - mixed signal")) -> Continue - efficient lift for margin cost
A55: =INDEX(tblModelPromotion[promotion_name],MATCH("Clearance Nov2022 - 10% Off",tblModelPromotion[promotion_name],0)) -> Clearance Nov2022 - 10% Off | B55: =INDEX(tblModelPromotion[promotion_type],MATCH(A55,tblModelPromotion[promotion_name],0)) -> Clearance | C55: =INDEX(tblModelPromotion[discount_pct],MATCH(A55,tblModelPromotion[promotion_name],0))/100 -> 0.1 | D55: =INDEX(tblModelPromotion[revenue],MATCH(A55,tblModelPromotion[promotion_name],0)) -> 66708635 | E55: =INDEX(tblModelPromotion[margin_pct],MATCH(A55,tblModelPromotion[promotion_name],0)) -> 0.1325 | F55: =INDEX(tblModelPromotion[baseline_margin_pct],MATCH(A55,tblModelPromotion[promotion_name],0)) -> 0.2226 | G55: =E55-F55 -> -0.0901 | H55: =INDEX(tblModelPromotion[aov_lift_pct],MATCH(A55,tblModelPromotion[promotion_name],0)) -> 0.011 | I55: =IF(AND(G55>=$L$1,H55>=$L$2),"Continue - efficient lift for margin cost",IF(AND(G55<=$L$3,H55<$L$2),"Discontinue - high margin cost, weak lift","Review - mixed signal")) -> Continue - efficient lift for margin cost
A56: =INDEX(tblModelPromotion[promotion_name],MATCH("Seasonal Sep2021 - 10% Off",tblModelPromotion[promotion_name],0)) -> Seasonal Sep2021 - 10% Off | B56: =INDEX(tblModelPromotion[promotion_type],MATCH(A56,tblModelPromotion[promotion_name],0)) -> Seasonal | C56: =INDEX(tblModelPromotion[discount_pct],MATCH(A56,tblModelPromotion[promotion_name],0))/100 -> 0.1 | D56: =INDEX(tblModelPromotion[revenue],MATCH(A56,tblModelPromotion[promotion_name],0)) -> 17587227 | E56: =INDEX(tblModelPromotion[margin_pct],MATCH(A56,tblModelPromotion[promotion_name],0)) -> 0.1324 | F56: =INDEX(tblModelPromotion[baseline_margin_pct],MATCH(A56,tblModelPromotion[promotion_name],0)) -> 0.2226 | G56: =E56-F56 -> -0.0902 | H56: =INDEX(tblModelPromotion[aov_lift_pct],MATCH(A56,tblModelPromotion[promotion_name],0)) -> -0.0142 | I56: =IF(AND(G56>=$L$1,H56>=$L$2),"Continue - efficient lift for margin cost",IF(AND(G56<=$L$3,H56<$L$2),"Discontinue - high margin cost, weak lift","Review - mixed signal")) -> Review - mixed signal
A57: =INDEX(tblModelPromotion[promotion_name],MATCH("Clearance Feb2024 - 10% Off",tblModelPromotion[promotion_name],0)) -> Clearance Feb2024 - 10% Off | B57: =INDEX(tblModelPromotion[promotion_type],MATCH(A57,tblModelPromotion[promotion_name],0)) -> Clearance | C57: =INDEX(tblModelPromotion[discount_pct],MATCH(A57,tblModelPromotion[promotion_name],0))/100 -> 0.1 | D57: =INDEX(tblModelPromotion[revenue],MATCH(A57,tblModelPromotion[promotion_name],0)) -> 54702959 | E57: =INDEX(tblModelPromotion[margin_pct],MATCH(A57,tblModelPromotion[promotion_name],0)) -> 0.132 | F57: =INDEX(tblModelPromotion[baseline_margin_pct],MATCH(A57,tblModelPromotion[promotion_name],0)) -> 0.2226 | G57: =E57-F57 -> -0.0906 | H57: =INDEX(tblModelPromotion[aov_lift_pct],MATCH(A57,tblModelPromotion[promotion_name],0)) -> 0.1559 | I57: =IF(AND(G57>=$L$1,H57>=$L$2),"Continue - efficient lift for margin cost",IF(AND(G57<=$L$3,H57<$L$2),"Discontinue - high margin cost, weak lift","Review - mixed signal")) -> Continue - efficient lift for margin cost
A58: =INDEX(tblModelPromotion[promotion_name],MATCH("Seasonal May2024 - 10% Off",tblModelPromotion[promotion_name],0)) -> Seasonal May2024 - 10% Off | B58: =INDEX(tblModelPromotion[promotion_type],MATCH(A58,tblModelPromotion[promotion_name],0)) -> Seasonal | C58: =INDEX(tblModelPromotion[discount_pct],MATCH(A58,tblModelPromotion[promotion_name],0))/100 -> 0.1 | D58: =INDEX(tblModelPromotion[revenue],MATCH(A58,tblModelPromotion[promotion_name],0)) -> 62410944 | E58: =INDEX(tblModelPromotion[margin_pct],MATCH(A58,tblModelPromotion[promotion_name],0)) -> 0.1306 | F58: =INDEX(tblModelPromotion[baseline_margin_pct],MATCH(A58,tblModelPromotion[promotion_name],0)) -> 0.2226 | G58: =E58-F58 -> -0.092 | H58: =INDEX(tblModelPromotion[aov_lift_pct],MATCH(A58,tblModelPromotion[promotion_name],0)) -> 0.0695 | I58: =IF(AND(G58>=$L$1,H58>=$L$2),"Continue - efficient lift for margin cost",IF(AND(G58<=$L$3,H58<$L$2),"Discontinue - high margin cost, weak lift","Review - mixed signal")) -> Continue - efficient lift for margin cost
A59: =INDEX(tblModelPromotion[promotion_name],MATCH("Loyalty Mar2024 - 10% Off",tblModelPromotion[promotion_name],0)) -> Loyalty Mar2024 - 10% Off | B59: =INDEX(tblModelPromotion[promotion_type],MATCH(A59,tblModelPromotion[promotion_name],0)) -> Loyalty | C59: =INDEX(tblModelPromotion[discount_pct],MATCH(A59,tblModelPromotion[promotion_name],0))/100 -> 0.1 | D59: =INDEX(tblModelPromotion[revenue],MATCH(A59,tblModelPromotion[promotion_name],0)) -> 22833583 | E59: =INDEX(tblModelPromotion[margin_pct],MATCH(A59,tblModelPromotion[promotion_name],0)) -> 0.1256 | F59: =INDEX(tblModelPromotion[baseline_margin_pct],MATCH(A59,tblModelPromotion[promotion_name],0)) -> 0.2226 | G59: =E59-F59 -> -0.097 | H59: =INDEX(tblModelPromotion[aov_lift_pct],MATCH(A59,tblModelPromotion[promotion_name],0)) -> 0.2328 | I59: =IF(AND(G59>=$L$1,H59>=$L$2),"Continue - efficient lift for margin cost",IF(AND(G59<=$L$3,H59<$L$2),"Discontinue - high margin cost, weak lift","Review - mixed signal")) -> Continue - efficient lift for margin cost
A60: =INDEX(tblModelPromotion[promotion_name],MATCH("Seasonal Jun2021 - 10% Off",tblModelPromotion[promotion_name],0)) -> Seasonal Jun2021 - 10% Off | B60: =INDEX(tblModelPromotion[promotion_type],MATCH(A60,tblModelPromotion[promotion_name],0)) -> Seasonal | C60: =INDEX(tblModelPromotion[discount_pct],MATCH(A60,tblModelPromotion[promotion_name],0))/100 -> 0.1 | D60: =INDEX(tblModelPromotion[revenue],MATCH(A60,tblModelPromotion[promotion_name],0)) -> 14303457 | E60: =INDEX(tblModelPromotion[margin_pct],MATCH(A60,tblModelPromotion[promotion_name],0)) -> 0.1352 | F60: =INDEX(tblModelPromotion[baseline_margin_pct],MATCH(A60,tblModelPromotion[promotion_name],0)) -> 0.2226 | G60: =E60-F60 -> -0.0874 | H60: =INDEX(tblModelPromotion[aov_lift_pct],MATCH(A60,tblModelPromotion[promotion_name],0)) -> 0.1354 | I60: =IF(AND(G60>=$L$1,H60>=$L$2),"Continue - efficient lift for margin cost",IF(AND(G60<=$L$3,H60<$L$2),"Discontinue - high margin cost, weak lift","Review - mixed signal")) -> Continue - efficient lift for margin cost
A61: =INDEX(tblModelPromotion[promotion_name],MATCH("Seasonal Jul2024 - 12% Off",tblModelPromotion[promotion_name],0)) -> Seasonal Jul2024 - 12% Off | B61: =INDEX(tblModelPromotion[promotion_type],MATCH(A61,tblModelPromotion[promotion_name],0)) -> Seasonal | C61: =INDEX(tblModelPromotion[discount_pct],MATCH(A61,tblModelPromotion[promotion_name],0))/100 -> 0.12 | D61: =INDEX(tblModelPromotion[revenue],MATCH(A61,tblModelPromotion[promotion_name],0)) -> 63959652 | E61: =INDEX(tblModelPromotion[margin_pct],MATCH(A61,tblModelPromotion[promotion_name],0)) -> 0.1229 | F61: =INDEX(tblModelPromotion[baseline_margin_pct],MATCH(A61,tblModelPromotion[promotion_name],0)) -> 0.2226 | G61: =E61-F61 -> -0.0997 | H61: =INDEX(tblModelPromotion[aov_lift_pct],MATCH(A61,tblModelPromotion[promotion_name],0)) -> -0.0483 | I61: =IF(AND(G61>=$L$1,H61>=$L$2),"Continue - efficient lift for margin cost",IF(AND(G61<=$L$3,H61<$L$2),"Discontinue - high margin cost, weak lift","Review - mixed signal")) -> Review - mixed signal
A62: =INDEX(tblModelPromotion[promotion_name],MATCH("Festive Apr2024 - 12% Off",tblModelPromotion[promotion_name],0)) -> Festive Apr2024 - 12% Off | B62: =INDEX(tblModelPromotion[promotion_type],MATCH(A62,tblModelPromotion[promotion_name],0)) -> Festive | C62: =INDEX(tblModelPromotion[discount_pct],MATCH(A62,tblModelPromotion[promotion_name],0))/100 -> 0.12 | D62: =INDEX(tblModelPromotion[revenue],MATCH(A62,tblModelPromotion[promotion_name],0)) -> 75489956 | E62: =INDEX(tblModelPromotion[margin_pct],MATCH(A62,tblModelPromotion[promotion_name],0)) -> 0.1202 | F62: =INDEX(tblModelPromotion[baseline_margin_pct],MATCH(A62,tblModelPromotion[promotion_name],0)) -> 0.2226 | G62: =E62-F62 -> -0.1024 | H62: =INDEX(tblModelPromotion[aov_lift_pct],MATCH(A62,tblModelPromotion[promotion_name],0)) -> 0.0508 | I62: =IF(AND(G62>=$L$1,H62>=$L$2),"Continue - efficient lift for margin cost",IF(AND(G62<=$L$3,H62<$L$2),"Discontinue - high margin cost, weak lift","Review - mixed signal")) -> Continue - efficient lift for margin cost
A63: =INDEX(tblModelPromotion[promotion_name],MATCH("Festive Nov2024 - 12% Off",tblModelPromotion[promotion_name],0)) -> Festive Nov2024 - 12% Off | B63: =INDEX(tblModelPromotion[promotion_type],MATCH(A63,tblModelPromotion[promotion_name],0)) -> Festive | C63: =INDEX(tblModelPromotion[discount_pct],MATCH(A63,tblModelPromotion[promotion_name],0))/100 -> 0.12 | D63: =INDEX(tblModelPromotion[revenue],MATCH(A63,tblModelPromotion[promotion_name],0)) -> 53757613 | E63: =INDEX(tblModelPromotion[margin_pct],MATCH(A63,tblModelPromotion[promotion_name],0)) -> 0.1198 | F63: =INDEX(tblModelPromotion[baseline_margin_pct],MATCH(A63,tblModelPromotion[promotion_name],0)) -> 0.2226 | G63: =E63-F63 -> -0.1028 | H63: =INDEX(tblModelPromotion[aov_lift_pct],MATCH(A63,tblModelPromotion[promotion_name],0)) -> 0.0374 | I63: =IF(AND(G63>=$L$1,H63>=$L$2),"Continue - efficient lift for margin cost",IF(AND(G63<=$L$3,H63<$L$2),"Discontinue - high margin cost, weak lift","Review - mixed signal")) -> Continue - efficient lift for margin cost
A64: =INDEX(tblModelPromotion[promotion_name],MATCH("Seasonal Feb2023 - 12% Off",tblModelPromotion[promotion_name],0)) -> Seasonal Feb2023 - 12% Off | B64: =INDEX(tblModelPromotion[promotion_type],MATCH(A64,tblModelPromotion[promotion_name],0)) -> Seasonal | C64: =INDEX(tblModelPromotion[discount_pct],MATCH(A64,tblModelPromotion[promotion_name],0))/100 -> 0.12 | D64: =INDEX(tblModelPromotion[revenue],MATCH(A64,tblModelPromotion[promotion_name],0)) -> 40724648 | E64: =INDEX(tblModelPromotion[margin_pct],MATCH(A64,tblModelPromotion[promotion_name],0)) -> 0.1198 | F64: =INDEX(tblModelPromotion[baseline_margin_pct],MATCH(A64,tblModelPromotion[promotion_name],0)) -> 0.2226 | G64: =E64-F64 -> -0.1028 | H64: =INDEX(tblModelPromotion[aov_lift_pct],MATCH(A64,tblModelPromotion[promotion_name],0)) -> 0.0241 | I64: =IF(AND(G64>=$L$1,H64>=$L$2),"Continue - efficient lift for margin cost",IF(AND(G64<=$L$3,H64<$L$2),"Discontinue - high margin cost, weak lift","Review - mixed signal")) -> Continue - efficient lift for margin cost
A65: =INDEX(tblModelPromotion[promotion_name],MATCH("Flash Sale Jun2021 - 12% Off",tblModelPromotion[promotion_name],0)) -> Flash Sale Jun2021 - 12% Off | B65: =INDEX(tblModelPromotion[promotion_type],MATCH(A65,tblModelPromotion[promotion_name],0)) -> Flash Sale | C65: =INDEX(tblModelPromotion[discount_pct],MATCH(A65,tblModelPromotion[promotion_name],0))/100 -> 0.12 | D65: =INDEX(tblModelPromotion[revenue],MATCH(A65,tblModelPromotion[promotion_name],0)) -> 12727031 | E65: =INDEX(tblModelPromotion[margin_pct],MATCH(A65,tblModelPromotion[promotion_name],0)) -> 0.1193 | F65: =INDEX(tblModelPromotion[baseline_margin_pct],MATCH(A65,tblModelPromotion[promotion_name],0)) -> 0.2226 | G65: =E65-F65 -> -0.1033 | H65: =INDEX(tblModelPromotion[aov_lift_pct],MATCH(A65,tblModelPromotion[promotion_name],0)) -> -0.0883 | I65: =IF(AND(G65>=$L$1,H65>=$L$2),"Continue - efficient lift for margin cost",IF(AND(G65<=$L$3,H65<$L$2),"Discontinue - high margin cost, weak lift","Review - mixed signal")) -> Review - mixed signal
A66: =INDEX(tblModelPromotion[promotion_name],MATCH("Seasonal Aug2021 - 12% Off",tblModelPromotion[promotion_name],0)) -> Seasonal Aug2021 - 12% Off | B66: =INDEX(tblModelPromotion[promotion_type],MATCH(A66,tblModelPromotion[promotion_name],0)) -> Seasonal | C66: =INDEX(tblModelPromotion[discount_pct],MATCH(A66,tblModelPromotion[promotion_name],0))/100 -> 0.12 | D66: =INDEX(tblModelPromotion[revenue],MATCH(A66,tblModelPromotion[promotion_name],0)) -> 50813992 | E66: =INDEX(tblModelPromotion[margin_pct],MATCH(A66,tblModelPromotion[promotion_name],0)) -> 0.1188 | F66: =INDEX(tblModelPromotion[baseline_margin_pct],MATCH(A66,tblModelPromotion[promotion_name],0)) -> 0.2226 | G66: =E66-F66 -> -0.1038 | H66: =INDEX(tblModelPromotion[aov_lift_pct],MATCH(A66,tblModelPromotion[promotion_name],0)) -> 0.1105 | I66: =IF(AND(G66>=$L$1,H66>=$L$2),"Continue - efficient lift for margin cost",IF(AND(G66<=$L$3,H66<$L$2),"Discontinue - high margin cost, weak lift","Review - mixed signal")) -> Continue - efficient lift for margin cost
A67: =INDEX(tblModelPromotion[promotion_name],MATCH("Loyalty Feb2023 - 12% Off",tblModelPromotion[promotion_name],0)) -> Loyalty Feb2023 - 12% Off | B67: =INDEX(tblModelPromotion[promotion_type],MATCH(A67,tblModelPromotion[promotion_name],0)) -> Loyalty | C67: =INDEX(tblModelPromotion[discount_pct],MATCH(A67,tblModelPromotion[promotion_name],0))/100 -> 0.12 | D67: =INDEX(tblModelPromotion[revenue],MATCH(A67,tblModelPromotion[promotion_name],0)) -> 15954420 | E67: =INDEX(tblModelPromotion[margin_pct],MATCH(A67,tblModelPromotion[promotion_name],0)) -> 0.1186 | F67: =INDEX(tblModelPromotion[baseline_margin_pct],MATCH(A67,tblModelPromotion[promotion_name],0)) -> 0.2226 | G67: =E67-F67 -> -0.104 | H67: =INDEX(tblModelPromotion[aov_lift_pct],MATCH(A67,tblModelPromotion[promotion_name],0)) -> -0.0114 | I67: =IF(AND(G67>=$L$1,H67>=$L$2),"Continue - efficient lift for margin cost",IF(AND(G67<=$L$3,H67<$L$2),"Discontinue - high margin cost, weak lift","Review - mixed signal")) -> Review - mixed signal
A68: =INDEX(tblModelPromotion[promotion_name],MATCH("Loyalty Aug2024 - 12% Off",tblModelPromotion[promotion_name],0)) -> Loyalty Aug2024 - 12% Off | B68: =INDEX(tblModelPromotion[promotion_type],MATCH(A68,tblModelPromotion[promotion_name],0)) -> Loyalty | C68: =INDEX(tblModelPromotion[discount_pct],MATCH(A68,tblModelPromotion[promotion_name],0))/100 -> 0.12 | D68: =INDEX(tblModelPromotion[revenue],MATCH(A68,tblModelPromotion[promotion_name],0)) -> 39967561 | E68: =INDEX(tblModelPromotion[margin_pct],MATCH(A68,tblModelPromotion[promotion_name],0)) -> 0.1185 | F68: =INDEX(tblModelPromotion[baseline_margin_pct],MATCH(A68,tblModelPromotion[promotion_name],0)) -> 0.2226 | G68: =E68-F68 -> -0.1041 | H68: =INDEX(tblModelPromotion[aov_lift_pct],MATCH(A68,tblModelPromotion[promotion_name],0)) -> 0.0576 | I68: =IF(AND(G68>=$L$1,H68>=$L$2),"Continue - efficient lift for margin cost",IF(AND(G68<=$L$3,H68<$L$2),"Discontinue - high margin cost, weak lift","Review - mixed signal")) -> Continue - efficient lift for margin cost
A69: =INDEX(tblModelPromotion[promotion_name],MATCH("Flash Sale May2024 - 12% Off",tblModelPromotion[promotion_name],0)) -> Flash Sale May2024 - 12% Off | B69: =INDEX(tblModelPromotion[promotion_type],MATCH(A69,tblModelPromotion[promotion_name],0)) -> Flash Sale | C69: =INDEX(tblModelPromotion[discount_pct],MATCH(A69,tblModelPromotion[promotion_name],0))/100 -> 0.12 | D69: =INDEX(tblModelPromotion[revenue],MATCH(A69,tblModelPromotion[promotion_name],0)) -> 56475275 | E69: =INDEX(tblModelPromotion[margin_pct],MATCH(A69,tblModelPromotion[promotion_name],0)) -> 0.1176 | F69: =INDEX(tblModelPromotion[baseline_margin_pct],MATCH(A69,tblModelPromotion[promotion_name],0)) -> 0.2226 | G69: =E69-F69 -> -0.105 | H69: =INDEX(tblModelPromotion[aov_lift_pct],MATCH(A69,tblModelPromotion[promotion_name],0)) -> 0.0512 | I69: =IF(AND(G69>=$L$1,H69>=$L$2),"Continue - efficient lift for margin cost",IF(AND(G69<=$L$3,H69<$L$2),"Discontinue - high margin cost, weak lift","Review - mixed signal")) -> Continue - efficient lift for margin cost
A70: =INDEX(tblModelPromotion[promotion_name],MATCH("Festive Dec2022 - 12% Off",tblModelPromotion[promotion_name],0)) -> Festive Dec2022 - 12% Off | B70: =INDEX(tblModelPromotion[promotion_type],MATCH(A70,tblModelPromotion[promotion_name],0)) -> Festive | C70: =INDEX(tblModelPromotion[discount_pct],MATCH(A70,tblModelPromotion[promotion_name],0))/100 -> 0.12 | D70: =INDEX(tblModelPromotion[revenue],MATCH(A70,tblModelPromotion[promotion_name],0)) -> 63007288 | E70: =INDEX(tblModelPromotion[margin_pct],MATCH(A70,tblModelPromotion[promotion_name],0)) -> 0.1168 | F70: =INDEX(tblModelPromotion[baseline_margin_pct],MATCH(A70,tblModelPromotion[promotion_name],0)) -> 0.2226 | G70: =E70-F70 -> -0.1058 | H70: =INDEX(tblModelPromotion[aov_lift_pct],MATCH(A70,tblModelPromotion[promotion_name],0)) -> 0.0047 | I70: =IF(AND(G70>=$L$1,H70>=$L$2),"Continue - efficient lift for margin cost",IF(AND(G70<=$L$3,H70<$L$2),"Discontinue - high margin cost, weak lift","Review - mixed signal")) -> Continue - efficient lift for margin cost
A71: =INDEX(tblModelPromotion[promotion_name],MATCH("Seasonal Jun2022 - 12% Off",tblModelPromotion[promotion_name],0)) -> Seasonal Jun2022 - 12% Off | B71: =INDEX(tblModelPromotion[promotion_type],MATCH(A71,tblModelPromotion[promotion_name],0)) -> Seasonal | C71: =INDEX(tblModelPromotion[discount_pct],MATCH(A71,tblModelPromotion[promotion_name],0))/100 -> 0.12 | D71: =INDEX(tblModelPromotion[revenue],MATCH(A71,tblModelPromotion[promotion_name],0)) -> 39624919 | E71: =INDEX(tblModelPromotion[margin_pct],MATCH(A71,tblModelPromotion[promotion_name],0)) -> 0.1163 | F71: =INDEX(tblModelPromotion[baseline_margin_pct],MATCH(A71,tblModelPromotion[promotion_name],0)) -> 0.2226 | G71: =E71-F71 -> -0.1063 | H71: =INDEX(tblModelPromotion[aov_lift_pct],MATCH(A71,tblModelPromotion[promotion_name],0)) -> 0.0542 | I71: =IF(AND(G71>=$L$1,H71>=$L$2),"Continue - efficient lift for margin cost",IF(AND(G71<=$L$3,H71<$L$2),"Discontinue - high margin cost, weak lift","Review - mixed signal")) -> Continue - efficient lift for margin cost
A72: =INDEX(tblModelPromotion[promotion_name],MATCH("Festive May2021 - 12% Off",tblModelPromotion[promotion_name],0)) -> Festive May2021 - 12% Off | B72: =INDEX(tblModelPromotion[promotion_type],MATCH(A72,tblModelPromotion[promotion_name],0)) -> Festive | C72: =INDEX(tblModelPromotion[discount_pct],MATCH(A72,tblModelPromotion[promotion_name],0))/100 -> 0.12 | D72: =INDEX(tblModelPromotion[revenue],MATCH(A72,tblModelPromotion[promotion_name],0)) -> 39715124 | E72: =INDEX(tblModelPromotion[margin_pct],MATCH(A72,tblModelPromotion[promotion_name],0)) -> 0.1141 | F72: =INDEX(tblModelPromotion[baseline_margin_pct],MATCH(A72,tblModelPromotion[promotion_name],0)) -> 0.2226 | G72: =E72-F72 -> -0.1085 | H72: =INDEX(tblModelPromotion[aov_lift_pct],MATCH(A72,tblModelPromotion[promotion_name],0)) -> 0.1131 | I72: =IF(AND(G72>=$L$1,H72>=$L$2),"Continue - efficient lift for margin cost",IF(AND(G72<=$L$3,H72<$L$2),"Discontinue - high margin cost, weak lift","Review - mixed signal")) -> Continue - efficient lift for margin cost
A73: =INDEX(tblModelPromotion[promotion_name],MATCH("Seasonal Jun2021 - 12% Off",tblModelPromotion[promotion_name],0)) -> Seasonal Jun2021 - 12% Off | B73: =INDEX(tblModelPromotion[promotion_type],MATCH(A73,tblModelPromotion[promotion_name],0)) -> Seasonal | C73: =INDEX(tblModelPromotion[discount_pct],MATCH(A73,tblModelPromotion[promotion_name],0))/100 -> 0.12 | D73: =INDEX(tblModelPromotion[revenue],MATCH(A73,tblModelPromotion[promotion_name],0)) -> 27851096 | E73: =INDEX(tblModelPromotion[margin_pct],MATCH(A73,tblModelPromotion[promotion_name],0)) -> 0.1162 | F73: =INDEX(tblModelPromotion[baseline_margin_pct],MATCH(A73,tblModelPromotion[promotion_name],0)) -> 0.2226 | G73: =E73-F73 -> -0.1064 | H73: =INDEX(tblModelPromotion[aov_lift_pct],MATCH(A73,tblModelPromotion[promotion_name],0)) -> 0.0792 | I73: =IF(AND(G73>=$L$1,H73>=$L$2),"Continue - efficient lift for margin cost",IF(AND(G73<=$L$3,H73<$L$2),"Discontinue - high margin cost, weak lift","Review - mixed signal")) -> Continue - efficient lift for margin cost
A74: =INDEX(tblModelPromotion[promotion_name],MATCH("Festive Apr2021 - 12% Off",tblModelPromotion[promotion_name],0)) -> Festive Apr2021 - 12% Off | B74: =INDEX(tblModelPromotion[promotion_type],MATCH(A74,tblModelPromotion[promotion_name],0)) -> Festive | C74: =INDEX(tblModelPromotion[discount_pct],MATCH(A74,tblModelPromotion[promotion_name],0))/100 -> 0.12 | D74: =INDEX(tblModelPromotion[revenue],MATCH(A74,tblModelPromotion[promotion_name],0)) -> 28164943 | E74: =INDEX(tblModelPromotion[margin_pct],MATCH(A74,tblModelPromotion[promotion_name],0)) -> 0.1159 | F74: =INDEX(tblModelPromotion[baseline_margin_pct],MATCH(A74,tblModelPromotion[promotion_name],0)) -> 0.2226 | G74: =E74-F74 -> -0.1067 | H74: =INDEX(tblModelPromotion[aov_lift_pct],MATCH(A74,tblModelPromotion[promotion_name],0)) -> -0.0381 | I74: =IF(AND(G74>=$L$1,H74>=$L$2),"Continue - efficient lift for margin cost",IF(AND(G74<=$L$3,H74<$L$2),"Discontinue - high margin cost, weak lift","Review - mixed signal")) -> Review - mixed signal
A75: =INDEX(tblModelPromotion[promotion_name],MATCH("Seasonal Nov2022 - 12% Off",tblModelPromotion[promotion_name],0)) -> Seasonal Nov2022 - 12% Off | B75: =INDEX(tblModelPromotion[promotion_type],MATCH(A75,tblModelPromotion[promotion_name],0)) -> Seasonal | C75: =INDEX(tblModelPromotion[discount_pct],MATCH(A75,tblModelPromotion[promotion_name],0))/100 -> 0.12 | D75: =INDEX(tblModelPromotion[revenue],MATCH(A75,tblModelPromotion[promotion_name],0)) -> 130476222 | E75: =INDEX(tblModelPromotion[margin_pct],MATCH(A75,tblModelPromotion[promotion_name],0)) -> 0.1151 | F75: =INDEX(tblModelPromotion[baseline_margin_pct],MATCH(A75,tblModelPromotion[promotion_name],0)) -> 0.2226 | G75: =E75-F75 -> -0.1075 | H75: =INDEX(tblModelPromotion[aov_lift_pct],MATCH(A75,tblModelPromotion[promotion_name],0)) -> 0.0112 | I75: =IF(AND(G75>=$L$1,H75>=$L$2),"Continue - efficient lift for margin cost",IF(AND(G75<=$L$3,H75<$L$2),"Discontinue - high margin cost, weak lift","Review - mixed signal")) -> Continue - efficient lift for margin cost
A76: =INDEX(tblModelPromotion[promotion_name],MATCH("Loyalty Aug2022 - 12% Off",tblModelPromotion[promotion_name],0)) -> Loyalty Aug2022 - 12% Off | B76: =INDEX(tblModelPromotion[promotion_type],MATCH(A76,tblModelPromotion[promotion_name],0)) -> Loyalty | C76: =INDEX(tblModelPromotion[discount_pct],MATCH(A76,tblModelPromotion[promotion_name],0))/100 -> 0.12 | D76: =INDEX(tblModelPromotion[revenue],MATCH(A76,tblModelPromotion[promotion_name],0)) -> 63984834 | E76: =INDEX(tblModelPromotion[margin_pct],MATCH(A76,tblModelPromotion[promotion_name],0)) -> 0.1144 | F76: =INDEX(tblModelPromotion[baseline_margin_pct],MATCH(A76,tblModelPromotion[promotion_name],0)) -> 0.2226 | G76: =E76-F76 -> -0.1082 | H76: =INDEX(tblModelPromotion[aov_lift_pct],MATCH(A76,tblModelPromotion[promotion_name],0)) -> 0.0406 | I76: =IF(AND(G76>=$L$1,H76>=$L$2),"Continue - efficient lift for margin cost",IF(AND(G76<=$L$3,H76<$L$2),"Discontinue - high margin cost, weak lift","Review - mixed signal")) -> Continue - efficient lift for margin cost
A77: =INDEX(tblModelPromotion[promotion_name],MATCH("Seasonal Nov2023 - 12% Off",tblModelPromotion[promotion_name],0)) -> Seasonal Nov2023 - 12% Off | B77: =INDEX(tblModelPromotion[promotion_type],MATCH(A77,tblModelPromotion[promotion_name],0)) -> Seasonal | C77: =INDEX(tblModelPromotion[discount_pct],MATCH(A77,tblModelPromotion[promotion_name],0))/100 -> 0.12 | D77: =INDEX(tblModelPromotion[revenue],MATCH(A77,tblModelPromotion[promotion_name],0)) -> 69467874 | E77: =INDEX(tblModelPromotion[margin_pct],MATCH(A77,tblModelPromotion[promotion_name],0)) -> 0.1142 | F77: =INDEX(tblModelPromotion[baseline_margin_pct],MATCH(A77,tblModelPromotion[promotion_name],0)) -> 0.2226 | G77: =E77-F77 -> -0.1084 | H77: =INDEX(tblModelPromotion[aov_lift_pct],MATCH(A77,tblModelPromotion[promotion_name],0)) -> 0.1186 | I77: =IF(AND(G77>=$L$1,H77>=$L$2),"Continue - efficient lift for margin cost",IF(AND(G77<=$L$3,H77<$L$2),"Discontinue - high margin cost, weak lift","Review - mixed signal")) -> Continue - efficient lift for margin cost
A78: =INDEX(tblModelPromotion[promotion_name],MATCH("Loyalty May2023 - 12% Off",tblModelPromotion[promotion_name],0)) -> Loyalty May2023 - 12% Off | B78: =INDEX(tblModelPromotion[promotion_type],MATCH(A78,tblModelPromotion[promotion_name],0)) -> Loyalty | C78: =INDEX(tblModelPromotion[discount_pct],MATCH(A78,tblModelPromotion[promotion_name],0))/100 -> 0.12 | D78: =INDEX(tblModelPromotion[revenue],MATCH(A78,tblModelPromotion[promotion_name],0)) -> 45949738 | E78: =INDEX(tblModelPromotion[margin_pct],MATCH(A78,tblModelPromotion[promotion_name],0)) -> 0.1142 | F78: =INDEX(tblModelPromotion[baseline_margin_pct],MATCH(A78,tblModelPromotion[promotion_name],0)) -> 0.2226 | G78: =E78-F78 -> -0.1084 | H78: =INDEX(tblModelPromotion[aov_lift_pct],MATCH(A78,tblModelPromotion[promotion_name],0)) -> 0.0462 | I78: =IF(AND(G78>=$L$1,H78>=$L$2),"Continue - efficient lift for margin cost",IF(AND(G78<=$L$3,H78<$L$2),"Discontinue - high margin cost, weak lift","Review - mixed signal")) -> Continue - efficient lift for margin cost
A79: =INDEX(tblModelPromotion[promotion_name],MATCH("Festive May2021 - 12% Off",tblModelPromotion[promotion_name],0)) -> Festive May2021 - 12% Off | B79: =INDEX(tblModelPromotion[promotion_type],MATCH(A79,tblModelPromotion[promotion_name],0)) -> Festive | C79: =INDEX(tblModelPromotion[discount_pct],MATCH(A79,tblModelPromotion[promotion_name],0))/100 -> 0.12 | D79: =INDEX(tblModelPromotion[revenue],MATCH(A79,tblModelPromotion[promotion_name],0)) -> 39715124 | E79: =INDEX(tblModelPromotion[margin_pct],MATCH(A79,tblModelPromotion[promotion_name],0)) -> 0.1141 | F79: =INDEX(tblModelPromotion[baseline_margin_pct],MATCH(A79,tblModelPromotion[promotion_name],0)) -> 0.2226 | G79: =E79-F79 -> -0.1085 | H79: =INDEX(tblModelPromotion[aov_lift_pct],MATCH(A79,tblModelPromotion[promotion_name],0)) -> 0.1131 | I79: =IF(AND(G79>=$L$1,H79>=$L$2),"Continue - efficient lift for margin cost",IF(AND(G79<=$L$3,H79<$L$2),"Discontinue - high margin cost, weak lift","Review - mixed signal")) -> Continue - efficient lift for margin cost
A80: =INDEX(tblModelPromotion[promotion_name],MATCH("Festive Mar2024 - 12% Off",tblModelPromotion[promotion_name],0)) -> Festive Mar2024 - 12% Off | B80: =INDEX(tblModelPromotion[promotion_type],MATCH(A80,tblModelPromotion[promotion_name],0)) -> Festive | C80: =INDEX(tblModelPromotion[discount_pct],MATCH(A80,tblModelPromotion[promotion_name],0))/100 -> 0.12 | D80: =INDEX(tblModelPromotion[revenue],MATCH(A80,tblModelPromotion[promotion_name],0)) -> 45722219 | E80: =INDEX(tblModelPromotion[margin_pct],MATCH(A80,tblModelPromotion[promotion_name],0)) -> 0.1092 | F80: =INDEX(tblModelPromotion[baseline_margin_pct],MATCH(A80,tblModelPromotion[promotion_name],0)) -> 0.2226 | G80: =E80-F80 -> -0.1134 | H80: =INDEX(tblModelPromotion[aov_lift_pct],MATCH(A80,tblModelPromotion[promotion_name],0)) -> 0.1637 | I80: =IF(AND(G80>=$L$1,H80>=$L$2),"Continue - efficient lift for margin cost",IF(AND(G80<=$L$3,H80<$L$2),"Discontinue - high margin cost, weak lift","Review - mixed signal")) -> Continue - efficient lift for margin cost
A81: =INDEX(tblModelPromotion[promotion_name],MATCH("Clearance Jul2021 - 12% Off",tblModelPromotion[promotion_name],0)) -> Clearance Jul2021 - 12% Off | B81: =INDEX(tblModelPromotion[promotion_type],MATCH(A81,tblModelPromotion[promotion_name],0)) -> Clearance | C81: =INDEX(tblModelPromotion[discount_pct],MATCH(A81,tblModelPromotion[promotion_name],0))/100 -> 0.12 | D81: =INDEX(tblModelPromotion[revenue],MATCH(A81,tblModelPromotion[promotion_name],0)) -> 48601622 | E81: =INDEX(tblModelPromotion[margin_pct],MATCH(A81,tblModelPromotion[promotion_name],0)) -> 0.1121 | F81: =INDEX(tblModelPromotion[baseline_margin_pct],MATCH(A81,tblModelPromotion[promotion_name],0)) -> 0.2226 | G81: =E81-F81 -> -0.1105 | H81: =INDEX(tblModelPromotion[aov_lift_pct],MATCH(A81,tblModelPromotion[promotion_name],0)) -> 0.059 | I81: =IF(AND(G81>=$L$1,H81>=$L$2),"Continue - efficient lift for margin cost",IF(AND(G81<=$L$3,H81<$L$2),"Discontinue - high margin cost, weak lift","Review - mixed signal")) -> Continue - efficient lift for margin cost
A82: =INDEX(tblModelPromotion[promotion_name],MATCH("Festive Sep2021 - 12% Off",tblModelPromotion[promotion_name],0)) -> Festive Sep2021 - 12% Off | B82: =INDEX(tblModelPromotion[promotion_type],MATCH(A82,tblModelPromotion[promotion_name],0)) -> Festive | C82: =INDEX(tblModelPromotion[discount_pct],MATCH(A82,tblModelPromotion[promotion_name],0))/100 -> 0.12 | D82: =INDEX(tblModelPromotion[revenue],MATCH(A82,tblModelPromotion[promotion_name],0)) -> 19982086 | E82: =INDEX(tblModelPromotion[margin_pct],MATCH(A82,tblModelPromotion[promotion_name],0)) -> 0.1112 | F82: =INDEX(tblModelPromotion[baseline_margin_pct],MATCH(A82,tblModelPromotion[promotion_name],0)) -> 0.2226 | G82: =E82-F82 -> -0.1114 | H82: =INDEX(tblModelPromotion[aov_lift_pct],MATCH(A82,tblModelPromotion[promotion_name],0)) -> 0.0828 | I82: =IF(AND(G82>=$L$1,H82>=$L$2),"Continue - efficient lift for margin cost",IF(AND(G82<=$L$3,H82<$L$2),"Discontinue - high margin cost, weak lift","Review - mixed signal")) -> Continue - efficient lift for margin cost
A83: =INDEX(tblModelPromotion[promotion_name],MATCH("Festive May2023 - 12% Off",tblModelPromotion[promotion_name],0)) -> Festive May2023 - 12% Off | B83: =INDEX(tblModelPromotion[promotion_type],MATCH(A83,tblModelPromotion[promotion_name],0)) -> Festive | C83: =INDEX(tblModelPromotion[discount_pct],MATCH(A83,tblModelPromotion[promotion_name],0))/100 -> 0.12 | D83: =INDEX(tblModelPromotion[revenue],MATCH(A83,tblModelPromotion[promotion_name],0)) -> 42597256 | E83: =INDEX(tblModelPromotion[margin_pct],MATCH(A83,tblModelPromotion[promotion_name],0)) -> 0.1099 | F83: =INDEX(tblModelPromotion[baseline_margin_pct],MATCH(A83,tblModelPromotion[promotion_name],0)) -> 0.2226 | G83: =E83-F83 -> -0.1127 | H83: =INDEX(tblModelPromotion[aov_lift_pct],MATCH(A83,tblModelPromotion[promotion_name],0)) -> 0.0749 | I83: =IF(AND(G83>=$L$1,H83>=$L$2),"Continue - efficient lift for margin cost",IF(AND(G83<=$L$3,H83<$L$2),"Discontinue - high margin cost, weak lift","Review - mixed signal")) -> Continue - efficient lift for margin cost
A84: =INDEX(tblModelPromotion[promotion_name],MATCH("Festive Mar2024 - 12% Off",tblModelPromotion[promotion_name],0)) -> Festive Mar2024 - 12% Off | B84: =INDEX(tblModelPromotion[promotion_type],MATCH(A84,tblModelPromotion[promotion_name],0)) -> Festive | C84: =INDEX(tblModelPromotion[discount_pct],MATCH(A84,tblModelPromotion[promotion_name],0))/100 -> 0.12 | D84: =INDEX(tblModelPromotion[revenue],MATCH(A84,tblModelPromotion[promotion_name],0)) -> 45722219 | E84: =INDEX(tblModelPromotion[margin_pct],MATCH(A84,tblModelPromotion[promotion_name],0)) -> 0.1092 | F84: =INDEX(tblModelPromotion[baseline_margin_pct],MATCH(A84,tblModelPromotion[promotion_name],0)) -> 0.2226 | G84: =E84-F84 -> -0.1134 | H84: =INDEX(tblModelPromotion[aov_lift_pct],MATCH(A84,tblModelPromotion[promotion_name],0)) -> 0.1637 | I84: =IF(AND(G84>=$L$1,H84>=$L$2),"Continue - efficient lift for margin cost",IF(AND(G84<=$L$3,H84<$L$2),"Discontinue - high margin cost, weak lift","Review - mixed signal")) -> Continue - efficient lift for margin cost
A85: =INDEX(tblModelPromotion[promotion_name],MATCH("Loyalty Jun2024 - 12% Off",tblModelPromotion[promotion_name],0)) -> Loyalty Jun2024 - 12% Off | B85: =INDEX(tblModelPromotion[promotion_type],MATCH(A85,tblModelPromotion[promotion_name],0)) -> Loyalty | C85: =INDEX(tblModelPromotion[discount_pct],MATCH(A85,tblModelPromotion[promotion_name],0))/100 -> 0.12 | D85: =INDEX(tblModelPromotion[revenue],MATCH(A85,tblModelPromotion[promotion_name],0)) -> 58991108 | E85: =INDEX(tblModelPromotion[margin_pct],MATCH(A85,tblModelPromotion[promotion_name],0)) -> 0.1076 | F85: =INDEX(tblModelPromotion[baseline_margin_pct],MATCH(A85,tblModelPromotion[promotion_name],0)) -> 0.2226 | G85: =E85-F85 -> -0.115 | H85: =INDEX(tblModelPromotion[aov_lift_pct],MATCH(A85,tblModelPromotion[promotion_name],0)) -> 0.1459 | I85: =IF(AND(G85>=$L$1,H85>=$L$2),"Continue - efficient lift for margin cost",IF(AND(G85<=$L$3,H85<$L$2),"Discontinue - high margin cost, weak lift","Review - mixed signal")) -> Continue - efficient lift for margin cost
A86: =INDEX(tblModelPromotion[promotion_name],MATCH("Seasonal Mar2023 - 15% Off",tblModelPromotion[promotion_name],0)) -> Seasonal Mar2023 - 15% Off | B86: =INDEX(tblModelPromotion[promotion_type],MATCH(A86,tblModelPromotion[promotion_name],0)) -> Seasonal | C86: =INDEX(tblModelPromotion[discount_pct],MATCH(A86,tblModelPromotion[promotion_name],0))/100 -> 0.15 | D86: =INDEX(tblModelPromotion[revenue],MATCH(A86,tblModelPromotion[promotion_name],0)) -> 62418438 | E86: =INDEX(tblModelPromotion[margin_pct],MATCH(A86,tblModelPromotion[promotion_name],0)) -> 0.0816 | F86: =INDEX(tblModelPromotion[baseline_margin_pct],MATCH(A86,tblModelPromotion[promotion_name],0)) -> 0.2226 | G86: =E86-F86 -> -0.141 | H86: =INDEX(tblModelPromotion[aov_lift_pct],MATCH(A86,tblModelPromotion[promotion_name],0)) -> 0.0323 | I86: =IF(AND(G86>=$L$1,H86>=$L$2),"Continue - efficient lift for margin cost",IF(AND(G86<=$L$3,H86<$L$2),"Discontinue - high margin cost, weak lift","Review - mixed signal")) -> Review - mixed signal
A87: =INDEX(tblModelPromotion[promotion_name],MATCH("Clearance Mar2023 - 15% Off",tblModelPromotion[promotion_name],0)) -> Clearance Mar2023 - 15% Off | B87: =INDEX(tblModelPromotion[promotion_type],MATCH(A87,tblModelPromotion[promotion_name],0)) -> Clearance | C87: =INDEX(tblModelPromotion[discount_pct],MATCH(A87,tblModelPromotion[promotion_name],0))/100 -> 0.15 | D87: =INDEX(tblModelPromotion[revenue],MATCH(A87,tblModelPromotion[promotion_name],0)) -> 20524110 | E87: =INDEX(tblModelPromotion[margin_pct],MATCH(A87,tblModelPromotion[promotion_name],0)) -> 0.0902 | F87: =INDEX(tblModelPromotion[baseline_margin_pct],MATCH(A87,tblModelPromotion[promotion_name],0)) -> 0.2226 | G87: =E87-F87 -> -0.1324 | H87: =INDEX(tblModelPromotion[aov_lift_pct],MATCH(A87,tblModelPromotion[promotion_name],0)) -> -0.0246 | I87: =IF(AND(G87>=$L$1,H87>=$L$2),"Continue - efficient lift for margin cost",IF(AND(G87<=$L$3,H87<$L$2),"Discontinue - high margin cost, weak lift","Review - mixed signal")) -> Review - mixed signal
A88: =INDEX(tblModelPromotion[promotion_name],MATCH("Seasonal Jul2023 - 15% Off",tblModelPromotion[promotion_name],0)) -> Seasonal Jul2023 - 15% Off | B88: =INDEX(tblModelPromotion[promotion_type],MATCH(A88,tblModelPromotion[promotion_name],0)) -> Seasonal | C88: =INDEX(tblModelPromotion[discount_pct],MATCH(A88,tblModelPromotion[promotion_name],0))/100 -> 0.15 | D88: =INDEX(tblModelPromotion[revenue],MATCH(A88,tblModelPromotion[promotion_name],0)) -> 45123159 | E88: =INDEX(tblModelPromotion[margin_pct],MATCH(A88,tblModelPromotion[promotion_name],0)) -> 0.0897 | F88: =INDEX(tblModelPromotion[baseline_margin_pct],MATCH(A88,tblModelPromotion[promotion_name],0)) -> 0.2226 | G88: =E88-F88 -> -0.1329 | H88: =INDEX(tblModelPromotion[aov_lift_pct],MATCH(A88,tblModelPromotion[promotion_name],0)) -> 0.1175 | I88: =IF(AND(G88>=$L$1,H88>=$L$2),"Continue - efficient lift for margin cost",IF(AND(G88<=$L$3,H88<$L$2),"Discontinue - high margin cost, weak lift","Review - mixed signal")) -> Continue - efficient lift for margin cost
A89: =INDEX(tblModelPromotion[promotion_name],MATCH("Seasonal Mar2024 - 15% Off",tblModelPromotion[promotion_name],0)) -> Seasonal Mar2024 - 15% Off | B89: =INDEX(tblModelPromotion[promotion_type],MATCH(A89,tblModelPromotion[promotion_name],0)) -> Seasonal | C89: =INDEX(tblModelPromotion[discount_pct],MATCH(A89,tblModelPromotion[promotion_name],0))/100 -> 0.15 | D89: =INDEX(tblModelPromotion[revenue],MATCH(A89,tblModelPromotion[promotion_name],0)) -> 42320844 | E89: =INDEX(tblModelPromotion[margin_pct],MATCH(A89,tblModelPromotion[promotion_name],0)) -> 0.0835 | F89: =INDEX(tblModelPromotion[baseline_margin_pct],MATCH(A89,tblModelPromotion[promotion_name],0)) -> 0.2226 | G89: =E89-F89 -> -0.1391 | H89: =INDEX(tblModelPromotion[aov_lift_pct],MATCH(A89,tblModelPromotion[promotion_name],0)) -> 0.0376 | I89: =IF(AND(G89>=$L$1,H89>=$L$2),"Continue - efficient lift for margin cost",IF(AND(G89<=$L$3,H89<$L$2),"Discontinue - high margin cost, weak lift","Review - mixed signal")) -> Continue - efficient lift for margin cost
A90: =INDEX(tblModelPromotion[promotion_name],MATCH("Festive Apr2024 - 15% Off",tblModelPromotion[promotion_name],0)) -> Festive Apr2024 - 15% Off | B90: =INDEX(tblModelPromotion[promotion_type],MATCH(A90,tblModelPromotion[promotion_name],0)) -> Festive | C90: =INDEX(tblModelPromotion[discount_pct],MATCH(A90,tblModelPromotion[promotion_name],0))/100 -> 0.15 | D90: =INDEX(tblModelPromotion[revenue],MATCH(A90,tblModelPromotion[promotion_name],0)) -> 21095923 | E90: =INDEX(tblModelPromotion[margin_pct],MATCH(A90,tblModelPromotion[promotion_name],0)) -> 0.0884 | F90: =INDEX(tblModelPromotion[baseline_margin_pct],MATCH(A90,tblModelPromotion[promotion_name],0)) -> 0.2226 | G90: =E90-F90 -> -0.1342 | H90: =INDEX(tblModelPromotion[aov_lift_pct],MATCH(A90,tblModelPromotion[promotion_name],0)) -> -0.0165 | I90: =IF(AND(G90>=$L$1,H90>=$L$2),"Continue - efficient lift for margin cost",IF(AND(G90<=$L$3,H90<$L$2),"Discontinue - high margin cost, weak lift","Review - mixed signal")) -> Review - mixed signal
A91: =INDEX(tblModelPromotion[promotion_name],MATCH("Festive Jul2024 - 15% Off",tblModelPromotion[promotion_name],0)) -> Festive Jul2024 - 15% Off | B91: =INDEX(tblModelPromotion[promotion_type],MATCH(A91,tblModelPromotion[promotion_name],0)) -> Festive | C91: =INDEX(tblModelPromotion[discount_pct],MATCH(A91,tblModelPromotion[promotion_name],0))/100 -> 0.15 | D91: =INDEX(tblModelPromotion[revenue],MATCH(A91,tblModelPromotion[promotion_name],0)) -> 66212341 | E91: =INDEX(tblModelPromotion[margin_pct],MATCH(A91,tblModelPromotion[promotion_name],0)) -> 0.0883 | F91: =INDEX(tblModelPromotion[baseline_margin_pct],MATCH(A91,tblModelPromotion[promotion_name],0)) -> 0.2226 | G91: =E91-F91 -> -0.1343 | H91: =INDEX(tblModelPromotion[aov_lift_pct],MATCH(A91,tblModelPromotion[promotion_name],0)) -> -0.0006 | I91: =IF(AND(G91>=$L$1,H91>=$L$2),"Continue - efficient lift for margin cost",IF(AND(G91<=$L$3,H91<$L$2),"Discontinue - high margin cost, weak lift","Review - mixed signal")) -> Review - mixed signal
A92: =INDEX(tblModelPromotion[promotion_name],MATCH("Clearance Oct2021 - 15% Off",tblModelPromotion[promotion_name],0)) -> Clearance Oct2021 - 15% Off | B92: =INDEX(tblModelPromotion[promotion_type],MATCH(A92,tblModelPromotion[promotion_name],0)) -> Clearance | C92: =INDEX(tblModelPromotion[discount_pct],MATCH(A92,tblModelPromotion[promotion_name],0))/100 -> 0.15 | D92: =INDEX(tblModelPromotion[revenue],MATCH(A92,tblModelPromotion[promotion_name],0)) -> 34584039 | E92: =INDEX(tblModelPromotion[margin_pct],MATCH(A92,tblModelPromotion[promotion_name],0)) -> 0.0883 | F92: =INDEX(tblModelPromotion[baseline_margin_pct],MATCH(A92,tblModelPromotion[promotion_name],0)) -> 0.2226 | G92: =E92-F92 -> -0.1343 | H92: =INDEX(tblModelPromotion[aov_lift_pct],MATCH(A92,tblModelPromotion[promotion_name],0)) -> 0.0494 | I92: =IF(AND(G92>=$L$1,H92>=$L$2),"Continue - efficient lift for margin cost",IF(AND(G92<=$L$3,H92<$L$2),"Discontinue - high margin cost, weak lift","Review - mixed signal")) -> Continue - efficient lift for margin cost
A93: =INDEX(tblModelPromotion[promotion_name],MATCH("Flash Sale Jun2023 - 15% Off",tblModelPromotion[promotion_name],0)) -> Flash Sale Jun2023 - 15% Off | B93: =INDEX(tblModelPromotion[promotion_type],MATCH(A93,tblModelPromotion[promotion_name],0)) -> Flash Sale | C93: =INDEX(tblModelPromotion[discount_pct],MATCH(A93,tblModelPromotion[promotion_name],0))/100 -> 0.15 | D93: =INDEX(tblModelPromotion[revenue],MATCH(A93,tblModelPromotion[promotion_name],0)) -> 65188184 | E93: =INDEX(tblModelPromotion[margin_pct],MATCH(A93,tblModelPromotion[promotion_name],0)) -> 0.087 | F93: =INDEX(tblModelPromotion[baseline_margin_pct],MATCH(A93,tblModelPromotion[promotion_name],0)) -> 0.2226 | G93: =E93-F93 -> -0.1356 | H93: =INDEX(tblModelPromotion[aov_lift_pct],MATCH(A93,tblModelPromotion[promotion_name],0)) -> 0.0769 | I93: =IF(AND(G93>=$L$1,H93>=$L$2),"Continue - efficient lift for margin cost",IF(AND(G93<=$L$3,H93<$L$2),"Discontinue - high margin cost, weak lift","Review - mixed signal")) -> Continue - efficient lift for margin cost
A94: =INDEX(tblModelPromotion[promotion_name],MATCH("Loyalty Jun2021 - 15% Off",tblModelPromotion[promotion_name],0)) -> Loyalty Jun2021 - 15% Off | B94: =INDEX(tblModelPromotion[promotion_type],MATCH(A94,tblModelPromotion[promotion_name],0)) -> Loyalty | C94: =INDEX(tblModelPromotion[discount_pct],MATCH(A94,tblModelPromotion[promotion_name],0))/100 -> 0.15 | D94: =INDEX(tblModelPromotion[revenue],MATCH(A94,tblModelPromotion[promotion_name],0)) -> 24731521 | E94: =INDEX(tblModelPromotion[margin_pct],MATCH(A94,tblModelPromotion[promotion_name],0)) -> 0.0868 | F94: =INDEX(tblModelPromotion[baseline_margin_pct],MATCH(A94,tblModelPromotion[promotion_name],0)) -> 0.2226 | G94: =E94-F94 -> -0.1358 | H94: =INDEX(tblModelPromotion[aov_lift_pct],MATCH(A94,tblModelPromotion[promotion_name],0)) -> -0.0289 | I94: =IF(AND(G94>=$L$1,H94>=$L$2),"Continue - efficient lift for margin cost",IF(AND(G94<=$L$3,H94<$L$2),"Discontinue - high margin cost, weak lift","Review - mixed signal")) -> Review - mixed signal
A95: =INDEX(tblModelPromotion[promotion_name],MATCH("Clearance Mar2022 - 15% Off",tblModelPromotion[promotion_name],0)) -> Clearance Mar2022 - 15% Off | B95: =INDEX(tblModelPromotion[promotion_type],MATCH(A95,tblModelPromotion[promotion_name],0)) -> Clearance | C95: =INDEX(tblModelPromotion[discount_pct],MATCH(A95,tblModelPromotion[promotion_name],0))/100 -> 0.15 | D95: =INDEX(tblModelPromotion[revenue],MATCH(A95,tblModelPromotion[promotion_name],0)) -> 56011145 | E95: =INDEX(tblModelPromotion[margin_pct],MATCH(A95,tblModelPromotion[promotion_name],0)) -> 0.0865 | F95: =INDEX(tblModelPromotion[baseline_margin_pct],MATCH(A95,tblModelPromotion[promotion_name],0)) -> 0.2226 | G95: =E95-F95 -> -0.1361 | H95: =INDEX(tblModelPromotion[aov_lift_pct],MATCH(A95,tblModelPromotion[promotion_name],0)) -> 0.0205 | I95: =IF(AND(G95>=$L$1,H95>=$L$2),"Continue - efficient lift for margin cost",IF(AND(G95<=$L$3,H95<$L$2),"Discontinue - high margin cost, weak lift","Review - mixed signal")) -> Continue - efficient lift for margin cost
A96: =INDEX(tblModelPromotion[promotion_name],MATCH("Clearance Dec2022 - 15% Off",tblModelPromotion[promotion_name],0)) -> Clearance Dec2022 - 15% Off | B96: =INDEX(tblModelPromotion[promotion_type],MATCH(A96,tblModelPromotion[promotion_name],0)) -> Clearance | C96: =INDEX(tblModelPromotion[discount_pct],MATCH(A96,tblModelPromotion[promotion_name],0))/100 -> 0.15 | D96: =INDEX(tblModelPromotion[revenue],MATCH(A96,tblModelPromotion[promotion_name],0)) -> 65974319 | E96: =INDEX(tblModelPromotion[margin_pct],MATCH(A96,tblModelPromotion[promotion_name],0)) -> 0.0864 | F96: =INDEX(tblModelPromotion[baseline_margin_pct],MATCH(A96,tblModelPromotion[promotion_name],0)) -> 0.2226 | G96: =E96-F96 -> -0.1362 | H96: =INDEX(tblModelPromotion[aov_lift_pct],MATCH(A96,tblModelPromotion[promotion_name],0)) -> -0.0331 | I96: =IF(AND(G96>=$L$1,H96>=$L$2),"Continue - efficient lift for margin cost",IF(AND(G96<=$L$3,H96<$L$2),"Discontinue - high margin cost, weak lift","Review - mixed signal")) -> Review - mixed signal
A97: =INDEX(tblModelPromotion[promotion_name],MATCH("Seasonal Dec2023 - 15% Off",tblModelPromotion[promotion_name],0)) -> Seasonal Dec2023 - 15% Off | B97: =INDEX(tblModelPromotion[promotion_type],MATCH(A97,tblModelPromotion[promotion_name],0)) -> Seasonal | C97: =INDEX(tblModelPromotion[discount_pct],MATCH(A97,tblModelPromotion[promotion_name],0))/100 -> 0.15 | D97: =INDEX(tblModelPromotion[revenue],MATCH(A97,tblModelPromotion[promotion_name],0)) -> 171291786 | E97: =INDEX(tblModelPromotion[margin_pct],MATCH(A97,tblModelPromotion[promotion_name],0)) -> 0.0862 | F97: =INDEX(tblModelPromotion[baseline_margin_pct],MATCH(A97,tblModelPromotion[promotion_name],0)) -> 0.2226 | G97: =E97-F97 -> -0.1364 | H97: =INDEX(tblModelPromotion[aov_lift_pct],MATCH(A97,tblModelPromotion[promotion_name],0)) -> 0.0442 | I97: =IF(AND(G97>=$L$1,H97>=$L$2),"Continue - efficient lift for margin cost",IF(AND(G97<=$L$3,H97<$L$2),"Discontinue - high margin cost, weak lift","Review - mixed signal")) -> Continue - efficient lift for margin cost
A98: =INDEX(tblModelPromotion[promotion_name],MATCH("Seasonal Apr2023 - 15% Off",tblModelPromotion[promotion_name],0)) -> Seasonal Apr2023 - 15% Off | B98: =INDEX(tblModelPromotion[promotion_type],MATCH(A98,tblModelPromotion[promotion_name],0)) -> Seasonal | C98: =INDEX(tblModelPromotion[discount_pct],MATCH(A98,tblModelPromotion[promotion_name],0))/100 -> 0.15 | D98: =INDEX(tblModelPromotion[revenue],MATCH(A98,tblModelPromotion[promotion_name],0)) -> 33861398 | E98: =INDEX(tblModelPromotion[margin_pct],MATCH(A98,tblModelPromotion[promotion_name],0)) -> 0.0853 | F98: =INDEX(tblModelPromotion[baseline_margin_pct],MATCH(A98,tblModelPromotion[promotion_name],0)) -> 0.2226 | G98: =E98-F98 -> -0.1373 | H98: =INDEX(tblModelPromotion[aov_lift_pct],MATCH(A98,tblModelPromotion[promotion_name],0)) -> 0.0169 | I98: =IF(AND(G98>=$L$1,H98>=$L$2),"Continue - efficient lift for margin cost",IF(AND(G98<=$L$3,H98<$L$2),"Discontinue - high margin cost, weak lift","Review - mixed signal")) -> Continue - efficient lift for margin cost
A99: =INDEX(tblModelPromotion[promotion_name],MATCH("Festive Sep2024 - 15% Off",tblModelPromotion[promotion_name],0)) -> Festive Sep2024 - 15% Off | B99: =INDEX(tblModelPromotion[promotion_type],MATCH(A99,tblModelPromotion[promotion_name],0)) -> Festive | C99: =INDEX(tblModelPromotion[discount_pct],MATCH(A99,tblModelPromotion[promotion_name],0))/100 -> 0.15 | D99: =INDEX(tblModelPromotion[revenue],MATCH(A99,tblModelPromotion[promotion_name],0)) -> 58258851 | E99: =INDEX(tblModelPromotion[margin_pct],MATCH(A99,tblModelPromotion[promotion_name],0)) -> 0.0849 | F99: =INDEX(tblModelPromotion[baseline_margin_pct],MATCH(A99,tblModelPromotion[promotion_name],0)) -> 0.2226 | G99: =E99-F99 -> -0.1377 | H99: =INDEX(tblModelPromotion[aov_lift_pct],MATCH(A99,tblModelPromotion[promotion_name],0)) -> -0.004 | I99: =IF(AND(G99>=$L$1,H99>=$L$2),"Continue - efficient lift for margin cost",IF(AND(G99<=$L$3,H99<$L$2),"Discontinue - high margin cost, weak lift","Review - mixed signal")) -> Review - mixed signal
A100: =INDEX(tblModelPromotion[promotion_name],MATCH("Festive Apr2021 - 15% Off",tblModelPromotion[promotion_name],0)) -> Festive Apr2021 - 15% Off | B100: =INDEX(tblModelPromotion[promotion_type],MATCH(A100,tblModelPromotion[promotion_name],0)) -> Festive | C100: =INDEX(tblModelPromotion[discount_pct],MATCH(A100,tblModelPromotion[promotion_name],0))/100 -> 0.15 | D100: =INDEX(tblModelPromotion[revenue],MATCH(A100,tblModelPromotion[promotion_name],0)) -> 32163471 | E100: =INDEX(tblModelPromotion[margin_pct],MATCH(A100,tblModelPromotion[promotion_name],0)) -> 0.0847 | F100: =INDEX(tblModelPromotion[baseline_margin_pct],MATCH(A100,tblModelPromotion[promotion_name],0)) -> 0.2226 | G100: =E100-F100 -> -0.1379 | H100: =INDEX(tblModelPromotion[aov_lift_pct],MATCH(A100,tblModelPromotion[promotion_name],0)) -> 0.0543 | I100: =IF(AND(G100>=$L$1,H100>=$L$2),"Continue - efficient lift for margin cost",IF(AND(G100<=$L$3,H100<$L$2),"Discontinue - high margin cost, weak lift","Review - mixed signal")) -> Continue - efficient lift for margin cost
...

Sheet 09_KPI_StoreScore
A1: Q9 — Store Performance Score (Transparent, Margin-Weighted, Auditable)
A2: Compares each store's last 6 months (Jul-Dec 2024) vs prior 6 months (Jan-Jun 2024). No store-level target used - not present in source data. Every weight below is editable; the whole score recomputes live.
A4: Scoring Weights (editable inputs)
A5: Metric | B5: Weight | C5: Direction | D5: Business Justification
A6: Gross Margin % | B6: 0.3 | C6: Higher better | D6: Core problem is margin, not sales - highest weight
A7: Margin Trend (last6 vs prior6) | B7: 0.25 | C7: Higher better | D7: Direction matters more than a snapshot - early warning signal
A8: Return Rate % | B8: 0.2 | C8: Lower better | D8: Direct, provable Rs margin leak via refunds
A9: Discount Leakage % | B9: 0.15 | C9: Lower better | D9: Real signal but overlaps with margin % itself - weighted lower to avoid double-counting
A10: Revenue Growth % | B10: 0.1 | C10: Higher better | D10: Lowest weight deliberately - this is a margin diagnostic, not a sales diagnostic
A11: Weights Sum Check | B11: =SUM(B6:B10) -> 1
A14: Store | B14: Region | C14: Margin % (Last6) | D14: Margin Trend (pp) | E14: Return Rate % | F14: Discount Leak % | G14: Revenue Growth % | H14: Norm: Margin | I14: Norm: Trend | J14: Norm: Return | K14: Norm: Discount | L14: Norm: Growth | M14: Weighted Score | N14: Rank | O14: Priority Flag
A15: =INDEX(tblModelStoreScore[store_name],MATCH(82,tblModelStoreScore[store_id],0)) -> Nova Retail - Ahmedabad Flagship | B15: =INDEX(tblModelStoreScore[region_name],MATCH(82,tblModelStoreScore[store_id],0)) -> Gujarat | C15: =INDEX(tblModelStoreScore[margin_pct_last6],MATCH(82,tblModelStoreScore[store_id],0)) -> 0.18 | D15: =INDEX(tblModelStoreScore[margin_trend_pp],MATCH(82,tblModelStoreScore[store_id],0)) -> 0.04 | E15: =INDEX(tblModelStoreScore[return_rate_last6],MATCH(82,tblModelStoreScore[store_id],0)) -> 0.0343 | F15: =INDEX(tblModelStoreScore[discount_leak_pct_last6],MATCH(82,tblModelStoreScore[store_id],0)) -> 0.055 | G15: =INDEX(tblModelStoreScore[revenue_growth_pct],MATCH(82,tblModelStoreScore[store_id],0)) -> 0.4894 | H15: =(C15-MIN($C$15:$C$134))/(MAX($C$15:$C$134)-MIN($C$15:$C$134))*100 -> 60.410557 | I15: =(D15-MIN($D$15:$D$134))/(MAX($D$15:$D$134)-MIN($D$15:$D$134))*100 -> 37.5 | J15: =(MAX($E$15:$E$134)-E15)/(MAX($E$15:$E$134)-MIN($E$15:$E$134))*100 -> 62.869198 | K15: =(MAX($F$15:$F$134)-F15)/(MAX($F$15:$F$134)-MIN($F$15:$F$134))*100 -> 66.666667 | L15: =(G15-MIN($G$15:$G$134))/(MAX($G$15:$G$134)-MIN($G$15:$G$134))*100 -> 53.437645 | M15: =H15*wMarginWeight+I15*wTrendWeight+J15*wReturnWeight+K15*wDiscountWeight+L15*wGrowthWeight -> 55.415771 | N15: =RANK(M15,$M$15:$M$134,0) -> 30 | O15: =IF(M15<=QUARTILE($M$15:$M$134,1),"Priority Intervention","")
A16: =INDEX(tblModelStoreScore[store_name],MATCH(42,tblModelStoreScore[store_id],0)) -> Nova Retail - Ahmedabad Standard | B16: =INDEX(tblModelStoreScore[region_name],MATCH(42,tblModelStoreScore[store_id],0)) -> Gujarat | C16: =INDEX(tblModelStoreScore[margin_pct_last6],MATCH(42,tblModelStoreScore[store_id],0)) -> 0.1845 | D16: =INDEX(tblModelStoreScore[margin_trend_pp],MATCH(42,tblModelStoreScore[store_id],0)) -> 0.06 | E16: =INDEX(tblModelStoreScore[return_rate_last6],MATCH(42,tblModelStoreScore[store_id],0)) -> 0.0342 | F16: =INDEX(tblModelStoreScore[discount_leak_pct_last6],MATCH(42,tblModelStoreScore[store_id],0)) -> 0.0571 | G16: =INDEX(tblModelStoreScore[revenue_growth_pct],MATCH(42,tblModelStoreScore[store_id],0)) -> 0.3723 | H16: =(C16-MIN($C$15:$C$134))/(MAX($C$15:$C$134)-MIN($C$15:$C$134))*100 -> 73.607038 | I16: =(D16-MIN($D$15:$D$134))/(MAX($D$15:$D$134)-MIN($D$15:$D$134))*100 -> 62.5 | J16: =(MAX($E$15:$E$134)-E16)/(MAX($E$15:$E$134)-MIN($E$15:$E$134))*100 -> 63.080169 | K16: =(MAX($F$15:$F$134)-F16)/(MAX($F$15:$F$134)-MIN($F$15:$F$134))*100 -> 60.632184 | L16: =(G16-MIN($G$15:$G$134))/(MAX($G$15:$G$134)-MIN($G$15:$G$134))*100 -> 44.411901 | M16: =H16*wMarginWeight+I16*wTrendWeight+J16*wReturnWeight+K16*wDiscountWeight+L16*wGrowthWeight -> 63.859163 | N16: =RANK(M16,$M$15:$M$134,0) -> 12 | O16: =IF(M16<=QUARTILE($M$15:$M$134,1),"Priority Intervention","")
A17: =INDEX(tblModelStoreScore[store_name],MATCH(33,tblModelStoreScore[store_id],0)) -> Nova Retail - Amritsar Compact | B17: =INDEX(tblModelStoreScore[region_name],MATCH(33,tblModelStoreScore[store_id],0)) -> Punjab-Haryana | C17: =INDEX(tblModelStoreScore[margin_pct_last6],MATCH(33,tblModelStoreScore[store_id],0)) -> 0.1916 | D17: =INDEX(tblModelStoreScore[margin_trend_pp],MATCH(33,tblModelStoreScore[store_id],0)) -> 0.07 | E17: =INDEX(tblModelStoreScore[return_rate_last6],MATCH(33,tblModelStoreScore[store_id],0)) -> 0.0484 | F17: =INDEX(tblModelStoreScore[discount_leak_pct_last6],MATCH(33,tblModelStoreScore[store_id],0)) -> 0.0542 | G17: =INDEX(tblModelStoreScore[revenue_growth_pct],MATCH(33,tblModelStoreScore[store_id],0)) -> 0.2608 | H17: =(C17-MIN($C$15:$C$134))/(MAX($C$15:$C$134)-MIN($C$15:$C$134))*100 -> 94.428152 | I17: =(D17-MIN($D$15:$D$134))/(MAX($D$15:$D$134)-MIN($D$15:$D$134))*100 -> 75 | J17: =(MAX($E$15:$E$134)-E17)/(MAX($E$15:$E$134)-MIN($E$15:$E$134))*100 -> 33.122363 | K17: =(MAX($F$15:$F$134)-F17)/(MAX($F$15:$F$134)-MIN($F$15:$F$134))*100 -> 68.965517 | L17: =(G17-MIN($G$15:$G$134))/(MAX($G$15:$G$134)-MIN($G$15:$G$134))*100 -> 35.817789 | M17: =H17*wMarginWeight+I17*wTrendWeight+J17*wReturnWeight+K17*wDiscountWeight+L17*wGrowthWeight -> 67.629525 | N17: =RANK(M17,$M$15:$M$134,0) -> 7 | O17: =IF(M17<=QUARTILE($M$15:$M$134,1),"Priority Intervention","")
A18: =INDEX(tblModelStoreScore[store_name],MATCH(105,tblModelStoreScore[store_id],0)) -> Nova Retail - Amritsar Compact | B18: =INDEX(tblModelStoreScore[region_name],MATCH(105,tblModelStoreScore[store_id],0)) -> Punjab-Haryana | C18: =INDEX(tblModelStoreScore[margin_pct_last6],MATCH(105,tblModelStoreScore[store_id],0)) -> 0.1884 | D18: =INDEX(tblModelStoreScore[margin_trend_pp],MATCH(105,tblModelStoreScore[store_id],0)) -> 0.05 | E18: =INDEX(tblModelStoreScore[return_rate_last6],MATCH(105,tblModelStoreScore[store_id],0)) -> 0.0248 | F18: =INDEX(tblModelStoreScore[discount_leak_pct_last6],MATCH(105,tblModelStoreScore[store_id],0)) -> 0.0458 | G18: =INDEX(tblModelStoreScore[revenue_growth_pct],MATCH(105,tblModelStoreScore[store_id],0)) -> 0.2688 | H18: =(C18-MIN($C$15:$C$134))/(MAX($C$15:$C$134)-MIN($C$15:$C$134))*100 -> 85.043988 | I18: =(D18-MIN($D$15:$D$134))/(MAX($D$15:$D$134)-MIN($D$15:$D$134))*100 -> 50 | J18: =(MAX($E$15:$E$134)-E18)/(MAX($E$15:$E$134)-MIN($E$15:$E$134))*100 -> 82.911392 | K18: =(MAX($F$15:$F$134)-F18)/(MAX($F$15:$F$134)-MIN($F$15:$F$134))*100 -> 93.103448 | L18: =(G18-MIN($G$15:$G$134))/(MAX($G$15:$G$134)-MIN($G$15:$G$134))*100 -> 36.434407 | M18: =H18*wMarginWeight+I18*wTrendWeight+J18*wReturnWeight+K18*wDiscountWeight+L18*wGrowthWeight -> 72.204433 | N18: =RANK(M18,$M$15:$M$134,0) -> 3 | O18: =IF(M18<=QUARTILE($M$15:$M$134,1),"Priority Intervention","")
A19: =INDEX(tblModelStoreScore[store_name],MATCH(3,tblModelStoreScore[store_id],0)) -> Nova Retail - Amritsar Flagship | B19: =INDEX(tblModelStoreScore[region_name],MATCH(3,tblModelStoreScore[store_id],0)) -> Punjab-Haryana | C19: =INDEX(tblModelStoreScore[margin_pct_last6],MATCH(3,tblModelStoreScore[store_id],0)) -> 0.1808 | D19: =INDEX(tblModelStoreScore[margin_trend_pp],MATCH(3,tblModelStoreScore[store_id],0)) -> 0.04 | E19: =INDEX(tblModelStoreScore[return_rate_last6],MATCH(3,tblModelStoreScore[store_id],0)) -> 0.0345 | F19: =INDEX(tblModelStoreScore[discount_leak_pct_last6],MATCH(3,tblModelStoreScore[store_id],0)) -> 0.0593 | G19: =INDEX(tblModelStoreScore[revenue_growth_pct],MATCH(3,tblModelStoreScore[store_id],0)) -> 0.3123 | H19: =(C19-MIN($C$15:$C$134))/(MAX($C$15:$C$134)-MIN($C$15:$C$134))*100 -> 62.756598 | I19: =(D19-MIN($D$15:$D$134))/(MAX($D$15:$D$134)-MIN($D$15:$D$134))*100 -> 37.5 | J19: =(MAX($E$15:$E$134)-E19)/(MAX($E$15:$E$134)-MIN($E$15:$E$134))*100 -> 62.447257 | K19: =(MAX($F$15:$F$134)-F19)/(MAX($F$15:$F$134)-MIN($F$15:$F$134))*100 -> 54.310345 | L19: =(G19-MIN($G$15:$G$134))/(MAX($G$15:$G$134)-MIN($G$15:$G$134))*100 -> 39.787267 | M19: =H19*wMarginWeight+I19*wTrendWeight+J19*wReturnWeight+K19*wDiscountWeight+L19*wGrowthWeight -> 52.816709 | N19: =RANK(M19,$M$15:$M$134,0) -> 37 | O19: =IF(M19<=QUARTILE($M$15:$M$134,1),"Priority Intervention","")
A20: =INDEX(tblModelStoreScore[store_name],MATCH(60,tblModelStoreScore[store_id],0)) -> Nova Retail - Amritsar Standard | B20: =INDEX(tblModelStoreScore[region_name],MATCH(60,tblModelStoreScore[store_id],0)) -> Punjab-Haryana | C20: =INDEX(tblModelStoreScore[margin_pct_last6],MATCH(60,tblModelStoreScore[store_id],0)) -> 0.1808 | D20: =INDEX(tblModelStoreScore[margin_trend_pp],MATCH(60,tblModelStoreScore[store_id],0)) -> 0.01 | E20: =INDEX(tblModelStoreScore[return_rate_last6],MATCH(60,tblModelStoreScore[store_id],0)) -> 0.0333 | F20: =INDEX(tblModelStoreScore[discount_leak_pct_last6],MATCH(60,tblModelStoreScore[store_id],0)) -> 0.0577 | G20: =INDEX(tblModelStoreScore[revenue_growth_pct],MATCH(60,tblModelStoreScore[store_id],0)) -> 0.1336 | H20: =(C20-MIN($C$15:$C$134))/(MAX($C$15:$C$134)-MIN($C$15:$C$134))*100 -> 62.756598 | I20: =(D20-MIN($D$15:$D$134))/(MAX($D$15:$D$134)-MIN($D$15:$D$134))*100 -> 0 | J20: =(MAX($E$15:$E$134)-E20)/(MAX($E$15:$E$134)-MIN($E$15:$E$134))*100 -> 64.978903 | K20: =(MAX($F$15:$F$134)-F20)/(MAX($F$15:$F$134)-MIN($F$15:$F$134))*100 -> 58.908046 | L20: =(G20-MIN($G$15:$G$134))/(MAX($G$15:$G$134)-MIN($G$15:$G$134))*100 -> 26.013566 | M20: =H20*wMarginWeight+I20*wTrendWeight+J20*wReturnWeight+K20*wDiscountWeight+L20*wGrowthWeight -> 43.260324 | N20: =RANK(M20,$M$15:$M$134,0) -> 83 | O20: =IF(M20<=QUARTILE($M$15:$M$134,1),"Priority Intervention","")
A21: =INDEX(tblModelStoreScore[store_name],MATCH(72,tblModelStoreScore[store_id],0)) -> Nova Retail - Amritsar Standard | B21: =INDEX(tblModelStoreScore[region_name],MATCH(72,tblModelStoreScore[store_id],0)) -> Punjab-Haryana | C21: =INDEX(tblModelStoreScore[margin_pct_last6],MATCH(72,tblModelStoreScore[store_id],0)) -> 0.1799 | D21: =INDEX(tblModelStoreScore[margin_trend_pp],MATCH(72,tblModelStoreScore[store_id],0)) -> 0.06 | E21: =INDEX(tblModelStoreScore[return_rate_last6],MATCH(72,tblModelStoreScore[store_id],0)) -> 0.036 | F21: =INDEX(tblModelStoreScore[discount_leak_pct_last6],MATCH(72,tblModelStoreScore[store_id],0)) -> 0.0598 | G21: =INDEX(tblModelStoreScore[revenue_growth_pct],MATCH(72,tblModelStoreScore[store_id],0)) -> 0.4591 | H21: =(C21-MIN($C$15:$C$134))/(MAX($C$15:$C$134)-MIN($C$15:$C$134))*100 -> 60.117302 | I21: =(D21-MIN($D$15:$D$134))/(MAX($D$15:$D$134)-MIN($D$15:$D$134))*100 -> 62.5 | J21: =(MAX($E$15:$E$134)-E21)/(MAX($E$15:$E$134)-MIN($E$15:$E$134))*100 -> 59.2827 | K21: =(MAX($F$15:$F$134)-F21)/(MAX($F$15:$F$134)-MIN($F$15:$F$134))*100 -> 52.873563 | L21: =(G21-MIN($G$15:$G$134))/(MAX($G$15:$G$134)-MIN($G$15:$G$134))*100 -> 51.102204 | M21: =H21*wMarginWeight+I21*wTrendWeight+J21*wReturnWeight+K21*wDiscountWeight+L21*wGrowthWeight -> 58.557986 | N21: =RANK(M21,$M$15:$M$134,0) -> 23 | O21: =IF(M21<=QUARTILE($M$15:$M$134,1),"Priority Intervention","")
A22: =INDEX(tblModelStoreScore[store_name],MATCH(7,tblModelStoreScore[store_id],0)) -> Nova Retail - Bengaluru Compact | B22: =INDEX(tblModelStoreScore[region_name],MATCH(7,tblModelStoreScore[store_id],0)) -> Karnataka | C22: =INDEX(tblModelStoreScore[margin_pct_last6],MATCH(7,tblModelStoreScore[store_id],0)) -> 0.1843 | D22: =INDEX(tblModelStoreScore[margin_trend_pp],MATCH(7,tblModelStoreScore[store_id],0)) -> 0.04 | E22: =INDEX(tblModelStoreScore[return_rate_last6],MATCH(7,tblModelStoreScore[store_id],0)) -> 0.0266 | F22: =INDEX(tblModelStoreScore[discount_leak_pct_last6],MATCH(7,tblModelStoreScore[store_id],0)) -> 0.0519 | G22: =INDEX(tblModelStoreScore[revenue_growth_pct],MATCH(7,tblModelStoreScore[store_id],0)) -> 0.3015 | H22: =(C22-MIN($C$15:$C$134))/(MAX($C$15:$C$134)-MIN($C$15:$C$134))*100 -> 73.020528 | I22: =(D22-MIN($D$15:$D$134))/(MAX($D$15:$D$134)-MIN($D$15:$D$134))*100 -> 37.5 | J22: =(MAX($E$15:$E$134)-E22)/(MAX($E$15:$E$134)-MIN($E$15:$E$134))*100 -> 79.113924 | K22: =(MAX($F$15:$F$134)-F22)/(MAX($F$15:$F$134)-MIN($F$15:$F$134))*100 -> 75.574713 | L22: =(G22-MIN($G$15:$G$134))/(MAX($G$15:$G$134)-MIN($G$15:$G$134))*100 -> 38.954833 | M22: =H22*wMarginWeight+I22*wTrendWeight+J22*wReturnWeight+K22*wDiscountWeight+L22*wGrowthWeight -> 62.335633 | N22: =RANK(M22,$M$15:$M$134,0) -> 14 | O22: =IF(M22<=QUARTILE($M$15:$M$134,1),"Priority Intervention","")
A23: =INDEX(tblModelStoreScore[store_name],MATCH(68,tblModelStoreScore[store_id],0)) -> Nova Retail - Bengaluru Standard | B23: =INDEX(tblModelStoreScore[region_name],MATCH(68,tblModelStoreScore[store_id],0)) -> Karnataka | C23: =INDEX(tblModelStoreScore[margin_pct_last6],MATCH(68,tblModelStoreScore[store_id],0)) -> 0.1738 | D23: =INDEX(tblModelStoreScore[margin_trend_pp],MATCH(68,tblModelStoreScore[store_id],0)) -> 0.03 | E23: =INDEX(tblModelStoreScore[return_rate_last6],MATCH(68,tblModelStoreScore[store_id],0)) -> 0.0305 | F23: =INDEX(tblModelStoreScore[discount_leak_pct_last6],MATCH(68,tblModelStoreScore[store_id],0)) -> 0.0606 | G23: =INDEX(tblModelStoreScore[revenue_growth_pct],MATCH(68,tblModelStoreScore[store_id],0)) -> 0.3647 | H23: =(C23-MIN($C$15:$C$134))/(MAX($C$15:$C$134)-MIN($C$15:$C$134))*100 -> 42.228739 | I23: =(D23-MIN($D$15:$D$134))/(MAX($D$15:$D$134)-MIN($D$15:$D$134))*100 -> 25 | J23: =(MAX($E$15:$E$134)-E23)/(MAX($E$15:$E$134)-MIN($E$15:$E$134))*100 -> 70.886076 | K23: =(MAX($F$15:$F$134)-F23)/(MAX($F$15:$F$134)-MIN($F$15:$F$134))*100 -> 50.574713 | L23: =(G23-MIN($G$15:$G$134))/(MAX($G$15:$G$134)-MIN($G$15:$G$134))*100 -> 43.826114 | M23: =H23*wMarginWeight+I23*wTrendWeight+J23*wReturnWeight+K23*wDiscountWeight+L23*wGrowthWeight -> 45.064655 | N23: =RANK(M23,$M$15:$M$134,0) -> 71 | O23: =IF(M23<=QUARTILE($M$15:$M$134,1),"Priority Intervention","")
A24: =INDEX(tblModelStoreScore[store_name],MATCH(98,tblModelStoreScore[store_id],0)) -> Nova Retail - Bengaluru Standard | B24: =INDEX(tblModelStoreScore[region_name],MATCH(98,tblModelStoreScore[store_id],0)) -> Karnataka | C24: =INDEX(tblModelStoreScore[margin_pct_last6],MATCH(98,tblModelStoreScore[store_id],0)) -> 0.1771 | D24: =INDEX(tblModelStoreScore[margin_trend_pp],MATCH(98,tblModelStoreScore[store_id],0)) -> 0.04 | E24: =INDEX(tblModelStoreScore[return_rate_last6],MATCH(98,tblModelStoreScore[store_id],0)) -> 0.0385 | F24: =INDEX(tblModelStoreScore[discount_leak_pct_last6],MATCH(98,tblModelStoreScore[store_id],0)) -> 0.0588 | G24: =INDEX(tblModelStoreScore[revenue_growth_pct],MATCH(98,tblModelStoreScore[store_id],0)) -> 0.2996 | H24: =(C24-MIN($C$15:$C$134))/(MAX($C$15:$C$134)-MIN($C$15:$C$134))*100 -> 51.906158 | I24: =(D24-MIN($D$15:$D$134))/(MAX($D$15:$D$134)-MIN($D$15:$D$134))*100 -> 37.5 | J24: =(MAX($E$15:$E$134)-E24)/(MAX($E$15:$E$134)-MIN($E$15:$E$134))*100 -> 54.008439 | K24: =(MAX($F$15:$F$134)-F24)/(MAX($F$15:$F$134)-MIN($F$15:$F$134))*100 -> 55.747126 | L24: =(G24-MIN($G$15:$G$134))/(MAX($G$15:$G$134)-MIN($G$15:$G$134))*100 -> 38.808386 | M24: =H24*wMarginWeight+I24*wTrendWeight+J24*wReturnWeight+K24*wDiscountWeight+L24*wGrowthWeight -> 47.991443 | N24: =RANK(M24,$M$15:$M$134,0) -> 60 | O24: =IF(M24<=QUARTILE($M$15:$M$134,1),"Priority Intervention","")
A25: =INDEX(tblModelStoreScore[store_name],MATCH(90,tblModelStoreScore[store_id],0)) -> Nova Retail - Bhopal Standard | B25: =INDEX(tblModelStoreScore[region_name],MATCH(90,tblModelStoreScore[store_id],0)) -> Madhya Pradesh | C25: =INDEX(tblModelStoreScore[margin_pct_last6],MATCH(90,tblModelStoreScore[store_id],0)) -> 0.1766 | D25: =INDEX(tblModelStoreScore[margin_trend_pp],MATCH(90,tblModelStoreScore[store_id],0)) -> 0.03 | E25: =INDEX(tblModelStoreScore[return_rate_last6],MATCH(90,tblModelStoreScore[store_id],0)) -> 0.0226 | F25: =INDEX(tblModelStoreScore[discount_leak_pct_last6],MATCH(90,tblModelStoreScore[store_id],0)) -> 0.0537 | G25: =INDEX(tblModelStoreScore[revenue_growth_pct],MATCH(90,tblModelStoreScore[store_id],0)) -> 0.9059 | H25: =(C25-MIN($C$15:$C$134))/(MAX($C$15:$C$134)-MIN($C$15:$C$134))*100 -> 50.439883 | I25: =(D25-MIN($D$15:$D$134))/(MAX($D$15:$D$134)-MIN($D$15:$D$134))*100 -> 25 | J25: =(MAX($E$15:$E$134)-E25)/(MAX($E$15:$E$134)-MIN($E$15:$E$134))*100 -> 87.552743 | K25: =(MAX($F$15:$F$134)-F25)/(MAX($F$15:$F$134)-MIN($F$15:$F$134))*100 -> 70.402299 | L25: =(G25-MIN($G$15:$G$134))/(MAX($G$15:$G$134)-MIN($G$15:$G$134))*100 -> 85.540311 | M25: =H25*wMarginWeight+I25*wTrendWeight+J25*wReturnWeight+K25*wDiscountWeight+L25*wGrowthWeight -> 58.006889 | N25: =RANK(M25,$M$15:$M$134,0) -> 24 | O25: =IF(M25<=QUARTILE($M$15:$M$134,1),"Priority Intervention","")
A26: =INDEX(tblModelStoreScore[store_name],MATCH(20,tblModelStoreScore[store_id],0)) -> Nova Retail - Bhubaneswar Standard | B26: =INDEX(tblModelStoreScore[region_name],MATCH(20,tblModelStoreScore[store_id],0)) -> Odisha-Jharkhand | C26: =INDEX(tblModelStoreScore[margin_pct_last6],MATCH(20,tblModelStoreScore[store_id],0)) -> 0.174 | D26: =INDEX(tblModelStoreScore[margin_trend_pp],MATCH(20,tblModelStoreScore[store_id],0)) -> 0.04 | E26: =INDEX(tblModelStoreScore[return_rate_last6],MATCH(20,tblModelStoreScore[store_id],0)) -> 0.0349 | F26: =INDEX(tblModelStoreScore[discount_leak_pct_last6],MATCH(20,tblModelStoreScore[store_id],0)) -> 0.0602 | G26: =INDEX(tblModelStoreScore[revenue_growth_pct],MATCH(20,tblModelStoreScore[store_id],0)) -> 0.5221 | H26: =(C26-MIN($C$15:$C$134))/(MAX($C$15:$C$134)-MIN($C$15:$C$134))*100 -> 42.815249 | I26: =(D26-MIN($D$15:$D$134))/(MAX($D$15:$D$134)-MIN($D$15:$D$134))*100 -> 37.5 | J26: =(MAX($E$15:$E$134)-E26)/(MAX($E$15:$E$134)-MIN($E$15:$E$134))*100 -> 61.603376 | K26: =(MAX($F$15:$F$134)-F26)/(MAX($F$15:$F$134)-MIN($F$15:$F$134))*100 -> 51.724138 | L26: =(G26-MIN($G$15:$G$134))/(MAX($G$15:$G$134)-MIN($G$15:$G$134))*100 -> 55.95807 | M26: =H26*wMarginWeight+I26*wTrendWeight+J26*wReturnWeight+K26*wDiscountWeight+L26*wGrowthWeight -> 47.894678 | N26: =RANK(M26,$M$15:$M$134,0) -> 61 | O26: =IF(M26<=QUARTILE($M$15:$M$134,1),"Priority Intervention","")
A27: =INDEX(tblModelStoreScore[store_name],MATCH(83,tblModelStoreScore[store_id],0)) -> Nova Retail - Chandigarh Compact | B27: =INDEX(tblModelStoreScore[region_name],MATCH(83,tblModelStoreScore[store_id],0)) -> Punjab-Haryana | C27: =INDEX(tblModelStoreScore[margin_pct_last6],MATCH(83,tblModelStoreScore[store_id],0)) -> 0.1877 | D27: =INDEX(tblModelStoreScore[margin_trend_pp],MATCH(83,tblModelStoreScore[store_id],0)) -> 0.07 | E27: =INDEX(tblModelStoreScore[return_rate_last6],MATCH(83,tblModelStoreScore[store_id],0)) -> 0.0425 | F27: =INDEX(tblModelStoreScore[discount_leak_pct_last6],MATCH(83,tblModelStoreScore[store_id],0)) -> 0.0489 | G27: =INDEX(tblModelStoreScore[revenue_growth_pct],MATCH(83,tblModelStoreScore[store_id],0)) -> 0.1981 | H27: =(C27-MIN($C$15:$C$134))/(MAX($C$15:$C$134)-MIN($C$15:$C$134))*100 -> 82.991202 | I27: =(D27-MIN($D$15:$D$134))/(MAX($D$15:$D$134)-MIN($D$15:$D$134))*100 -> 75 | J27: =(MAX($E$15:$E$134)-E27)/(MAX($E$15:$E$134)-MIN($E$15:$E$134))*100 -> 45.56962 | K27: =(MAX($F$15:$F$134)-F27)/(MAX($F$15:$F$134)-MIN($F$15:$F$134))*100 -> 84.195402 | L27: =(G27-MIN($G$15:$G$134))/(MAX($G$15:$G$134)-MIN($G$15:$G$134))*100 -> 30.985047 | M27: =H27*wMarginWeight+I27*wTrendWeight+J27*wReturnWeight+K27*wDiscountWeight+L27*wGrowthWeight -> 68.4891 | N27: =RANK(M27,$M$15:$M$134,0) -> 5 | O27: =IF(M27<=QUARTILE($M$15:$M$134,1),"Priority Intervention","")
A28: =INDEX(tblModelStoreScore[store_name],MATCH(11,tblModelStoreScore[store_id],0)) -> Nova Retail - Chandigarh Standard | B28: =INDEX(tblModelStoreScore[region_name],MATCH(11,tblModelStoreScore[store_id],0)) -> Punjab-Haryana | C28: =INDEX(tblModelStoreScore[margin_pct_last6],MATCH(11,tblModelStoreScore[store_id],0)) -> 0.1704 | D28: =INDEX(tblModelStoreScore[margin_trend_pp],MATCH(11,tblModelStoreScore[store_id],0)) -> 0.04 | E28: =INDEX(tblModelStoreScore[return_rate_last6],MATCH(11,tblModelStoreScore[store_id],0)) -> 0.0341 | F28: =INDEX(tblModelStoreScore[discount_leak_pct_last6],MATCH(11,tblModelStoreScore[store_id],0)) -> 0.0611 | G28: =INDEX(tblModelStoreScore[revenue_growth_pct],MATCH(11,tblModelStoreScore[store_id],0)) -> 0.0955 | H28: =(C28-MIN($C$15:$C$134))/(MAX($C$15:$C$134)-MIN($C$15:$C$134))*100 -> 32.258065 | I28: =(D28-MIN($D$15:$D$134))/(MAX($D$15:$D$134)-MIN($D$15:$D$134))*100 -> 37.5 | J28: =(MAX($E$15:$E$134)-E28)/(MAX($E$15:$E$134)-MIN($E$15:$E$134))*100 -> 63.291139 | K28: =(MAX($F$15:$F$134)-F28)/(MAX($F$15:$F$134)-MIN($F$15:$F$134))*100 -> 49.137931 | L28: =(G28-MIN($G$15:$G$134))/(MAX($G$15:$G$134)-MIN($G$15:$G$134))*100 -> 23.076923 | M28: =H28*wMarginWeight+I28*wTrendWeight+J28*wReturnWeight+K28*wDiscountWeight+L28*wGrowthWeight -> 41.389029 | N28: =RANK(M28,$M$15:$M$134,0) -> 91 | O28: =IF(M28<=QUARTILE($M$15:$M$134,1),"Priority Intervention","") -> Priority Intervention
A29: =INDEX(tblModelStoreScore[store_name],MATCH(65,tblModelStoreScore[store_id],0)) -> Nova Retail - Chandigarh Standard | B29: =INDEX(tblModelStoreScore[region_name],MATCH(65,tblModelStoreScore[store_id],0)) -> Punjab-Haryana | C29: =INDEX(tblModelStoreScore[margin_pct_last6],MATCH(65,tblModelStoreScore[store_id],0)) -> 0.1765 | D29: =INDEX(tblModelStoreScore[margin_trend_pp],MATCH(65,tblModelStoreScore[store_id],0)) -> 0.03 | E29: =INDEX(tblModelStoreScore[return_rate_last6],MATCH(65,tblModelStoreScore[store_id],0)) -> 0.0362 | F29: =INDEX(tblModelStoreScore[discount_leak_pct_last6],MATCH(65,tblModelStoreScore[store_id],0)) -> 0.0512 | G29: =INDEX(tblModelStoreScore[revenue_growth_pct],MATCH(65,tblModelStoreScore[store_id],0)) -> 0.3388 | H29: =(C29-MIN($C$15:$C$134))/(MAX($C$15:$C$134)-MIN($C$15:$C$134))*100 -> 50.146628 | I29: =(D29-MIN($D$15:$D$134))/(MAX($D$15:$D$134)-MIN($D$15:$D$134))*100 -> 25 | J29: =(MAX($E$15:$E$134)-E29)/(MAX($E$15:$E$134)-MIN($E$15:$E$134))*100 -> 58.860759 | K29: =(MAX($F$15:$F$134)-F29)/(MAX($F$15:$F$134)-MIN($F$15:$F$134))*100 -> 77.586207 | L29: =(G29-MIN($G$15:$G$134))/(MAX($G$15:$G$134)-MIN($G$15:$G$134))*100 -> 41.829813 | M29: =H29*wMarginWeight+I29*wTrendWeight+J29*wReturnWeight+K29*wDiscountWeight+L29*wGrowthWeight -> 48.887053 | N29: =RANK(M29,$M$15:$M$134,0) -> 56 | O29: =IF(M29<=QUARTILE($M$15:$M$134,1),"Priority Intervention","")
A30: =INDEX(tblModelStoreScore[store_name],MATCH(89,tblModelStoreScore[store_id],0)) -> Nova Retail - Chandigarh Standard | B30: =INDEX(tblModelStoreScore[region_name],MATCH(89,tblModelStoreScore[store_id],0)) -> Punjab-Haryana | C30: =INDEX(tblModelStoreScore[margin_pct_last6],MATCH(89,tblModelStoreScore[store_id],0)) -> 0.1659 | D30: =INDEX(tblModelStoreScore[margin_trend_pp],MATCH(89,tblModelStoreScore[store_id],0)) -> 0.03 | E30: =INDEX(tblModelStoreScore[return_rate_last6],MATCH(89,tblModelStoreScore[store_id],0)) -> 0.0364 | F30: =INDEX(tblModelStoreScore[discount_leak_pct_last6],MATCH(89,tblModelStoreScore[store_id],0)) -> 0.0686 | G30: =INDEX(tblModelStoreScore[revenue_growth_pct],MATCH(89,tblModelStoreScore[store_id],0)) -> 0.1956 | H30: =(C30-MIN($C$15:$C$134))/(MAX($C$15:$C$134)-MIN($C$15:$C$134))*100 -> 19.061584 | I30: =(D30-MIN($D$15:$D$134))/(MAX($D$15:$D$134)-MIN($D$15:$D$134))*100 -> 25 | J30: =(MAX($E$15:$E$134)-E30)/(MAX($E$15:$E$134)-MIN($E$15:$E$134))*100 -> 58.438819 | K30: =(MAX($F$15:$F$134)-F30)/(MAX($F$15:$F$134)-MIN($F$15:$F$134))*100 -> 27.586207 | L30: =(G30-MIN($G$15:$G$134))/(MAX($G$15:$G$134)-MIN($G$15:$G$134))*100 -> 30.792354 | M30: =H30*wMarginWeight+I30*wTrendWeight+J30*wReturnWeight+K30*wDiscountWeight+L30*wGrowthWeight -> 30.873405 | N30: =RANK(M30,$M$15:$M$134,0) -> 117 | O30: =IF(M30<=QUARTILE($M$15:$M$134,1),"Priority Intervention","") -> Priority Intervention
A31: =INDEX(tblModelStoreScore[store_name],MATCH(103,tblModelStoreScore[store_id],0)) -> Nova Retail - Chandigarh Standard | B31: =INDEX(tblModelStoreScore[region_name],MATCH(103,tblModelStoreScore[store_id],0)) -> Punjab-Haryana | C31: =INDEX(tblModelStoreScore[margin_pct_last6],MATCH(103,tblModelStoreScore[store_id],0)) -> 0.1747 | D31: =INDEX(tblModelStoreScore[margin_trend_pp],MATCH(103,tblModelStoreScore[store_id],0)) -> 0.03 | E31: =INDEX(tblModelStoreScore[return_rate_last6],MATCH(103,tblModelStoreScore[store_id],0)) -> 0.0303 | F31: =INDEX(tblModelStoreScore[discount_leak_pct_last6],MATCH(103,tblModelStoreScore[store_id],0)) -> 0.064 | G31: =INDEX(tblModelStoreScore[revenue_growth_pct],MATCH(103,tblModelStoreScore[store_id],0)) -> 0.3018 | H31: =(C31-MIN($C$15:$C$134))/(MAX($C$15:$C$134)-MIN($C$15:$C$134))*100 -> 44.868035 | I31: =(D31-MIN($D$15:$D$134))/(MAX($D$15:$D$134)-MIN($D$15:$D$134))*100 -> 25 | J31: =(MAX($E$15:$E$134)-E31)/(MAX($E$15:$E$134)-MIN($E$15:$E$134))*100 -> 71.308017 | K31: =(MAX($F$15:$F$134)-F31)/(MAX($F$15:$F$134)-MIN($F$15:$F$134))*100 -> 40.804598 | L31: =(G31-MIN($G$15:$G$134))/(MAX($G$15:$G$134)-MIN($G$15:$G$134))*100 -> 38.977956 | M31: =H31*wMarginWeight+I31*wTrendWeight+J31*wReturnWeight+K31*wDiscountWeight+L31*wGrowthWeight -> 43.990499 | N31: =RANK(M31,$M$15:$M$134,0) -> 80 | O31: =IF(M31<=QUARTILE($M$15:$M$134,1),"Priority Intervention","")
A32: =INDEX(tblModelStoreScore[store_name],MATCH(114,tblModelStoreScore[store_id],0)) -> Nova Retail - Chandigarh Standard | B32: =INDEX(tblModelStoreScore[region_name],MATCH(114,tblModelStoreScore[store_id],0)) -> Punjab-Haryana | C32: =INDEX(tblModelStoreScore[margin_pct_last6],MATCH(114,tblModelStoreScore[store_id],0)) -> 0.1755 | D32: =INDEX(tblModelStoreScore[margin_trend_pp],MATCH(114,tblModelStoreScore[store_id],0)) -> 0.04 | E32: =INDEX(tblModelStoreScore[return_rate_last6],MATCH(114,tblModelStoreScore[store_id],0)) -> 0.0452 | F32: =INDEX(tblModelStoreScore[discount_leak_pct_last6],MATCH(114,tblModelStoreScore[store_id],0)) -> 0.0564 | G32: =INDEX(tblModelStoreScore[revenue_growth_pct],MATCH(114,tblModelStoreScore[store_id],0)) -> 0.2946 | H32: =(C32-MIN($C$15:$C$134))/(MAX($C$15:$C$134)-MIN($C$15:$C$134))*100 -> 47.214076 | I32: =(D32-MIN($D$15:$D$134))/(MAX($D$15:$D$134)-MIN($D$15:$D$134))*100 -> 37.5 | J32: =(MAX($E$15:$E$134)-E32)/(MAX($E$15:$E$134)-MIN($E$15:$E$134))*100 -> 39.873418 | K32: =(MAX($F$15:$F$134)-F32)/(MAX($F$15:$F$134)-MIN($F$15:$F$134))*100 -> 62.643678 | L32: =(G32-MIN($G$15:$G$134))/(MAX($G$15:$G$134)-MIN($G$15:$G$134))*100 -> 38.423 | M32: =H32*wMarginWeight+I32*wTrendWeight+J32*wReturnWeight+K32*wDiscountWeight+L32*wGrowthWeight -> 44.752758 | N32: =RANK(M32,$M$15:$M$134,0) -> 74 | O32: =IF(M32<=QUARTILE($M$15:$M$134,1),"Priority Intervention","")
